Workbook
Name ColumnTitle..P44: #REF!
Name ColumnTitle..P44: #REF!
Name dd: #REF!
Name dd: #REF!
Name de: #REF!
Name de: #REF!
Name means: #REF!
Name means: #REF!
Name Numbers: #REF!
Name Numbers: #REF!
Name SASOutput: #REF!
Name SASOutput: #REF!
Name Table1: #REF!
Name Table1: #REF!
Name Table1a: '1 Prov territorial profile'!$A$10:$D$49
Name Table1b: '1 Prov territorial profile'!$A$50:$D$56
Name Table1b: '1 Prov territorial profile'!$A$50:$D$56
Name Table2: '2 Supply'!$A$11:$G$21
Name Table3: '3 Inflow and outflow'!$A$10:$E$20
Name Table3: #REF!
Name Table3: #REF!
Name Table4: '4 Workforce'!$A$11:$G$21
Name Table5a: '5 Direct care'!$A$11:$C$16
Name Table5b: '5 Direct care'!$A$18:$C$23
Name Table6: '6 New graduate migrations'!$A$10:$D$23
Name Table7a: '7 Hospital Staffing indicators'!$A$11:$H$16
Name Table7b: '7 Hospital Staffing indicators'!$A$18:$H$23
Name Table7c: '7 Hospital Staffing indicators'!$A$25:$H$30
Name Table7d: '7 Hospital Staffing indicators'!$A$32:$H$37
Name Table7e: '7 Hospital Staffing indicators'!$A$39:$H$44
Name Table7f: '7 Hospital Staffing indicators'!$A$46:$H$51
Name Table7g: '7 Hospital Staffing indicators'!$A$53:$H$58
Name Table8a: '8 Vacancy metrics'!$A$11:$D$20
Name Table8b: '8 Vacancy metrics'!$A$35:$C$43
Name TABLEX: #REF!
Name TABLEX: #REF!
Name tablexy: #REF!
Name tablexy: #REF!
Name Title..AE156: #REF!
Name Title..AE156: #REF!
Name Title..AE177: #REF!
Name Title..AE177: #REF!
Name Title..AF143: #REF!
Name Title..AF143: #REF!
Name Title..AL116: #REF!
Name Title..AL116: #REF!
Name Title..BI156: #REF!
Name Title..BI156: #REF!
Name Title..BI183: #REF!
Name Title..BI183: #REF!
Name Title..BJ143: #REF!
Name Title..BJ143: #REF!
Name Title..D33: #REF!
Name Title..D33: #REF!
Name Title..D55: #REF!
Name Title..D62: #REF!
Name Title..E24: #REF!
Name Title..E44: #REF!
Name Title..E44: #REF!
Name Title..E74: #REF!

Sheet Instructions
A1: This workbook has 15 worksheets, including this title page, a table of contents on tab 2, figures and data tables on tabs 3 to 10, notes and terminology on tabs 11 to 14, and contact information on tab 15. Notes and sources can be found after the data tables in column A.
A2: Instructions The following Unicode symbols are used in this workbook (these symbols may need to be enabled if using screen reading software): em dash (—) asterisk (*) dagger (†) caret (^) Instructions are provided in each tab where there are interactive drop-down lists on how to operate them.
A3: Health Workforce in Canada, 2023 — Quick Stats (Updated June 2025)
A4: The collection and reporting of health workforce data assists decision-makers in the planning and distribution of health care professionals.
A5: Health Workforce in Canada, 2023 — Quick Stats contains data on the supply, workforce, inflow/outflow and provincial and territorial trends of Canada’s health workforce in the Quick Stats tool. The file currently contains information on physicians, regulated nurses, physiotherapists, occupational therapists and pharmacists.
A6: This Quick Stats file provides 8 interactive data tables to facilitate research and analysis, including by profession; by demographic, education and employment data elements, including vacancies; and by selected hospital staffing indicators.
A7: Unless otherwise indicated, this product uses data from the following CIHI databases: Health Workforce Database, with data provided by provincial and territorial regulatory bodies; Scott’s Medical Database, with raw data provided by iMD (© 2023 iMD Health Global Corp.); and Canadian MIS Database, with data provided by provincial ministries and departments of health; or from Statistics Canada’s Job Vacancy and Wage Survey.
A8: Additional resources
A9: The following health workforce products are available on CIHI’s website:
A10: • The state of the health workforce in Canada, 2023 (digital report)
A11: • Nursing in Canada, 2023 (data tables, methodology notes)
A12: • Occupational Therapists in Canada, 2023 (data tables, methodology notes)
... A22: End of worksheet (go to Table of contents)

Sheet Table of contents
A1: Table of contents
A2: Table 1 Provincial/territorial profile of providers, by selected type, place of work, province/territory and data year (with figures)
A3: Table 2 Supply of providers, by selected type and province/territory, 2014 to 2023 (with figures)
A4: Table 3 Inflow and outflow of providers, by selected type and province/territory, 2014 to 2023 (with figure)
A5: Table 4 Workforce of providers, by selected type and province/territory, 2014 to 2023 (with figures)
A6: Tables 5a and 5b Providers working in direct care by selected type and province/territory, 2019 to 2023 (with figures)
A7: Table 6 Migration of recent health professional graduates: Province/territory in 2023, by selected province/territory of graduation (with figure)
A8: Tables 7a to 7g Selected Hospital Staffing indicators, by hospital service area and province/territory, 2019–2020 to 2023–2024 (with figures)
A9: Tables 8a and 8b Vacancy metrics, by National Occupation Code (NOC) occupation and province/territory, 2015 to 2023 (with figures)
A10: Notes to readers
A11: Terminology
A12: Notes on selected Hospital Staffing indicators
... A15: End of worksheet

Sheet 1 Prov territorial profile
A1: This tab provides the provincial or territorial profile for different types of providers for a given place of work and year. The figures and table will populate information based on your selections. Select the type of provider in cell A6. Select the province or territory in cell B6. Select the place of work in cell C6. Select the year in cell D6. The table begins at cell A10 and ends at D56. The notes and sources begin in cell A57 and end in cell A99. There are 8 figures in cell A8: Sex, Age Group, Country of Graduation, Geographic Designation, Employment Status, Position, Area of Responsibility and Place of Work. A link back to the Table of contents is in cell A2 and A100.
A2: Back to the Table of contents
A3: =IF(A6="All Physicians",CONCATENATE("Provincial/territorial profile for ",LOWER(A6)," ","in"," ",B6,", ",D6),IF(A6="Family medicine physicians",CONCATENATE("Provincial/territorial profile for ",LOWER(A6)," in"," ",B6,", ",D6),IF(A6="Specialists",CONCATENATE("Provincial/territorial profile for ","specialist"," physicians in"," ",B6,", ",D6),CONCATENATE("Provincial/territorial profile for ",LOWER(A6)," workforce in ",B6,", ",LOWER(C6),", ",D6)))) -> Provincial/territorial profile for registered nurses workforce in Ontario, all places of work, 2023
A4: Instructions: Select a provider, jurisdiction, place of work and year from the drop-down lists in cells A6, B6, C6 and D6.
A5: Type of provider | B5: Province/territory | C5: Place of work* | D5: Year
A6: Registered nurses | B6: Ontario | C6: All places of work | D6: 2023
A7: Data will change in the figures and table below based on your selections above. Hover over the chart area to show values and categories. When a figure does not populate, it indicates that data for the selection is unavailable, does not exist or is not applicable.
A8: The information can be found in the table below.
A9: =CONCATENATE("Table 1 "," ",A3) -> Table 1 Provincial/territorial profile for registered nurses workforce in Ontario, all places of work, 2023
A10: Data element | B10: Category | C10: Count | D10: Percentage
A11: Sex | B11: Female | C11: =IF(A6="Family medicine physicians",IFERROR(VLOOKUP(CONCATENATE($D$6,$A$6,$B$6),Phyprofile!A3:AU464,6,FALSE),"—"),IF(A6="Specialists",IFERROR(VLOOKUP(CONCATENATE($D$6,$A$6,$B$6),Phyprofile!A3:AU464,6,FALSE),"—"),IF(A6="All physicians",IFERROR(VLOOKUP(CONCATENATE($D$6,$A$6,$B$6),Phyprofile!A3:AU464,6,FALSE),"—"),IF(A6="Occupational therapists",IFERROR(VLOOKUP(CONCATENATE($D$6,$A$6,$B$6,$C$6),OTProfileData!$A$2:$AR$1920,6,FALSE),"—"),IF(A6="Physiotherapists",IFERROR(VLOOKUP(CONCATENATE($D$6,$A$6,$B$6,$C$6),PTProfileData!$A$2:$BV$1802,6,FALSE),"—"),IF(A6="Pharmacists",IFERROR(VLOOKUP(CONCATENATE($D$6,$A$6,$B$6,$C$6),PHProfileData!$A$3:$AO$1868,6,FALSE),"—"),IF(A6="nurse practitioners",IFERROR(VLOOKUP(CONCATENATE($D$6,$A$6,$B$6,$C$6),NursProfileData!$A$2:$AN$2066,6,FALSE),"—"),IF(A6="Registered nurses",IFERROR(VLOOKUP(CONCATENATE($D$6,$A$6,$B$6,$C$6),NursProfileData!$A$2:$AN$2066,6,FALSE),"—"),IF(A6="Registered psychiatric nurses",IFERROR(VLOOKUP(CONCATENATE($D$6,$A$6,$B$6,$C$6),NursProfileData!$A$2:$AN$2066,6,FALSE),"—"),IF(A6="Licensed practical nurses",IFERROR(VLOOKUP(CONCATENATE($D$6,$A$6,$B$6,$C$6),NursProfileData!$A$2:$AN$2066,6,FALSE),"—"),"-")))))))))) -> 92239 | D11: =IF(A6="Family medicine physicians",IFERROR(VLOOKUP(CONCATENATE($D$6,$A$6,$B$6),Phyprofile!$A$2:$AU$464,27,FALSE),"—"),IF(A6="Specialists",IFERROR(VLOOKUP(CONCATENATE($D$6,$A$6,$B$6),Phyprofile!$A$2:$AU$464,27,FALSE),"—"),IF(A6="All physicians",IFERROR(VLOOKUP(CONCATENATE($D$6,$A$6,$B$6),Phyprofile!$A$2:$AU$464,27,FALSE),"—"),IF(A6="Occupational therapists",IFERROR(VLOOKUP(CONCATENATE($D$6,$A$6,$B$6,$C$6),OTProfileData!$A$2:$CB$1920,42,FALSE),"—"),IF(A6="Physiotherapists",IFERROR(VLOOKUP(CONCATENATE($D$6,$A$6,$B$6,$C$6),PTProfileData!$A$2:$BW$1802,39,FALSE),"—"),IF(A6="Pharmacists",IFERROR(VLOOKUP(CONCATENATE($D$6,$A$6,$B$6,$C$6),PHProfileData!$A$3:$BR$1868,37,FALSE),"—"),IF(A6="nurse practitioners",IFERROR(VLOOKUP(CONCATENATE($D$6,$A$6,$B$6,$C$6),NursProfileData!$A$2:$BZ$2066,41,FALSE),"—"),IF(A6="Registered nurses",IFERROR(VLOOKUP(CONCATENATE($D$6,$A$6,$B$6,$C$6),NursProfileData!$A$2:$BZ$2066,41,FALSE),"—"),IF(A6="Registered psychiatric nurses",IFERROR(VLOOKUP(CONCATENATE($D$6,$A$6,$B$6,$C$6),NursProfileData!$A$2:$BZ$2066,41,FALSE),"—"),IF(A6="Licensed practical nurses",IFERROR(VLOOKUP(CONCATENATE($D$6,$A$6,$B$6,$C$6),NursProfileData!$A$2:$BZ$2066,41,FALSE),"—"),"-")))))))))) -> 0.90787311
B12: Male | C12: =IF(A6="Family medicine physicians",IFERROR(VLOOKUP(CONCATENATE($D$6,$A$6,$B$6),Phyprofile!A3:AU464,7,FALSE),"—"),IF(A6="Specialists",IFERROR(VLOOKUP(CONCATENATE($D$6,$A$6,$B$6),Phyprofile!A3:AU464,7,FALSE),"—"),IF(A6="All physicians",IFERROR(VLOOKUP(CONCATENATE($D$6,$A$6,$B$6),Phyprofile!A3:AU464,7,FALSE),"—"),IF(A6="Occupational therapists",IFERROR(VLOOKUP(CONCATENATE($D$6,$A$6,$B$6,$C$6),OTProfileData!$A$2:$AR$1920,7,FALSE),"—"),IF(A6="Physiotherapists",IFERROR(VLOOKUP(CONCATENATE($D$6,$A$6,$B$6,$C$6),PTProfileData!$A$2:$BW$1802,7,FALSE),"—"),IF(A6="Pharmacists",IFERROR(VLOOKUP(CONCATENATE($D$6,$A$6,$B$6,$C$6),PHProfileData!$A$3:$AO$1868,7,FALSE),"—"),IF(A6="nurse practitioners",IFERROR(VLOOKUP(CONCATENATE($D$6,$A$6,$B$6,$C$6),NursProfileData!$A$2:$AN$2066,7,FALSE),"—"),IF(A6="Registered nurses",IFERROR(VLOOKUP(CONCATENATE($D$6,$A$6,$B$6,$C$6),NursProfileData!$A$2:$AN$2066,7,FALSE),"—"),IF(A6="Registered psychiatric nurses",IFERROR(VLOOKUP(CONCATENATE($D$6,$A$6,$B$6,$C$6),NursProfileData!$A$2:$AN$2066,7,FALSE),"—"),IF(A6="Licensed practical nurses",IFERROR(VLOOKUP(CONCATENATE($D$6,$A$6,$B$6,$C$6),NursProfileData!$A$2:$AN$2066,7,FALSE),"—"),"-")))))))))) -> 9304 | D12: =IF(A6="Family medicine physicians",IFERROR(VLOOKUP(CONCATENATE($D$6,$A$6,$B$6),Phyprofile!A3:AU464,28,FALSE),"—"),IF(A6="Specialists",IFERROR(VLOOKUP(CONCATENATE($D$6,$A$6,$B$6),Phyprofile!A3:AU464,28,FALSE),"—"),IF(A6="All physicians",IFERROR(VLOOKUP(CONCATENATE($D$6,$A$6,$B$6),Phyprofile!A3:AU464,28,FALSE),"—"),IF(A6="Occupational therapists",IFERROR(VLOOKUP(CONCATENATE($D$6,$A$6,$B$6,$C$6),OTProfileData!$A$2:$CB$1920,43,FALSE),"—"),IF(A6="Physiotherapists",IFERROR(VLOOKUP(CONCATENATE($D$6,$A$6,$B$6,$C$6),PTProfileData!$A$2:$BW$1802,40,FALSE),"—"),IF(A6="Pharmacists",IFERROR(VLOOKUP(CONCATENATE($D$6,$A$6,$B$6,$C$6),PHProfileData!$A$3:$BR$1868,38,FALSE),"—"),IF(A6="nurse practitioners",IFERROR(VLOOKUP(CONCATENATE($D$6,$A$6,$B$6,$C$6),NursProfileData!$A$2:$BZ$2066,42,FALSE),"—"),IF(A6="Registered nurses",IFERROR(VLOOKUP(CONCATENATE($D$6,$A$6,$B$6,$C$6),NursProfileData!$A$2:$BZ$2066,42,FALSE),"—"),IF(A6="Registered psychiatric nurses",IFERROR(VLOOKUP(CONCATENATE($D$6,$A$6,$B$6,$C$6),NursProfileData!$A$2:$BZ$2066,42,FALSE),"—"),IF(A6="Licensed practical nurses",IFERROR(VLOOKUP(CONCATENATE($D$6,$A$6,$B$6,$C$6),NursProfileData!$A$2:$BZ$2066,42,FALSE),"—"),"-")))))))))) -> 0.091575704
B13: Not stated | C13: =IF(A6="Family medicine physicians",IFERROR(VLOOKUP(CONCATENATE($D$6,$A$6,$B$6),Phyprofile!A3:AU464,8,FALSE),"—"),IF(A6="Specialists",IFERROR(VLOOKUP(CONCATENATE($D$6,$A$6,$B$6),Phyprofile!A3:AU464,8,FALSE),"—"),IF(A6="All physicians",IFERROR(VLOOKUP(CONCATENATE($D$6,$A$6,$B$6),Phyprofile!A3:AU464,8,FALSE),"—"),IF(A6="Occupational therapists",IFERROR(VLOOKUP(CONCATENATE($D$6,$A$6,$B$6,$C$6),OTProfileData!$A$2:$AR$1920,8,FALSE),"—"),IF(A6="Physiotherapists",IFERROR(VLOOKUP(CONCATENATE($D$6,$A$6,$B$6,$C$6),PTProfileData!$A$2:$BW$1802,8,FALSE),"—"),IF(A6="Pharmacists",IFERROR(VLOOKUP(CONCATENATE($D$6,$A$6,$B$6,$C$6),PHProfileData!$A$3:$AO$1868,8,FALSE),"—"),IF(A6="nurse practitioners",IFERROR(VLOOKUP(CONCATENATE($D$6,$A$6,$B$6,$C$6),NursProfileData!$A$2:$AN$2066,8,FALSE),"—"),IF(A6="Registered nurses",IFERROR(VLOOKUP(CONCATENATE($D$6,$A$6,$B$6,$C$6),NursProfileData!$A$2:$AN$2066,8,FALSE),"—"),IF(A6="Registered psychiatric nurses",IFERROR(VLOOKUP(CONCATENATE($D$6,$A$6,$B$6,$C$6),NursProfileData!$A$2:$AN$2066,8,FALSE),"—"),IF(A6="Licensed practical nurses",IFERROR(VLOOKUP(CONCATENATE($D$6,$A$6,$B$6,$C$6),NursProfileData!$A$2:$AN$243,8,FALSE),"—"),"-")))))))))) -> 56 | D13: =IF(A6="Family medicine physicians",IFERROR(VLOOKUP(CONCATENATE($D$6,$A$6,$B$6),Phyprofile!A3:AU464,29,FALSE),"—"),IF(A6="Specialists",IFERROR(VLOOKUP(CONCATENATE($D$6,$A$6,$B$6),Phyprofile!A3:AU464,29,FALSE),"—"),IF(A6="All physicians",IFERROR(VLOOKUP(CONCATENATE($D$6,$A$6,$B$6),Phyprofile!A3:AU464,29,FALSE),"—"),IF(A6="Occupational therapists",IFERROR(VLOOKUP(CONCATENATE($D$6,$A$6,$B$6,$C$6),OTProfileData!$A$2:$CB$1920,44,FALSE),"—"),IF(A6="Physiotherapists",IFERROR(VLOOKUP(CONCATENATE($D$6,$A$6,$B$6,$C$6),PTProfileData!$A$2:$BW$1802,41,FALSE),"—"),IF(A6="Pharmacists",IFERROR(VLOOKUP(CONCATENATE($D$6,$A$6,$B$6,$C$6),PHProfileData!$A$3:$BR$1868,39,FALSE),"—"),IF(A6="nurse practitioners",IFERROR(VLOOKUP(CONCATENATE($D$6,$A$6,$B$6,$C$6),NursProfileData!$A$2:$BZ$2066,43,FALSE),"—"),IF(A6="Registered nurses",IFERROR(VLOOKUP(CONCATENATE($D$6,$A$6,$B$6,$C$6),NursProfileData!$A$2:$BZ$2066,43,FALSE),"—"),IF(A6="Registered psychiatric nurses",IFERROR(VLOOKUP(CONCATENATE($D$6,$A$6,$B$6,$C$6),NursProfileData!$A$2:$BZ$2066,43,FALSE),"—"),IF(A6="Licensed practical nurses",IFERROR(VLOOKUP(CONCATENATE($D$6,$A$6,$B$6,$C$6),NursProfileData!$A$2:$BZ$2066,43,FALSE),"—"),"-")))))))))) -> 0.00055118653
A14: Age Group | B14: <25 | C14: =IF(A6="Family medicine physicians",IFERROR(VLOOKUP(CONCATENATE($D$6,$A$6,$B$6),Phyprofile!A3:AU464,19,FALSE),"—"),IF(A6="Specialists",IFERROR(VLOOKUP(CONCATENATE($D$6,$A$6,$B$6),Phyprofile!A3:AU464,19,FALSE),"—"),IF(A6="All physicians",IFERROR(VLOOKUP(CONCATENATE($D$6,$A$6,$B$6),Phyprofile!A3:AU464,19,FALSE),"—"),IF(A6="Occupational therapists",IFERROR(VLOOKUP(CONCATENATE($D$6,$A$6,$B$6,$C$6),OTProfileData!$A$2:$AR$1920,19,FALSE),"—"),IF(A6="Physiotherapists",IFERROR(VLOOKUP(CONCATENATE($D$6,$A$6,$B$6,$C$6),PTProfileData!$A$2:$BW$1802,19,FALSE),"—"),IF(A6="Pharmacists",IFERROR(VLOOKUP(CONCATENATE($D$6,$A$6,$B$6,$C$6),PHProfileData!$A$3:$AO$1868,19,FALSE),"—"),IF(A6="nurse practitioners",IFERROR(VLOOKUP(CONCATENATE($D$6,$A$6,$B$6,$C$6),NursProfileData!$A$2:$BZ$2066,19,FALSE),"—"),IF(A6="Registered nurses",IFERROR(VLOOKUP(CONCATENATE($D$6,$A$6,$B$6,$C$6),NursProfileData!$A$2:$BZ$2066,19,FALSE),"—"),IF(A6="Registered psychiatric nurses",IFERROR(VLOOKUP(CONCATENATE($D$6,$A$6,$B$6,$C$6),NursProfileData!$A$2:$BZ$2066,19,FALSE),"—"),IF(A6="Licensed practical nurses",IFERROR(VLOOKUP(CONCATENATE($D$6,$A$6,$B$6,$C$6),NursProfileData!$A$2:$BZ$2066,19,FALSE),"—"),"-")))))))))) -> 2751 | D14: =IF(A6="Family medicine physicians",IFERROR(VLOOKUP(CONCATENATE($D$6,$A$6,$B$6),Phyprofile!A3:AU464,40,FALSE),"—"),IF(A6="Specialists",IFERROR(VLOOKUP(CONCATENATE($D$6,$A$6,$B$6),Phyprofile!A3:AU464,40,FALSE),"—"),IF(A6="All physicians",IFERROR(VLOOKUP(CONCATENATE($D$6,$A$6,$B$6),Phyprofile!A3:AU464,40,FALSE),"—"),IF(A6="Occupational therapists",IFERROR(VLOOKUP(CONCATENATE($D$6,$A$6,$B$6,$C$6),OTProfileData!$A$2:$CB$1920,55,FALSE),"—"),IF(A6="Physiotherapists",IFERROR(VLOOKUP(CONCATENATE($D$6,$A$6,$B$6,$C$6),PTProfileData!$A$2:$BW$1802,52,FALSE),"—"),IF(A6="Pharmacists",IFERROR(VLOOKUP(CONCATENATE($D$6,$A$6,$B$6,$C$6),PHProfileData!$A$3:$BR$1868,50,FALSE),"—"),IF(A6="nurse practitioners",IFERROR(VLOOKUP(CONCATENATE($D$6,$A$6,$B$6,$C$6),NursProfileData!$A$2:$BZ$2066,54,FALSE),"—"),IF(A6="Registered nurses",IFERROR(VLOOKUP(CONCATENATE($D$6,$A$6,$B$6,$C$6),NursProfileData!$A$2:$BZ$2066,54,FALSE),"—"),IF(A6="Registered psychiatric nurses",IFERROR(VLOOKUP(CONCATENATE($D$6,$A$6,$B$6,$C$6),NursProfileData!$A$2:$BZ$2066,54,FALSE),"—"),IF(A6="Licensed practical nurses",IFERROR(VLOOKUP(CONCATENATE($D$6,$A$6,$B$6,$C$6),NursProfileData!$A$2:$BZ$2066,54,FALSE),"—"),"-")))))))))) -> 0.017992303
B15: 25–29 | C15: =IF(A6="Family medicine physicians",IFERROR(VLOOKUP(CONCATENATE($D$6,$A$6,$B$6),Phyprofile!A3:AU464,9,FALSE),"—"),IF(A6="Specialists",IFERROR(VLOOKUP(CONCATENATE($D$6,$A$6,$B$6),Phyprofile!A3:AU464,9,FALSE),"—"),IF(A6="All physicians",IFERROR(VLOOKUP(CONCATENATE($D$6,$A$6,$B$6),Phyprofile!A3:AU464,9,FALSE),"—"),IF(A6="Occupational therapists",IFERROR(VLOOKUP(CONCATENATE($D$6,$A$6,$B$6,$C$6),OTProfileData!$A$2:$AR$1920,9,FALSE),"—"),IF(A6="Physiotherapists",IFERROR(VLOOKUP(CONCATENATE($D$6,$A$6,$B$6,$C$6),PTProfileData!$A$2:$BW$1802,9,FALSE),"—"),IF(A6="Pharmacists",IFERROR(VLOOKUP(CONCATENATE($D$6,$A$6,$B$6,$C$6),PHProfileData!$A$3:$AO$1868,9,FALSE),"—"),IF(A6="nurse practitioners",IFERROR(VLOOKUP(CONCATENATE($D$6,$A$6,$B$6,$C$6),NursProfileData!$A$2:$BZ$2066,9,FALSE),"—"),IF(A6="Registered nurses",IFERROR(VLOOKUP(CONCATENATE($D$6,$A$6,$B$6,$C$6),NursProfileData!$A$2:$BZ$2066,9,FALSE),"—"),IF(A6="Registered psychiatric nurses",IFERROR(VLOOKUP(CONCATENATE($D$6,$A$6,$B$6,$C$6),NursProfileData!$A$2:$BZ$2066,9,FALSE),"—"),IF(A6="Licensed practical nurses",IFERROR(VLOOKUP(CONCATENATE($D$6,$A$6,$B$6,$C$6),NursProfileData!$A$2:$BZ$2066,9,FALSE),"—"),"-")))))))))) -> 12945 | D15: =IF(A6="Family medicine physicians",IFERROR(VLOOKUP(CONCATENATE($D$6,$A$6,$B$6),Phyprofile!A3:AU464,30,FALSE),"—"),IF(A6="Specialists",IFERROR(VLOOKUP(CONCATENATE($D$6,$A$6,$B$6),Phyprofile!A3:AU464,30,FALSE),"—"),IF(A6="All physicians",IFERROR(VLOOKUP(CONCATENATE($D$6,$A$6,$B$6),Phyprofile!A3:AU464,30,FALSE),"—"),IF(A6="Occupational therapists",IFERROR(VLOOKUP(CONCATENATE($D$6,$A$6,$B$6,$C$6),OTProfileData!$A$2:$CB$1920,45,FALSE),"—"),IF(A6="Physiotherapists",IFERROR(VLOOKUP(CONCATENATE($D$6,$A$6,$B$6,$C$6),PTProfileData!$A$2:$BW$1802,42,FALSE),"—"),IF(A6="Pharmacists",IFERROR(VLOOKUP(CONCATENATE($D$6,$A$6,$B$6,$C$6),PHProfileData!$A$3:$BR$1868,40,FALSE),"—"),IF(A6="nurse practitioners",IFERROR(VLOOKUP(CONCATENATE($D$6,$A$6,$B$6,$C$6),NursProfileData!$A$2:$BZ$2066,44,FALSE),"—"),IF(A6="Registered nurses",IFERROR(VLOOKUP(CONCATENATE($D$6,$A$6,$B$6,$C$6),NursProfileData!$A$2:$BZ$2066,44,FALSE),"—"),IF(A6="Registered psychiatric nurses",IFERROR(VLOOKUP(CONCATENATE($D$6,$A$6,$B$6,$C$6),NursProfileData!$A$2:$BZ$2066,44,FALSE),"—"),IF(A6="Licensed practical nurses",IFERROR(VLOOKUP(CONCATENATE($D$6,$A$6,$B$6,$C$6),NursProfileData!$A$2:$BZ$2066,44,FALSE),"—"),"-")))))))))) -> 0.12741267
B16: 30–34 | C16: =IF(A6="Family medicine physicians",IFERROR(VLOOKUP(CONCATENATE($D$6,$A$6,$B$6),Phyprofile!A3:AU464,10,FALSE),"—"),IF(A6="Specialists",IFERROR(VLOOKUP(CONCATENATE($D$6,$A$6,$B$6),Phyprofile!A3:AU464,10,FALSE),"—"),IF(A6="All physicians",IFERROR(VLOOKUP(CONCATENATE($D$6,$A$6,$B$6),Phyprofile!A3:AU464,10,FALSE),"—"),IF(A6="Occupational therapists",IFERROR(VLOOKUP(CONCATENATE($D$6,$A$6,$B$6,$C$6),OTProfileData!$A$2:$AR$1920,10,FALSE),"—"),IF(A6="Physiotherapists",IFERROR(VLOOKUP(CONCATENATE($D$6,$A$6,$B$6,$C$6),PTProfileData!$A$2:$BW$1802,10,FALSE),"—"),IF(A6="Pharmacists",IFERROR(VLOOKUP(CONCATENATE($D$6,$A$6,$B$6,$C$6),PHProfileData!$A$3:$AO$1868,10,FALSE),"—"),IF(A6="nurse practitioners",IFERROR(VLOOKUP(CONCATENATE($D$6,$A$6,$B$6,$C$6),NursProfileData!$A$2:$BZ$2066,10,FALSE),"—"),IF(A6="Registered nurses",IFERROR(VLOOKUP(CONCATENATE($D$6,$A$6,$B$6,$C$6),NursProfileData!$A$2:$BZ$2066,10,FALSE),"—"),IF(A6="Registered psychiatric nurses",IFERROR(VLOOKUP(CONCATENATE($D$6,$A$6,$B$6,$C$6),NursProfileData!$A$2:$BZ$2066,10,FALSE),"—"),IF(A6="Licensed practical nurses",IFERROR(VLOOKUP(CONCATENATE($D$6,$A$6,$B$6,$C$6),NursProfileData!$A$2:$BZ$2066,10,FALSE),"—"),"-")))))))))) -> 15108 | D16: =IF(A6="Family medicine physicians",IFERROR(VLOOKUP(CONCATENATE($D$6,$A$6,$B$6),Phyprofile!A3:AU464,31,FALSE),"—"),IF(A6="Specialists",IFERROR(VLOOKUP(CONCATENATE($D$6,$A$6,$B$6),Phyprofile!A3:AU464,31,FALSE),"—"),IF(A6="All physicians",IFERROR(VLOOKUP(CONCATENATE($D$6,$A$6,$B$6),Phyprofile!A3:AU464,31,FALSE),"—"),IF(A6="Occupational therapists",IFERROR(VLOOKUP(CONCATENATE($D$6,$A$6,$B$6,$C$6),OTProfileData!$A$2:$CB$1920,46,FALSE),"—"),IF(A6="Physiotherapists",IFERROR(VLOOKUP(CONCATENATE($D$6,$A$6,$B$6,$C$6),PTProfileData!$A$2:$BW$1802,43,FALSE),"—"),IF(A6="Pharmacists",IFERROR(VLOOKUP(CONCATENATE($D$6,$A$6,$B$6,$C$6),PHProfileData!$A$3:$BR$1868,41,FALSE),"—"),IF(A6="nurse practitioners",IFERROR(VLOOKUP(CONCATENATE($D$6,$A$6,$B$6,$C$6),NursProfileData!$A$2:$BZ$2066,45,FALSE),"—"),IF(A6="Registered nurses",IFERROR(VLOOKUP(CONCATENATE($D$6,$A$6,$B$6,$C$6),NursProfileData!$A$2:$BZ$2066,45,FALSE),"—"),IF(A6="Registered psychiatric nurses",IFERROR(VLOOKUP(CONCATENATE($D$6,$A$6,$B$6,$C$6),NursProfileData!$A$2:$BZ$2066,45,FALSE),"—"),IF(A6="Licensed practical nurses",IFERROR(VLOOKUP(CONCATENATE($D$6,$A$6,$B$6,$C$6),NursProfileData!$A$2:$BZ$2066,45,FALSE),"—"),"-")))))))))) -> 0.14870225
B17: 35–39 | C17: =IF(A6="Family medicine physicians",IFERROR(VLOOKUP(CONCATENATE($D$6,$A$6,$B$6),Phyprofile!A3:AU464,11,FALSE),"—"),IF(A6="Specialists",IFERROR(VLOOKUP(CONCATENATE($D$6,$A$6,$B$6),Phyprofile!A3:AU464,11,FALSE),"—"),IF(A6="All physicians",IFERROR(VLOOKUP(CONCATENATE($D$6,$A$6,$B$6),Phyprofile!A3:AU464,11,FALSE),"—"),IF(A6="Occupational therapists",IFERROR(VLOOKUP(CONCATENATE($D$6,$A$6,$B$6,$C$6),OTProfileData!$A$2:$AR$1920,11,FALSE),"—"),IF(A6="Physiotherapists",IFERROR(VLOOKUP(CONCATENATE($D$6,$A$6,$B$6,$C$6),PTProfileData!$A$2:$BW$1802,11,FALSE),"—"),IF(A6="Pharmacists",IFERROR(VLOOKUP(CONCATENATE($D$6,$A$6,$B$6,$C$6),PHProfileData!$A$3:$AO$1868,11,FALSE),"—"),IF(A6="nurse practitioners",IFERROR(VLOOKUP(CONCATENATE($D$6,$A$6,$B$6,$C$6),NursProfileData!$A$2:$BZ$2066,11,FALSE),"—"),IF(A6="Registered nurses",IFERROR(VLOOKUP(CONCATENATE($D$6,$A$6,$B$6,$C$6),NursProfileData!$A$2:$BZ$2066,11,FALSE),"—"),IF(A6="Registered psychiatric nurses",IFERROR(VLOOKUP(CONCATENATE($D$6,$A$6,$B$6,$C$6),NursProfileData!$A$2:$BZ$2066,11,FALSE),"—"),IF(A6="Licensed practical nurses",IFERROR(VLOOKUP(CONCATENATE($D$6,$A$6,$B$6,$C$6),NursProfileData!$A$2:$BZ$2066,11,FALSE),"—"),"-")))))))))) -> 14168 | D17: =IF(A6="Family medicine physicians",IFERROR(VLOOKUP(CONCATENATE($D$6,$A$6,$B$6),Phyprofile!A3:AU464,32,FALSE),"—"),IF(A6="Specialists",IFERROR(VLOOKUP(CONCATENATE($D$6,$A$6,$B$6),Phyprofile!A3:AU464,32,FALSE),"—"),IF(A6="All physicians",IFERROR(VLOOKUP(CONCATENATE($D$6,$A$6,$B$6),Phyprofile!A3:AU464,32,FALSE),"—"),IF(A6="Occupational therapists",IFERROR(VLOOKUP(CONCATENATE($D$6,$A$6,$B$6,$C$6),OTProfileData!$A$2:$CB$1920,47,FALSE),"—"),IF(A6="Physiotherapists",IFERROR(VLOOKUP(CONCATENATE($D$6,$A$6,$B$6,$C$6),PTProfileData!$A$2:$BW$1802,44,FALSE),"—"),IF(A6="Pharmacists",IFERROR(VLOOKUP(CONCATENATE($D$6,$A$6,$B$6,$C$6),PHProfileData!$A$3:$BR$1868,42,FALSE),"—"),IF(A6="nurse practitioners",IFERROR(VLOOKUP(CONCATENATE($D$6,$A$6,$B$6,$C$6),NursProfileData!$A$2:$BZ$2066,46,FALSE),"—"),IF(A6="Registered nurses",IFERROR(VLOOKUP(CONCATENATE($D$6,$A$6,$B$6,$C$6),NursProfileData!$A$2:$BZ$2066,46,FALSE),"—"),IF(A6="Registered psychiatric nurses",IFERROR(VLOOKUP(CONCATENATE($D$6,$A$6,$B$6,$C$6),NursProfileData!$A$2:$BZ$2066,46,FALSE),"—"),IF(A6="Licensed practical nurses",IFERROR(VLOOKUP(CONCATENATE($D$6,$A$6,$B$6,$C$6),NursProfileData!$A$2:$BZ$2066,46,FALSE),"—"),"-")))))))))) -> 0.13945019
B18: 40–44 | C18: =IF(A6="Family medicine physicians",IFERROR(VLOOKUP(CONCATENATE($D$6,$A$6,$B$6),Phyprofile!A3:AU464,12,FALSE),"—"),IF(A6="Specialists",IFERROR(VLOOKUP(CONCATENATE($D$6,$A$6,$B$6),Phyprofile!A3:AU464,12,FALSE),"—"),IF(A6="All physicians",IFERROR(VLOOKUP(CONCATENATE($D$6,$A$6,$B$6),Phyprofile!A3:AU464,12,FALSE),"—"),IF(A6="Occupational therapists",IFERROR(VLOOKUP(CONCATENATE($D$6,$A$6,$B$6,$C$6),OTProfileData!$A$2:$AR$1920,12,FALSE),"—"),IF(A6="Physiotherapists",IFERROR(VLOOKUP(CONCATENATE($D$6,$A$6,$B$6,$C$6),PTProfileData!$A$2:$BW$1802,12,FALSE),"—"),IF(A6="Pharmacists",IFERROR(VLOOKUP(CONCATENATE($D$6,$A$6,$B$6,$C$6),PHProfileData!$A$3:$AO$1868,12,FALSE),"—"),IF(A6="nurse practitioners",IFERROR(VLOOKUP(CONCATENATE($D$6,$A$6,$B$6,$C$6),NursProfileData!$A$2:$BZ$2066,12,FALSE),"—"),IF(A6="Registered nurses",IFERROR(VLOOKUP(CONCATENATE($D$6,$A$6,$B$6,$C$6),NursProfileData!$A$2:$BZ$2066,12,FALSE),"—"),IF(A6="Registered psychiatric nurses",IFERROR(VLOOKUP(CONCATENATE($D$6,$A$6,$B$6,$C$6),NursProfileData!$A$2:$BZ$2066,12,FALSE),"—"),IF(A6="Licensed practical nurses",IFERROR(VLOOKUP(CONCATENATE($D$6,$A$6,$B$6,$C$6),NursProfileData!$A$2:$BZ$2066,12,FALSE),"—"),"-")))))))))) -> 11053 | D18: =IF(A6="Family medicine physicians",IFERROR(VLOOKUP(CONCATENATE($D$6,$A$6,$B$6),Phyprofile!A3:AU464,33,FALSE),"—"),IF(A6="Specialists",IFERROR(VLOOKUP(CONCATENATE($D$6,$A$6,$B$6),Phyprofile!A3:AU464,33,FALSE),"—"),IF(A6="All physicians",IFERROR(VLOOKUP(CONCATENATE($D$6,$A$6,$B$6),Phyprofile!A3:AU464,33,FALSE),"—"),IF(A6="Occupational therapists",IFERROR(VLOOKUP(CONCATENATE($D$6,$A$6,$B$6,$C$6),OTProfileData!$A$2:$CB$1920,48,FALSE),"—"),IF(A6="Physiotherapists",IFERROR(VLOOKUP(CONCATENATE($D$6,$A$6,$B$6,$C$6),PTProfileData!$A$2:$BW$1802,45,FALSE),"—"),IF(A6="Pharmacists",IFERROR(VLOOKUP(CONCATENATE($D$6,$A$6,$B$6,$C$6),PHProfileData!$A$3:$BR$1868,43,FALSE),"—"),IF(A6="nurse practitioners",IFERROR(VLOOKUP(CONCATENATE($D$6,$A$6,$B$6,$C$6),NursProfileData!$A$2:$BZ$2066,47,FALSE),"—"),IF(A6="Registered nurses",IFERROR(VLOOKUP(CONCATENATE($D$6,$A$6,$B$6,$C$6),NursProfileData!$A$2:$BZ$2066,47,FALSE),"—"),IF(A6="Registered psychiatric nurses",IFERROR(VLOOKUP(CONCATENATE($D$6,$A$6,$B$6,$C$6),NursProfileData!$A$2:$BZ$2066,47,FALSE),"—"),IF(A6="Licensed practical nurses",IFERROR(VLOOKUP(CONCATENATE($D$6,$A$6,$B$6,$C$6),NursProfileData!$A$2:$BZ$2066,47,FALSE),"—"),"-")))))))))) -> 0.10879044
B19: 45–49 | C19: =IF(A6="Family medicine physicians",IFERROR(VLOOKUP(CONCATENATE($D$6,$A$6,$B$6),Phyprofile!A3:AU464,13,FALSE),"—"),IF(A6="Specialists",IFERROR(VLOOKUP(CONCATENATE($D$6,$A$6,$B$6),Phyprofile!A3:AU464,13,FALSE),"—"),IF(A6="All physicians",IFERROR(VLOOKUP(CONCATENATE($D$6,$A$6,$B$6),Phyprofile!A3:AU464,13,FALSE),"—"),IF(A6="Occupational therapists",IFERROR(VLOOKUP(CONCATENATE($D$6,$A$6,$B$6,$C$6),OTProfileData!$A$2:$AR$1920,13,FALSE),"—"),IF(A6="Physiotherapists",IFERROR(VLOOKUP(CONCATENATE($D$6,$A$6,$B$6,$C$6),PTProfileData!$A$2:$BW$1802,13,FALSE),"—"),IF(A6="Pharmacists",IFERROR(VLOOKUP(CONCATENATE($D$6,$A$6,$B$6,$C$6),PHProfileData!$A$3:$AO$1868,13,FALSE),"—"),IF(A6="nurse practitioners",IFERROR(VLOOKUP(CONCATENATE($D$6,$A$6,$B$6,$C$6),NursProfileData!$A$2:$BZ$2066,13,FALSE),"—"),IF(A6="Registered nurses",IFERROR(VLOOKUP(CONCATENATE($D$6,$A$6,$B$6,$C$6),NursProfileData!$A$2:$BZ$2066,13,FALSE),"—"),IF(A6="Registered psychiatric nurses",IFERROR(VLOOKUP(CONCATENATE($D$6,$A$6,$B$6,$C$6),NursProfileData!$A$2:$BZ$2066,13,FALSE),"—"),IF(A6="Licensed practical nurses",IFERROR(VLOOKUP(CONCATENATE($D$6,$A$6,$B$6,$C$6),NursProfileData!$A$2:$BZ$2066,13,FALSE),"—"),"-")))))))))) -> 10105 | D19: =IF(A6="Family medicine physicians",IFERROR(VLOOKUP(CONCATENATE($D$6,$A$6,$B$6),Phyprofile!A3:AU464,34,FALSE),"—"),IF(A6="Specialists",IFERROR(VLOOKUP(CONCATENATE($D$6,$A$6,$B$6),Phyprofile!A3:AU464,34,FALSE),"—"),IF(A6="All physicians",IFERROR(VLOOKUP(CONCATENATE($D$6,$A$6,$B$6),Phyprofile!A3:AU464,34,FALSE),"—"),IF(A6="Occupational therapists",IFERROR(VLOOKUP(CONCATENATE($D$6,$A$6,$B$6,$C$6),OTProfileData!$A$2:$CB$1920,49,FALSE),"—"),IF(A6="Physiotherapists",IFERROR(VLOOKUP(CONCATENATE($D$6,$A$6,$B$6,$C$6),PTProfileData!$A$2:$BW$1802,46,FALSE),"—"),IF(A6="Pharmacists",IFERROR(VLOOKUP(CONCATENATE($D$6,$A$6,$B$6,$C$6),PHProfileData!$A$3:$BR$1868,44,FALSE),"—"),IF(A6="nurse practitioners",IFERROR(VLOOKUP(CONCATENATE($D$6,$A$6,$B$6,$C$6),NursProfileData!$A$2:$BZ$2066,48,FALSE),"—"),IF(A6="Registered nurses",IFERROR(VLOOKUP(CONCATENATE($D$6,$A$6,$B$6,$C$6),NursProfileData!$A$2:$BZ$2066,48,FALSE),"—"),IF(A6="Registered psychiatric nurses",IFERROR(VLOOKUP(CONCATENATE($D$6,$A$6,$B$6,$C$6),NursProfileData!$A$2:$BZ$2066,48,FALSE),"—"),IF(A6="Licensed practical nurses",IFERROR(VLOOKUP(CONCATENATE($D$6,$A$6,$B$6,$C$6),NursProfileData!$A$2:$BZ$2066,48,FALSE),"—"),"-")))))))))) -> 0.09945964
B20: 50–54 | C20: =IF(A6="Family medicine physicians",IFERROR(VLOOKUP(CONCATENATE($D$6,$A$6,$B$6),Phyprofile!A3:AU464,14,FALSE),"—"),IF(A6="Specialists",IFERROR(VLOOKUP(CONCATENATE($D$6,$A$6,$B$6),Phyprofile!A3:AU464,14,FALSE),"—"),IF(A6="All physicians",IFERROR(VLOOKUP(CONCATENATE($D$6,$A$6,$B$6),Phyprofile!A3:AU464,14,FALSE),"—"),IF(A6="Occupational therapists",IFERROR(VLOOKUP(CONCATENATE($D$6,$A$6,$B$6,$C$6),OTProfileData!$A$2:$AR$1920,14,FALSE),"—"),IF(A6="Physiotherapists",IFERROR(VLOOKUP(CONCATENATE($D$6,$A$6,$B$6,$C$6),PTProfileData!$A$2:$BW$1802,14,FALSE),"—"),IF(A6="Pharmacists",IFERROR(VLOOKUP(CONCATENATE($D$6,$A$6,$B$6,$C$6),PHProfileData!$A$3:$AO$1868,14,FALSE),"—"),IF(A6="nurse practitioners",IFERROR(VLOOKUP(CONCATENATE($D$6,$A$6,$B$6,$C$6),NursProfileData!$A$2:$BZ$2066,14,FALSE),"—"),IF(A6="Registered nurses",IFERROR(VLOOKUP(CONCATENATE($D$6,$A$6,$B$6,$C$6),NursProfileData!$A$2:$BZ$2066,14,FALSE),"—"),IF(A6="Registered psychiatric nurses",IFERROR(VLOOKUP(CONCATENATE($D$6,$A$6,$B$6,$C$6),NursProfileData!$A$2:$BZ$2066,14,FALSE),"—"),IF(A6="Licensed practical nurses",IFERROR(VLOOKUP(CONCATENATE($D$6,$A$6,$B$6,$C$6),NursProfileData!$A$2:$BZ$2066,14,FALSE),"—"),"-")))))))))) -> 11340 | D20: =IF(A6="Family medicine physicians",IFERROR(VLOOKUP(CONCATENATE($D$6,$A$6,$B$6),Phyprofile!A3:AU464,35,FALSE),"—"),IF(A6="Specialists",IFERROR(VLOOKUP(CONCATENATE($D$6,$A$6,$B$6),Phyprofile!A3:AU464,35,FALSE),"—"),IF(A6="All physicians",IFERROR(VLOOKUP(CONCATENATE($D$6,$A$6,$B$6),Phyprofile!A3:AU464,35,FALSE),"—"),IF(A6="Occupational therapists",IFERROR(VLOOKUP(CONCATENATE($D$6,$A$6,$B$6,$C$6),OTProfileData!$A$2:$CB$1920,50,FALSE),"—"),IF(A6="Physiotherapists",IFERROR(VLOOKUP(CONCATENATE($D$6,$A$6,$B$6,$C$6),PTProfileData!$A$2:$BW$1802,47,FALSE),"—"),IF(A6="Pharmacists",IFERROR(VLOOKUP(CONCATENATE($D$6,$A$6,$B$6,$C$6),PHProfileData!$A$3:$BR$1868,45,FALSE),"—"),IF(A6="nurse practitioners",IFERROR(VLOOKUP(CONCATENATE($D$6,$A$6,$B$6,$C$6),NursProfileData!$A$2:$BZ$2066,49,FALSE),"—"),IF(A6="Registered nurses",IFERROR(VLOOKUP(CONCATENATE($D$6,$A$6,$B$6,$C$6),NursProfileData!$A$2:$BZ$2066,49,FALSE),"—"),IF(A6="Registered psychiatric nurses",IFERROR(VLOOKUP(CONCATENATE($D$6,$A$6,$B$6,$C$6),NursProfileData!$A$2:$BZ$2066,49,FALSE),"—"),IF(A6="Licensed practical nurses",IFERROR(VLOOKUP(CONCATENATE($D$6,$A$6,$B$6,$C$6),NursProfileData!$A$2:$BZ$2066,49,FALSE),"—"),"-")))))))))) -> 0.11161527
B21: 55–59 | C21: =IF(A6="Family medicine physicians",IFERROR(VLOOKUP(CONCATENATE($D$6,$A$6,$B$6),Phyprofile!A3:AU464,15,FALSE),"—"),IF(A6="Specialists",IFERROR(VLOOKUP(CONCATENATE($D$6,$A$6,$B$6),Phyprofile!A3:AU464,15,FALSE),"—"),IF(A6="All physicians",IFERROR(VLOOKUP(CONCATENATE($D$6,$A$6,$B$6),Phyprofile!A3:AU464,15,FALSE),"—"),IF(A6="Occupational therapists",IFERROR(VLOOKUP(CONCATENATE($D$6,$A$6,$B$6,$C$6),OTProfileData!$A$2:$AR$1920,15,FALSE),"—"),IF(A6="Physiotherapists",IFERROR(VLOOKUP(CONCATENATE($D$6,$A$6,$B$6,$C$6),PTProfileData!$A$2:$BW$1802,15,FALSE),"—"),IF(A6="Pharmacists",IFERROR(VLOOKUP(CONCATENATE($D$6,$A$6,$B$6,$C$6),PHProfileData!$A$3:$AO$1868,15,FALSE),"—"),IF(A6="nurse practitioners",IFERROR(VLOOKUP(CONCATENATE($D$6,$A$6,$B$6,$C$6),NursProfileData!$A$2:$BZ$2066,15,FALSE),"—"),IF(A6="Registered nurses",IFERROR(VLOOKUP(CONCATENATE($D$6,$A$6,$B$6,$C$6),NursProfileData!$A$2:$BZ$2066,15,FALSE),"—"),IF(A6="Registered psychiatric nurses",IFERROR(VLOOKUP(CONCATENATE($D$6,$A$6,$B$6,$C$6),NursProfileData!$A$2:$BZ$2066,15,FALSE),"—"),IF(A6="Licensed practical nurses",IFERROR(VLOOKUP(CONCATENATE($D$6,$A$6,$B$6,$C$6),NursProfileData!$A$2:$BZ$2066,15,FALSE),"—"),"-")))))))))) -> 10730 | D21: =IF(A6="Family medicine physicians",IFERROR(VLOOKUP(CONCATENATE($D$6,$A$6,$B$6),Phyprofile!A3:AU464,36,FALSE),"—"),IF(A6="Specialists",IFERROR(VLOOKUP(CONCATENATE($D$6,$A$6,$B$6),Phyprofile!A3:AU464,36,FALSE),"—"),IF(A6="All physicians",IFERROR(VLOOKUP(CONCATENATE($D$6,$A$6,$B$6),Phyprofile!A3:AU464,36,FALSE),"—"),IF(A6="Occupational therapists",IFERROR(VLOOKUP(CONCATENATE($D$6,$A$6,$B$6,$C$6),OTProfileData!$A$2:$CB$1920,51,FALSE),"—"),IF(A6="Physiotherapists",IFERROR(VLOOKUP(CONCATENATE($D$6,$A$6,$B$6,$C$6),PTProfileData!$A$2:$BW$1802,48,FALSE),"—"),IF(A6="Pharmacists",IFERROR(VLOOKUP(CONCATENATE($D$6,$A$6,$B$6,$C$6),PHProfileData!$A$3:$BR$1868,46,FALSE),"—"),IF(A6="nurse practitioners",IFERROR(VLOOKUP(CONCATENATE($D$6,$A$6,$B$6,$C$6),NursProfileData!$A$2:$BZ$2066,50,FALSE),"—"),IF(A6="Registered nurses",IFERROR(VLOOKUP(CONCATENATE($D$6,$A$6,$B$6,$C$6),NursProfileData!$A$2:$BZ$2066,50,FALSE),"—"),IF(A6="Registered psychiatric nurses",IFERROR(VLOOKUP(CONCATENATE($D$6,$A$6,$B$6,$C$6),NursProfileData!$A$2:$BZ$2066,50,FALSE),"—"),IF(A6="Licensed practical nurses",IFERROR(VLOOKUP(CONCATENATE($D$6,$A$6,$B$6,$C$6),NursProfileData!$A$2:$BZ$2066,50,FALSE),"—"),"-")))))))))) -> 0.10561128
B22: 60–64 | C22: =IF(A6="Family medicine physicians",IFERROR(VLOOKUP(CONCATENATE($D$6,$A$6,$B$6),Phyprofile!A3:AU464,16,FALSE),"—"),IF(A6="Specialists",IFERROR(VLOOKUP(CONCATENATE($D$6,$A$6,$B$6),Phyprofile!A3:AU464,16,FALSE),"—"),IF(A6="All physicians",IFERROR(VLOOKUP(CONCATENATE($D$6,$A$6,$B$6),Phyprofile!A3:AU464,16,FALSE),"—"),IF(A6="Occupational therapists",IFERROR(VLOOKUP(CONCATENATE($D$6,$A$6,$B$6,$C$6),OTProfileData!$A$2:$AR$1920,16,FALSE),"—"),IF(A6="Physiotherapists",IFERROR(VLOOKUP(CONCATENATE($D$6,$A$6,$B$6,$C$6),PTProfileData!$A$2:$BW$1802,16,FALSE),"—"),IF(A6="Pharmacists",IFERROR(VLOOKUP(CONCATENATE($D$6,$A$6,$B$6,$C$6),PHProfileData!$A$3:$AO$1868,16,FALSE),"—"),IF(A6="nurse practitioners",IFERROR(VLOOKUP(CONCATENATE($D$6,$A$6,$B$6,$C$6),NursProfileData!$A$2:$BZ$2066,16,FALSE),"—"),IF(A6="Registered nurses",IFERROR(VLOOKUP(CONCATENATE($D$6,$A$6,$B$6,$C$6),NursProfileData!$A$2:$BZ$2066,16,FALSE),"—"),IF(A6="Registered psychiatric nurses",IFERROR(VLOOKUP(CONCATENATE($D$6,$A$6,$B$6,$C$6),NursProfileData!$A$2:$BZ$2066,16,FALSE),"—"),IF(A6="Licensed practical nurses",IFERROR(VLOOKUP(CONCATENATE($D$6,$A$6,$B$6,$C$6),NursProfileData!$A$2:$BZ$2066,16,FALSE),"—"),"-")))))))))) -> 7872 | D22: =IF(A6="Family medicine physicians",IFERROR(VLOOKUP(CONCATENATE($D$6,$A$6,$B$6),Phyprofile!A3:AU464,37,FALSE),"—"),IF(A6="Specialists",IFERROR(VLOOKUP(CONCATENATE($D$6,$A$6,$B$6),Phyprofile!A3:AU464,37,FALSE),"—"),IF(A6="All physicians",IFERROR(VLOOKUP(CONCATENATE($D$6,$A$6,$B$6),Phyprofile!A3:AU464,37,FALSE),"—"),IF(A6="Occupational therapists",IFERROR(VLOOKUP(CONCATENATE($D$6,$A$6,$B$6,$C$6),OTProfileData!$A$2:$CB$1920,52,FALSE),"—"),IF(A6="Physiotherapists",IFERROR(VLOOKUP(CONCATENATE($D$6,$A$6,$B$6,$C$6),PTProfileData!$A$2:$BW$1802,49,FALSE),"—"),IF(A6="Pharmacists",IFERROR(VLOOKUP(CONCATENATE($D$6,$A$6,$B$6,$C$6),PHProfileData!$A$3:$BR$1868,47,FALSE),"—"),IF(A6="nurse practitioners",IFERROR(VLOOKUP(CONCATENATE($D$6,$A$6,$B$6,$C$6),NursProfileData!$A$2:$BZ$2066,51,FALSE),"—"),IF(A6="Registered nurses",IFERROR(VLOOKUP(CONCATENATE($D$6,$A$6,$B$6,$C$6),NursProfileData!$A$2:$BZ$2066,51,FALSE),"—"),IF(A6="Registered psychiatric nurses",IFERROR(VLOOKUP(CONCATENATE($D$6,$A$6,$B$6,$C$6),NursProfileData!$A$2:$BZ$2066,51,FALSE),"—"),IF(A6="Licensed practical nurses",IFERROR(VLOOKUP(CONCATENATE($D$6,$A$6,$B$6,$C$6),NursProfileData!$A$2:$BZ$2066,51,FALSE),"—"),"-")))))))))) -> 0.077481078
B23: 65–69 | C23: =IF(A6="Family medicine physicians",IFERROR(VLOOKUP(CONCATENATE($D$6,$A$6,$B$6),Phyprofile!A3:AU464,17,FALSE),"—"),IF(A6="Specialists",IFERROR(VLOOKUP(CONCATENATE($D$6,$A$6,$B$6),Phyprofile!A3:AU464,17,FALSE),"—"),IF(A6="All physicians",IFERROR(VLOOKUP(CONCATENATE($D$6,$A$6,$B$6),Phyprofile!A3:AU464,17,FALSE),"—"),IF(A6="Occupational therapists",IFERROR(VLOOKUP(CONCATENATE($D$6,$A$6,$B$6,$C$6),OTProfileData!$A$2:$AR$1920,17,FALSE),"—"),IF(A6="Physiotherapists",IFERROR(VLOOKUP(CONCATENATE($D$6,$A$6,$B$6,$C$6),PTProfileData!$A$2:$BW$1802,17,FALSE),"—"),IF(A6="Pharmacists",IFERROR(VLOOKUP(CONCATENATE($D$6,$A$6,$B$6,$C$6),PHProfileData!$A$3:$AO$1868,17,FALSE),"—"),IF(A6="nurse practitioners",IFERROR(VLOOKUP(CONCATENATE($D$6,$A$6,$B$6,$C$6),NursProfileData!$A$2:$BZ$2066,17,FALSE),"—"),IF(A6="Registered nurses",IFERROR(VLOOKUP(CONCATENATE($D$6,$A$6,$B$6,$C$6),NursProfileData!$A$2:$BZ$2066,17,FALSE),"—"),IF(A6="Registered psychiatric nurses",IFERROR(VLOOKUP(CONCATENATE($D$6,$A$6,$B$6,$C$6),NursProfileData!$A$2:$BZ$2066,17,FALSE),"—"),IF(A6="Licensed practical nurses",IFERROR(VLOOKUP(CONCATENATE($D$6,$A$6,$B$6,$C$6),NursProfileData!$A$2:$BZ$2066,17,FALSE),"—"),"-")))))))))) -> 3699 | D23: =IF(A6="Family medicine physicians",IFERROR(VLOOKUP(CONCATENATE($D$6,$A$6,$B$6),Phyprofile!A3:AU464,38,FALSE),"—"),IF(A6="Specialists",IFERROR(VLOOKUP(CONCATENATE($D$6,$A$6,$B$6),Phyprofile!A3:AU464,38,FALSE),"—"),IF(A6="All physicians",IFERROR(VLOOKUP(CONCATENATE($D$6,$A$6,$B$6),Phyprofile!A3:AU464,38,FALSE),"—"),IF(A6="Occupational therapists",IFERROR(VLOOKUP(CONCATENATE($D$6,$A$6,$B$6,$C$6),OTProfileData!$A$2:$CB$1920,53,FALSE),"—"),IF(A6="Physiotherapists",IFERROR(VLOOKUP(CONCATENATE($D$6,$A$6,$B$6,$C$6),PTProfileData!$A$2:$BW$1802,50,FALSE),"—"),IF(A6="Pharmacists",IFERROR(VLOOKUP(CONCATENATE($D$6,$A$6,$B$6,$C$6),PHProfileData!$A$3:$BR$1868,48,FALSE),"—"),IF(A6="nurse practitioners",IFERROR(VLOOKUP(CONCATENATE($D$6,$A$6,$B$6,$C$6),NursProfileData!$A$2:$BZ$2066,52,FALSE),"—"),IF(A6="Registered nurses",IFERROR(VLOOKUP(CONCATENATE($D$6,$A$6,$B$6,$C$6),NursProfileData!$A$2:$BZ$2066,52,FALSE),"—"),IF(A6="Registered psychiatric nurses",IFERROR(VLOOKUP(CONCATENATE($D$6,$A$6,$B$6,$C$6),NursProfileData!$A$2:$BZ$2066,52,FALSE),"—"),IF(A6="Licensed practical nurses",IFERROR(VLOOKUP(CONCATENATE($D$6,$A$6,$B$6,$C$6),NursProfileData!$A$2:$BZ$2066,52,FALSE),"—"),"-")))))))))) -> 0.036407839
B24: 70+ | C24: =IF(A6="Family medicine physicians",IFERROR(VLOOKUP(CONCATENATE($D$6,$A$6,$B$6),Phyprofile!A3:AU464,18,FALSE),"—"),IF(A6="Specialists",IFERROR(VLOOKUP(CONCATENATE($D$6,$A$6,$B$6),Phyprofile!A3:AU464,18,FALSE),"—"),IF(A6="All physicians",IFERROR(VLOOKUP(CONCATENATE($D$6,$A$6,$B$6),Phyprofile!A3:AU464,18,FALSE),"—"),IF(A6="Occupational therapists",IFERROR(VLOOKUP(CONCATENATE($D$6,$A$6,$B$6,$C$6),OTProfileData!$A$2:$AR$1920,18,FALSE),"—"),IF(A6="Physiotherapists",IFERROR(VLOOKUP(CONCATENATE($D$6,$A$6,$B$6,$C$6),PTProfileData!$A$2:$BW$1802,18,FALSE),"—"),IF(A6="Pharmacists",IFERROR(VLOOKUP(CONCATENATE($D$6,$A$6,$B$6,$C$6),PHProfileData!$A$3:$AO$1868,18,FALSE),"—"),IF(A6="nurse practitioners",IFERROR(VLOOKUP(CONCATENATE($D$6,$A$6,$B$6,$C$6),NursProfileData!$A$2:$BZ$2066,18,FALSE),"—"),IF(A6="Registered nurses",IFERROR(VLOOKUP(CONCATENATE($D$6,$A$6,$B$6,$C$6),NursProfileData!$A$2:$BZ$2066,18,FALSE),"—"),IF(A6="Registered psychiatric nurses",IFERROR(VLOOKUP(CONCATENATE($D$6,$A$6,$B$6,$C$6),NursProfileData!$A$2:$BZ$2066,18,FALSE),"—"),IF(A6="Licensed practical nurses",IFERROR(VLOOKUP(CONCATENATE($D$6,$A$6,$B$6,$C$6),NursProfileData!$A$2:$BZ$2066,18,FALSE),"—"),"-")))))))))) -> 1828 | D24: =IF(A6="Family medicine physicians",IFERROR(VLOOKUP(CONCATENATE($D$6,$A$6,$B$6),Phyprofile!A3:AU464,39,FALSE),"—"),IF(A6="Specialists",IFERROR(VLOOKUP(CONCATENATE($D$6,$A$6,$B$6),Phyprofile!A3:AU464,39,FALSE),"—"),IF(A6="All physicians",IFERROR(VLOOKUP(CONCATENATE($D$6,$A$6,$B$6),Phyprofile!A3:AU464,39,FALSE),"—"),IF(A6="Occupational therapists",IFERROR(VLOOKUP(CONCATENATE($D$6,$A$6,$B$6,$C$6),OTProfileData!$A$2:$CB$1920,54,FALSE),"—"),IF(A6="Physiotherapists",IFERROR(VLOOKUP(CONCATENATE($D$6,$A$6,$B$6,$C$6),PTProfileData!$A$2:$BW$1802,51,FALSE),"—"),IF(A6="Pharmacists",IFERROR(VLOOKUP(CONCATENATE($D$6,$A$6,$B$6,$C$6),PHProfileData!$A$3:$BR$1868,49,FALSE),"—"),IF(A6="nurse practitioners",IFERROR(VLOOKUP(CONCATENATE($D$6,$A$6,$B$6,$C$6),NursProfileData!$A$2:$BZ$2066,53,FALSE),"—"),IF(A6="Registered nurses",IFERROR(VLOOKUP(CONCATENATE($D$6,$A$6,$B$6,$C$6),NursProfileData!$A$2:$BZ$2066,53,FALSE),"—"),IF(A6="Registered psychiatric nurses",IFERROR(VLOOKUP(CONCATENATE($D$6,$A$6,$B$6,$C$6),NursProfileData!$A$2:$BZ$2066,53,FALSE),"—"),IF(A6="Licensed practical nurses",IFERROR(VLOOKUP(CONCATENATE($D$6,$A$6,$B$6,$C$6),NursProfileData!$A$2:$BZ$2066,53,FALSE),"—"),"-")))))))))) -> 0.027077038
B25: Not stated | C25: =IF(A6="Family medicine physicians",IFERROR(VLOOKUP(CONCATENATE($D$6,$A$6,$B$6),Phyprofile!A3:AU464,20,FALSE),"—"),IF(A6="Specialists",IFERROR(VLOOKUP(CONCATENATE($D$6,$A$6,$B$6),Phyprofile!A3:AU464,20,FALSE),"—"),IF(A6="All physicians",IFERROR(VLOOKUP(CONCATENATE($D$6,$A$6,$B$6),Phyprofile!A3:AU464,20,FALSE),"—"),IF(A6="Occupational therapists",IFERROR(VLOOKUP(CONCATENATE($D$6,$A$6,$B$6,$C$6),OTProfileData!$A$2:$AR$1920,20,FALSE),"—"),IF(A6="Physiotherapists",IFERROR(VLOOKUP(CONCATENATE($D$6,$A$6,$B$6,$C$6),PTProfileData!$A$2:$BW$1802,20,FALSE),"—"),IF(A6="Pharmacists",IFERROR(VLOOKUP(CONCATENATE($D$6,$A$6,$B$6,$C$6),PHProfileData!$A$3:$AO$1868,20,FALSE),"—"),IF(A6="nurse practitioners",IFERROR(VLOOKUP(CONCATENATE($D$6,$A$6,$B$6,$C$6),NursProfileData!$A$2:$BZ$2066,20,FALSE),"—"),IF(A6="Registered nurses",IFERROR(VLOOKUP(CONCATENATE($D$6,$A$6,$B$6,$C$6),NursProfileData!$A$2:$BZ$2066,20,FALSE),"—"),IF(A6="Registered psychiatric nurses",IFERROR(VLOOKUP(CONCATENATE($D$6,$A$6,$B$6,$C$6),NursProfileData!$A$2:$BZ$2066,20,FALSE),"—"),IF(A6="Licensed practical nurses",IFERROR(VLOOKUP(CONCATENATE($D$6,$A$6,$B$6,$C$6),NursProfileData!$A$2:$BZ$2066,20,FALSE),"—"),"-")))))))))) -> 0 | D25: =IF(A6="Family medicine physicians",IFERROR(VLOOKUP(CONCATENATE($D$6,$A$6,$B$6),Phyprofile!A3:AU464,41,FALSE),"—"),IF(A6="Specialists",IFERROR(VLOOKUP(CONCATENATE($D$6,$A$6,$B$6),Phyprofile!A3:AU464,41,FALSE),"—"),IF(A6="All physicians",IFERROR(VLOOKUP(CONCATENATE($D$6,$A$6,$B$6),Phyprofile!A3:AU464,41,FALSE),"—"),IF(A6="Occupational therapists",IFERROR(VLOOKUP(CONCATENATE($D$6,$A$6,$B$6,$C$6),OTProfileData!$A$2:$CB$1920,56,FALSE),"—"),IF(A6="Physiotherapists",IFERROR(VLOOKUP(CONCATENATE($D$6,$A$6,$B$6,$C$6),PTProfileData!$A$2:$BW$1802,53,FALSE),"—"),IF(A6="Pharmacists",IFERROR(VLOOKUP(CONCATENATE($D$6,$A$6,$B$6,$C$6),PHProfileData!$A$3:$BR$1868,51,FALSE),"—"),IF(A6="nurse practitioners",IFERROR(VLOOKUP(CONCATENATE($D$6,$A$6,$B$6,$C$6),NursProfileData!$A$2:$BZ$2066,55,FALSE),"—"),IF(A6="Registered nurses",IFERROR(VLOOKUP(CONCATENATE($D$6,$A$6,$B$6,$C$6),NursProfileData!$A$2:$BZ$2066,55,FALSE),"—"),IF(A6="Registered psychiatric nurses",IFERROR(VLOOKUP(CONCATENATE($D$6,$A$6,$B$6,$C$6),NursProfileData!$A$2:$BZ$2066,55,FALSE),"—"),IF(A6="Licensed practical nurses",IFERROR(VLOOKUP(CONCATENATE($D$6,$A$6,$B$6,$C$6),NursProfileData!$A$2:$BZ$2066,55,FALSE),"—"),"-")))))))))) -> 0
A26: Country of Graduation | B26: Canadian educated | C26: =IF(A6="Family medicine physicians",IFERROR(VLOOKUP(CONCATENATE($D$6,$A$6,$B$6),Phyprofile!A3:AU464,21,FALSE),"—"),IF(A6="Specialists",IFERROR(VLOOKUP(CONCATENATE($D$6,$A$6,$B$6),Phyprofile!A3:AU464,21,FALSE),"—"),IF(A6="All physicians",IFERROR(VLOOKUP(CONCATENATE($D$6,$A$6,$B$6),Phyprofile!A3:AU464,21,FALSE),"—"),IF(A6="Occupational therapists",IFERROR(VLOOKUP(CONCATENATE($D$6,$A$6,$B$6,$C$6),OTProfileData!$A$2:$AR$1920,21,FALSE),"—"),IF(A6="Physiotherapists",IFERROR(VLOOKUP(CONCATENATE($D$6,$A$6,$B$6,$C$6),PTProfileData!$A$2:$BW$1802,21,FALSE),"—"),IF(A6="Pharmacists",IFERROR(VLOOKUP(CONCATENATE($D$6,$A$6,$B$6,$C$6),PHProfileData!$A$3:$AO$1868,21,FALSE),"—"),IF(A6="nurse practitioners",IFERROR(VLOOKUP(CONCATENATE($D$6,$A$6,$B$6,$C$6),NursProfileData!$A$2:$BZ$2066,21,FALSE),"—"),IF(A6="Registered nurses",IFERROR(VLOOKUP(CONCATENATE($D$6,$A$6,$B$6,$C$6),NursProfileData!$A$2:$BZ$2066,21,FALSE),"—"),IF(A6="Registered psychiatric nurses",IFERROR(VLOOKUP(CONCATENATE($D$6,$A$6,$B$6,$C$6),NursProfileData!$A$2:$BZ$2066,21,FALSE),"—"),IF(A6="Licensed practical nurses",IFERROR(VLOOKUP(CONCATENATE($D$6,$A$6,$B$6,$C$6),NursProfileData!$A$2:$BZ$2066,21,FALSE),"—"),"-")))))))))) -> 87066 | D26: =IF(A6="Family medicine physicians",IFERROR(VLOOKUP(CONCATENATE($D$6,$A$6,$B$6),Phyprofile!A3:AU464,42,FALSE),"—"),IF(A6="Specialists",IFERROR(VLOOKUP(CONCATENATE($D$6,$A$6,$B$6),Phyprofile!A3:AU464,42,FALSE),"—"),IF(A6="All physicians",IFERROR(VLOOKUP(CONCATENATE($D$6,$A$6,$B$6),Phyprofile!A3:AU464,42,FALSE),"—"),IF(A6="Occupational therapists",IFERROR(VLOOKUP(CONCATENATE($D$6,$A$6,$B$6,$C$6),OTProfileData!$A$2:$CB$1920,57,FALSE),"—"),IF(A6="Physiotherapists",IFERROR(VLOOKUP(CONCATENATE($D$6,$A$6,$B$6,$C$6),PTProfileData!$A$2:$BW$1802,54,FALSE),"—"),IF(A6="Pharmacists",IFERROR(VLOOKUP(CONCATENATE($D$6,$A$6,$B$6,$C$6),PHProfileData!$A$3:$BR$1868,52,FALSE),"—"),IF(A6="nurse practitioners",IFERROR(VLOOKUP(CONCATENATE($D$6,$A$6,$B$6,$C$6),NursProfileData!$A$2:$BZ$2066,56,FALSE),"—"),IF(A6="Registered nurses",IFERROR(VLOOKUP(CONCATENATE($D$6,$A$6,$B$6,$C$6),NursProfileData!$A$2:$BZ$2066,56,FALSE),"—"),IF(A6="Registered psychiatric nurses",IFERROR(VLOOKUP(CONCATENATE($D$6,$A$6,$B$6,$C$6),NursProfileData!$A$2:$BZ$2066,56,FALSE),"—"),IF(A6="Licensed practical nurses",IFERROR(VLOOKUP(CONCATENATE($D$6,$A$6,$B$6,$C$6),NursProfileData!$A$2:$BZ$2066,56,FALSE),"—"),"-")))))))))) -> 0.85695725
B27: Internationally educated | C27: =IF(A6="Family medicine physicians",IFERROR(VLOOKUP(CONCATENATE($D$6,$A$6,$B$6),Phyprofile!A3:AU464,22,FALSE),"—"),IF(A6="Specialists",IFERROR(VLOOKUP(CONCATENATE($D$6,$A$6,$B$6),Phyprofile!A3:AU464,22,FALSE),"—"),IF(A6="All physicians",IFERROR(VLOOKUP(CONCATENATE($D$6,$A$6,$B$6),Phyprofile!A3:AU464,22,FALSE),"—"),IF(A6="Occupational therapists",IFERROR(VLOOKUP(CONCATENATE($D$6,$A$6,$B$6,$C$6),OTProfileData!$A$2:$AR$1920,22,FALSE),"—"),IF(A6="Physiotherapists",IFERROR(VLOOKUP(CONCATENATE($D$6,$A$6,$B$6,$C$6),PTProfileData!$A$2:$BW$1802,22,FALSE),"—"),IF(A6="Pharmacists",IFERROR(VLOOKUP(CONCATENATE($D$6,$A$6,$B$6,$C$6),PHProfileData!$A$3:$AO$1868,22,FALSE),"—"),IF(A6="nurse practitioners",IFERROR(VLOOKUP(CONCATENATE($D$6,$A$6,$B$6,$C$6),NursProfileData!$A$2:$BZ$2066,22,FALSE),"—"),IF(A6="Registered nurses",IFERROR(VLOOKUP(CONCATENATE($D$6,$A$6,$B$6,$C$6),NursProfileData!$A$2:$BZ$2066,22,FALSE),"—"),IF(A6="Registered psychiatric nurses",IFERROR(VLOOKUP(CONCATENATE($D$6,$A$6,$B$6,$C$6),NursProfileData!$A$2:$BZ$2066,22,FALSE),"—"),IF(A6="Licensed practical nurses",IFERROR(VLOOKUP(CONCATENATE($D$6,$A$6,$B$6,$C$6),NursProfileData!$A$2:$BZ$2066,22,FALSE),"—"),"-")))))))))) -> 14529 | D27: =IF(A6="Family medicine physicians",IFERROR(VLOOKUP(CONCATENATE($D$6,$A$6,$B$6),Phyprofile!A3:AU464,43,FALSE),"—"),IF(A6="Specialists",IFERROR(VLOOKUP(CONCATENATE($D$6,$A$6,$B$6),Phyprofile!A3:AU464,43,FALSE),"—"),IF(A6="All physicians",IFERROR(VLOOKUP(CONCATENATE($D$6,$A$6,$B$6),Phyprofile!A3:AU464,43,FALSE),"—"),IF(A6="Occupational therapists",IFERROR(VLOOKUP(CONCATENATE($D$6,$A$6,$B$6,$C$6),OTProfileData!$A$2:$CB$1920,58,FALSE),"—"),IF(A6="Physiotherapists",IFERROR(VLOOKUP(CONCATENATE($D$6,$A$6,$B$6,$C$6),PTProfileData!$A$2:$BW$1802,55,FALSE),"—"),IF(A6="Pharmacists",IFERROR(VLOOKUP(CONCATENATE($D$6,$A$6,$B$6,$C$6),PHProfileData!$A$3:$BR$1868,53,FALSE),"—"),IF(A6="nurse practitioners",IFERROR(VLOOKUP(CONCATENATE($D$6,$A$6,$B$6,$C$6),NursProfileData!$A$2:$BZ$2066,57,FALSE),"—"),IF(A6="Registered nurses",IFERROR(VLOOKUP(CONCATENATE($D$6,$A$6,$B$6,$C$6),NursProfileData!$A$2:$BZ$2066,57,FALSE),"—"),IF(A6="Registered psychiatric nurses",IFERROR(VLOOKUP(CONCATENATE($D$6,$A$6,$B$6,$C$6),NursProfileData!$A$2:$BZ$2066,57,FALSE),"—"),IF(A6="Licensed practical nurses",IFERROR(VLOOKUP(CONCATENATE($D$6,$A$6,$B$6,$C$6),NursProfileData!$A$2:$BZ$2066,57,FALSE),"—"),"-")))))))))) -> 0.14300338
B28: Not stated | C28: =IF(A6="Family medicine physicians",IFERROR(VLOOKUP(CONCATENATE($D$6,$A$6,$B$6),Phyprofile!A3:AU464,23,FALSE),"—"),IF(A6="Specialists",IFERROR(VLOOKUP(CONCATENATE($D$6,$A$6,$B$6),Phyprofile!A3:AU464,23,FALSE),"—"),IF(A6="All physicians",IFERROR(VLOOKUP(CONCATENATE($D$6,$A$6,$B$6),Phyprofile!A3:AU464,23,FALSE),"—"),IF(A6="Occupational therapists",IFERROR(VLOOKUP(CONCATENATE($D$6,$A$6,$B$6,$C$6),OTProfileData!$A$2:$AR$1920,23,FALSE),"—"),IF(A6="Physiotherapists",IFERROR(VLOOKUP(CONCATENATE($D$6,$A$6,$B$6,$C$6),PTProfileData!$A$2:$BW$1802,23,FALSE),"—"),IF(A6="Pharmacists",IFERROR(VLOOKUP(CONCATENATE($D$6,$A$6,$B$6,$C$6),PHProfileData!$A$3:$AO$1868,23,FALSE),"—"),IF(A6="nurse practitioners",IFERROR(VLOOKUP(CONCATENATE($D$6,$A$6,$B$6,$C$6),NursProfileData!$A$2:$BZ$2066,23,FALSE),"—"),IF(A6="Registered nurses",IFERROR(VLOOKUP(CONCATENATE($D$6,$A$6,$B$6,$C$6),NursProfileData!$A$2:$BZ$2066,23,FALSE),"—"),IF(A6="Registered psychiatric nurses",IFERROR(VLOOKUP(CONCATENATE($D$6,$A$6,$B$6,$C$6),NursProfileData!$A$2:$BZ$2066,23,FALSE),"—"),IF(A6="Licensed practical nurses",IFERROR(VLOOKUP(CONCATENATE($D$6,$A$6,$B$6,$C$6),NursProfileData!$A$2:$BZ$2066,23,FALSE),"—"),"-")))))))))) -> 4 | D28: =IF(A6="Family medicine physicians",IFERROR(VLOOKUP(CONCATENATE($D$6,$A$6,$B$6),Phyprofile!A3:AU464,44,FALSE),"—"),IF(A6="Specialists",IFERROR(VLOOKUP(CONCATENATE($D$6,$A$6,$B$6),Phyprofile!A3:AU464,44,FALSE),"—"),IF(A6="All physicians",IFERROR(VLOOKUP(CONCATENATE($D$6,$A$6,$B$6),Phyprofile!A3:AU464,44,FALSE),"—"),IF(A6="Occupational therapists",IFERROR(VLOOKUP(CONCATENATE($D$6,$A$6,$B$6,$C$6),OTProfileData!$A$2:$CB$1920,59,FALSE),"—"),IF(A6="Physiotherapists",IFERROR(VLOOKUP(CONCATENATE($D$6,$A$6,$B$6,$C$6),PTProfileData!$A$2:$BW$1802,56,FALSE),"—"),IF(A6="Pharmacists",IFERROR(VLOOKUP(CONCATENATE($D$6,$A$6,$B$6,$C$6),PHProfileData!$A$3:$BR$1868,54,FALSE),"—"),IF(A6="nurse practitioners",IFERROR(VLOOKUP(CONCATENATE($D$6,$A$6,$B$6,$C$6),NursProfileData!$A$2:$BZ$2066,58,FALSE),"—"),IF(A6="Registered nurses",IFERROR(VLOOKUP(CONCATENATE($D$6,$A$6,$B$6,$C$6),NursProfileData!$A$2:$BZ$2066,58,FALSE),"—"),IF(A6="Registered psychiatric nurses",IFERROR(VLOOKUP(CONCATENATE($D$6,$A$6,$B$6,$C$6),NursProfileData!$A$2:$BZ$2066,58,FALSE),"—"),IF(A6="Licensed practical nurses",IFERROR(VLOOKUP(CONCATENATE($D$6,$A$6,$B$6,$C$6),NursProfileData!$A$2:$BZ$2066,58,FALSE),"—"),"-")))))))))) -> 3.9370466e-05
A29: =IF(A6="Family medicine physicians","—",IF(A6="Specialists","—",IF(A6="All physicians","—",IF(A6="Occupational therapists","Employment Status",IF(A6="Physiotherapists","Employment Status",IF(A6="Pharmacists","Employment Category",IF(A6="nurse practitioners","Employment Status",IF(A6="Registered nurses","Employment Status",IF(A6="Registered psychiatric nurses","Employment Status",IF(A6="Licensed practical nurses","Employment Status","-")))))))))) -> Employment Status | B29: =IF(A6="Family medicine physicians","—",IF(A6="Specialists","—",IF(A6="All physicians","—",IF(A6="Occupational therapists","Full-time",IF(A6="Physiotherapists","Full-time",IF(A6="Pharmacists","Permanent",IF(A6="Nurse practitioners","Full-time",IF(A6="Registered nurses","Full-time",IF(A6="Registered psychiatric nurses","Full-time",IF(A6="Licensed practical nurses","Full-time","—")))))))))) -> Full-time | C29: =IF(A6="Family medicine physicians","—",IF(A6="Specialists","—",IF(A6="All physicians","—",IF(A6="Occupational therapists",IFERROR(VLOOKUP(CONCATENATE($D$6,$A$6,$B$6,$C$6),OTProfileData!$A$2:$AR$1920,24,FALSE),"—"),IF(A6="Physiotherapists",IFERROR(VLOOKUP(CONCATENATE($D$6,$A$6,$B$6,$C$6),PTProfileData!$A$2:$BW$1802,24,FALSE),"—"),IF(A6="Pharmacists",IFERROR(VLOOKUP(CONCATENATE($D$6,$A$6,$B$6,$C$6),PHProfileData!$A$3:$AO$1868,24,FALSE),"—"),IF(A6="nurse practitioners",IFERROR(VLOOKUP(CONCATENATE($D$6,$A$6,$B$6,$C$6),NursProfileData!$A$2:$BZ$2066,24,FALSE),"—"),IF(A6="Registered nurses",IFERROR(VLOOKUP(CONCATENATE($D$6,$A$6,$B$6,$C$6),NursProfileData!$A$2:$BZ$2066,24,FALSE),"—"),IF(A6="Registered psychiatric nurses",IFERROR(VLOOKUP(CONCATENATE($D$6,$A$6,$B$6,$C$6),NursProfileData!$A$2:$BZ$2066,24,FALSE),"—"),IF(A6="Licensed practical nurses",IFERROR(VLOOKUP(CONCATENATE($D$6,$A$6,$B$6,$C$6),NursProfileData!$A$2:$BZ$2066,24,FALSE),"—"),"—")))))))))) -> 71775 | D29: =IF(A6="Family medicine physicians","—",IF(A6="Specialists","—",IF(A6="All physicians","—",IF(A6="Occupational therapists",IFERROR(VLOOKUP(CONCATENATE($D$6,$A$6,$B$6,$C$6),OTProfileData!$A$2:$CB$1920,60,FALSE),"—"),IF(A6="Physiotherapists",IFERROR(VLOOKUP(CONCATENATE($D$6,$A$6,$B$6,$C$6),PTProfileData!$A$2:$BW$1802,57,FALSE),"—"),IF(A6="Pharmacists",IFERROR(VLOOKUP(CONCATENATE($D$6,$A$6,$B$6,$C$6),PHProfileData!$A$3:$BR$1868,55,FALSE),"—"),IF(A6="nurse practitioners",IFERROR(VLOOKUP(CONCATENATE($D$6,$A$6,$B$6,$C$6),NursProfileData!$A$2:$BZ$2066,59,FALSE),"—"),IF(A6="Registered nurses",IFERROR(VLOOKUP(CONCATENATE($D$6,$A$6,$B$6,$C$6),NursProfileData!$A$2:$BZ$2066,59,FALSE),"—"),IF(A6="Registered psychiatric nurses",IFERROR(VLOOKUP(CONCATENATE($D$6,$A$6,$B$6,$C$6),NursProfileData!$A$2:$BZ$2066,59,FALSE),"—"),IF(A6="Licensed practical nurses",IFERROR(VLOOKUP(CONCATENATE($D$6,$A$6,$B$6,$C$6),NursProfileData!$A$2:$BZ$2066,59,FALSE),"—"),"—")))))))))) -> 0.7064538
B30: =IF(A6="Family medicine physicians","—",IF(A6="Specialists","—",IF(A6="All physicians","—",IF(A6="Occupational therapists","Part-time",IF(A6="Physiotherapists","Part-time",IF(A6="Pharmacists","Temporary",IF(A6="nurse practitioners","Part-time",IF(A6="Registered nurses","Part-time",IF(A6="Registered psychiatric nurses","Part-time",IF(A6="Licensed practical nurses","Part-time","—")))))))))) -> Part-time | C30: =IF(A6="Family medicine physicians","—",IF(A6="Specialists","—",IF(A6="All physicians","—",IF(A6="Occupational therapists",IFERROR(VLOOKUP(CONCATENATE($D$6,$A$6,$B$6,$C$6),OTProfileData!$A$2:$AR$1920,25,FALSE),"—"),IF(A6="Physiotherapists",IFERROR(VLOOKUP(CONCATENATE($D$6,$A$6,$B$6,$C$6),PTProfileData!$A$2:$BW$1802,25,FALSE),"—"),IF(A6="Pharmacists",IFERROR(VLOOKUP(CONCATENATE($D$6,$A$6,$B$6,$C$6),PHProfileData!$A$3:$AO$1868,25,FALSE),"—"),IF(A6="nurse practitioners",IFERROR(VLOOKUP(CONCATENATE($D$6,$A$6,$B$6,$C$6),NursProfileData!$A$2:$BZ$2066,25,FALSE),"—"),IF(A6="Registered nurses",IFERROR(VLOOKUP(CONCATENATE($D$6,$A$6,$B$6,$C$6),NursProfileData!$A$2:$BZ$2066,25,FALSE),"—"),IF(A6="Registered psychiatric nurses",IFERROR(VLOOKUP(CONCATENATE($D$6,$A$6,$B$6,$C$6),NursProfileData!$A$2:$BZ$2066,25,FALSE),"—"),IF(A6="Licensed practical nurses",IFERROR(VLOOKUP(CONCATENATE($D$6,$A$6,$B$6,$C$6),NursProfileData!$A$2:$BZ$2066,25,FALSE),"—"),"-")))))))))) -> 21636 | D30: =IF(A6="Family medicine physicians","—",IF(A6="Specialists","—",IF(A6="All physicians","—",IF(A6="Occupational therapists",IFERROR(VLOOKUP(CONCATENATE($D$6,$A$6,$B$6,$C$6),OTProfileData!$A$2:$CB$1920,61,FALSE),"—"),IF(A6="Physiotherapists",IFERROR(VLOOKUP(CONCATENATE($D$6,$A$6,$B$6,$C$6),PTProfileData!$A$2:$BW$1802,58,FALSE),"—"),IF(A6="Pharmacists",IFERROR(VLOOKUP(CONCATENATE($D$6,$A$6,$B$6,$C$6),PHProfileData!$A$3:$BR$1868,56,FALSE),"—"),IF(A6="nurse practitioners",IFERROR(VLOOKUP(CONCATENATE($D$6,$A$6,$B$6,$C$6),NursProfileData!$A$2:$BZ$2066,60,FALSE),"—"),IF(A6="Registered nurses",IFERROR(VLOOKUP(CONCATENATE($D$6,$A$6,$B$6,$C$6),NursProfileData!$A$2:$BZ$2066,60,FALSE),"—"),IF(A6="Registered psychiatric nurses",IFERROR(VLOOKUP(CONCATENATE($D$6,$A$6,$B$6,$C$6),NursProfileData!$A$2:$BZ$2066,60,FALSE),"—"),IF(A6="Licensed practical nurses",IFERROR(VLOOKUP(CONCATENATE($D$6,$A$6,$B$6,$C$6),NursProfileData!$A$2:$BZ$2066,60,FALSE),"—"),"-")))))))))) -> 0.21295485
B31: =IF(A6="Family medicine physicians","—",IF(A6="Specialists","—",IF(A6="All physicians","—",IF(A6="Occupational therapists","—",IF(A6="Physiotherapists","—",IF(A6="Pharmacists","Casual",IF(A6="nurse practitioners","Casual",IF(A6="Registered nurses","Casual",IF(A6="Registered psychiatric nurses","Casual",IF(A6="Licensed practical nurses","Casual","—")))))))))) -> Casual | C31: =IF(A6="Family medicine physicians","—",IF(A6="Specialists","—",IF(A6="All physicians","—",IF(A6="Occupational therapists","—",IF(A6="Physiotherapists","—",IF(A6="Pharmacists",IFERROR(VLOOKUP(CONCATENATE($D$6,$A$6,$B$6,$C$6),PHProfileData!$A$3:$AO$1868,26,FALSE),"—"),IF(A6="nurse practitioners",IFERROR(VLOOKUP(CONCATENATE($D$6,$A$6,$B$6,$C$6),NursProfileData!$A$2:$BZ$2066,26,FALSE),"—"),IF(A6="Registered nurses",IFERROR(VLOOKUP(CONCATENATE($D$6,$A$6,$B$6,$C$6),NursProfileData!$A$2:$BZ$2066,26,FALSE),"—"),IF(A6="Registered psychiatric nurses",IFERROR(VLOOKUP(CONCATENATE($D$6,$A$6,$B$6,$C$6),NursProfileData!$A$2:$BZ$2066,26,FALSE),"—"),IF(A6="Licensed practical nurses",IFERROR(VLOOKUP(CONCATENATE($D$6,$A$6,$B$6,$C$6),NursProfileData!$A$2:$BZ$2066,26,FALSE),"—"),"—")))))))))) -> 8188 | D31: =IF(A6="Family medicine physicians","—",IF(A6="Specialists","—",IF(A6="All physicians","—",IF(A6="Occupational therapists","—",IF(A6="Physiotherapists","—",IF(A6="Pharmacists",IFERROR(VLOOKUP(CONCATENATE($D$6,$A$6,$B$6,$C$6),PHProfileData!$A$3:$BR$1868,57,FALSE),"—"),IF(A6="nurse practitioners",IFERROR(VLOOKUP(CONCATENATE($D$6,$A$6,$B$6,$C$6),NursProfileData!$A$2:$BZ$2066,61,FALSE),"—"),IF(A6="Registered nurses",IFERROR(VLOOKUP(CONCATENATE($D$6,$A$6,$B$6,$C$6),NursProfileData!$A$2:$BZ$2066,61,FALSE),"—"),IF(A6="Registered psychiatric nurses",IFERROR(VLOOKUP(CONCATENATE($D$6,$A$6,$B$6,$C$6),NursProfileData!$A$2:$BZ$2066,61,FALSE),"—"),IF(A6="Licensed practical nurses",IFERROR(VLOOKUP(CONCATENATE($D$6,$A$6,$B$6,$C$6),NursProfileData!$A$2:$BZ$2066,61,FALSE),"—"),"-")))))))))) -> 0.080591344
B32: =IF(A6="Family medicine physicians","—",IF(A6="Specialists","—",IF(A6="All physicians","—",IF(A6="Occupational therapists","—",IF(A6="Physiotherapists","—",IF(A6="Pharmacists","Self-employed",IF(A6="Nurse practitioners","—",IF(A6="Registered nurses","—",IF(A6="Registered psychiatric nurses","—",IF(A6="Licensed practical nurses","—","—")))))))))) -> — | C32: =IF(A6="Family medicine physicians","—",IF(A6="Specialists","—",IF(A6="All physicians","—",IF(A6="Occupational therapists","—",IF(A6="Physiotherapists","—",IF(A6="Pharmacists",IFERROR(VLOOKUP(CONCATENATE($D$6,$A$6,$B$6,$C$6),PHProfileData!$A$3:$AO$1868,27,FALSE),"—"),IF(A6="nurse practitioners","—",IF(A6="Registered nurses","—",IF(A6="Registered psychiatric nurses","—",IF(A6="Licensed practical nurses","—")))))))))) -> — | D32: =IF(A6="Family medicine physicians","—",IF(A6="Specialists","—",IF(A6="All physicians","—",IF(A6="Occupational therapists","—",IF(A6="Physiotherapists","—",IF(A6="Pharmacists",IFERROR(VLOOKUP(CONCATENATE($D$6,$A$6,$B$6,$C$6),PHProfileData!$A$3:$BR$1868,58,FALSE),"—"),IF(A6="nurse practitioners","—",IF(A6="Registered nurses","—",IF(A6="Registered psychiatric nurses","—",IF(A6="Licensed practical nurses","—")))))))))) -> —
B33: =IF(OR(A6="Family medicine physicians",A6="Specialists",A6="All physicians"),"—","Not stated") -> Not stated | C33: =IF(A6="Family medicine physicians","—",IF(A6="Specialists","—",IF(A6="All physicians","—",IF(A6="Occupational therapists",IFERROR(VLOOKUP(CONCATENATE($D$6,$A$6,$B$6,$C$6),OTProfileData!$A$2:$AR$1920,26,FALSE),"—"),IF(A6="Physiotherapists",IFERROR(VLOOKUP(CONCATENATE($D$6,$A$6,$B$6,$C$6),PTProfileData!$A$2:$BW$1802,26,FALSE),"—"),IF(A6="Pharmacists",IFERROR(VLOOKUP(CONCATENATE($D$6,$A$6,$B$6,$C$6),PHProfileData!$A$3:$AO$1868,28,FALSE),"—"),IF(A6="nurse practitioners",IFERROR(VLOOKUP(CONCATENATE($D$6,$A$6,$B$6,$C$6),NursProfileData!$A$2:$BZ$2066,27,FALSE),"—"),IF(A6="Registered nurses",IFERROR(VLOOKUP(CONCATENATE($D$6,$A$6,$B$6,$C$6),NursProfileData!$A$2:$BZ$2066,27,FALSE),"—"),IF(A6="Registered psychiatric nurses",IFERROR(VLOOKUP(CONCATENATE($D$6,$A$6,$B$6,$C$6),NursProfileData!$A$2:$BZ$2066,27,FALSE),"—"),IF(A6="Licensed practical nurses",IFERROR(VLOOKUP(CONCATENATE($D$6,$A$6,$B$6,$C$6),NursProfileData!$A$2:$BZ$2066,27,FALSE),"—"),"—")))))))))) -> 0 | D33: =IF(A6="Family medicine physicians","—",IF(A6="Specialists","—",IF(A6="All physicians","—",IF(A6="Occupational therapists",IFERROR(VLOOKUP(CONCATENATE($D$6,$A$6,$B$6,$C$6),OTProfileData!$A$2:$CB$1920,62,FALSE),"—"),IF(A6="Physiotherapists",IFERROR(VLOOKUP(CONCATENATE($D$6,$A$6,$B$6,$C$6),PTProfileData!$A$2:$BW$1802,59,FALSE),"—"),IF(A6="Pharmacists",IFERROR(VLOOKUP(CONCATENATE($D$6,$A$6,$B$6,$C$6),PHProfileData!$A$3:$BR$1868,59,FALSE),"—"),IF(A6="nurse practitioners",IFERROR(VLOOKUP(CONCATENATE($D$6,$A$6,$B$6,$C$6),NursProfileData!$A$2:$BZ$2066,62,FALSE),"—"),IF(A6="Registered nurses",IFERROR(VLOOKUP(CONCATENATE($D$6,$A$6,$B$6,$C$6),NursProfileData!$A$2:$BZ$2066,62,FALSE),"—"),IF(A6="Registered psychiatric nurses",IFERROR(VLOOKUP(CONCATENATE($D$6,$A$6,$B$6,$C$6),NursProfileData!$A$2:$BZ$2066,62,FALSE),"—"),IF(A6="Licensed practical nurses",IFERROR(VLOOKUP(CONCATENATE($D$6,$A$6,$B$6,$C$6),NursProfileData!$A$2:$BZ$2066,62,FALSE),"—"),"—")))))))))) -> 0
A34: =IF(OR(A6="Family medicine physicians",A6="Specialists",A6="All physicians",A6="Physiotherapists"),"—","Position") -> Position | B34: =IF(A6="Family medicine physicians","—",IF(A6="Specialists","—",IF(A6="All physicians","—",IF(A6="Occupational therapists","Direct service provider",IF(A6="Physiotherapists","—",IF(A6="Pharmacists","Pharmacy owner/manager",IF(A6="nurse practitioners","Staff nurse",IF(A6="Registered nurses","Staff nurse",IF(A6="Registered psychiatric nurses","Staff nurse",IF(A6="Licensed practical nurses","Staff nurse","-")))))))))) -> Staff nurse | C34: =IF(A6="Family medicine physicians","—",IF(A6="Specialists","—",IF(A6="All physicians","—",IF(A6="Occupational therapists",IFERROR(VLOOKUP(CONCATENATE($D$6,$A$6,$B$6,$C$6),OTProfileData!$A$2:$AR$1920,30,FALSE),"—"),IF(A6="Physiotherapists","—",IF(A6="Pharmacists",IFERROR(VLOOKUP(CONCATENATE($D$6,$A$6,$B$6,$C$6),PHProfileData!$A$3:$AO$1868,29,FALSE),"—"),IF(A6="nurse practitioners",IFERROR(VLOOKUP(CONCATENATE($D$6,$A$6,$B$6,$C$6),NursProfileData!$A$2:$BZ$2066,29,FALSE),"—"),IF(A6="Registered nurses",IFERROR(VLOOKUP(CONCATENATE($D$6,$A$6,$B$6,$C$6),NursProfileData!$A$2:$BZ$2066,29,FALSE),"—"),IF(A6="Registered psychiatric nurses",IFERROR(VLOOKUP(CONCATENATE($D$6,$A$6,$B$6,$C$6),NursProfileData!$A$2:$BZ$2066,29,FALSE),"—"),IF(A6="Licensed practical nurses",IFERROR(VLOOKUP(CONCATENATE($D$6,$A$6,$B$6,$C$6),NursProfileData!$A$2:$BZ$2066,29,FALSE),"—"),"-")))))))))) -> 76674 | D34: =IF(A6="Family medicine physicians","—",IF(A6="Specialists","—",IF(A6="All physicians","—",IF(A6="Occupational therapists",IFERROR(VLOOKUP(CONCATENATE($D$6,$A$6,$B$6,$C$6),OTProfileData!$A$2:$CB$1920,66,FALSE),"—"),IF(A6="Physiotherapists","—",IF(A6="Pharmacists",IFERROR(VLOOKUP(CONCATENATE($D$6,$A$6,$B$6,$C$6),PHProfileData!$A$3:$BR$1868,60,FALSE),"—"),IF(A6="nurse practitioners",IFERROR(VLOOKUP(CONCATENATE($D$6,$A$6,$B$6,$C$6),NursProfileData!$A$2:$BZ$2066,66,FALSE),"—"),IF(A6="Registered nurses",IFERROR(VLOOKUP(CONCATENATE($D$6,$A$6,$B$6,$C$6),NursProfileData!$A$2:$BZ$2066,66,FALSE),"—"),IF(A6="Registered psychiatric nurses",IFERROR(VLOOKUP(CONCATENATE($D$6,$A$6,$B$6,$C$6),NursProfileData!$A$2:$BZ$2066,66,FALSE),"—"),IF(A6="Licensed practical nurses",IFERROR(VLOOKUP(CONCATENATE($D$6,$A$6,$B$6,$C$6),NursProfileData!$A$2:$BZ$2066,66,FALSE),"—"),"—")))))))))) -> 0.18892902
B35: =IF(A6="Family medicine physicians","—",IF(A6="Specialists","—",IF(A6="All physicians","—",IF(A6="Occupational therapists","Manager/leader/coordinator",IF(A6="Physiotherapists","—",IF(A6="Pharmacists","Staff pharmacist",IF(A6="nurse practitioners","Manager",IF(A6="Registered nurses","Manager",IF(A6="Registered psychiatric nurses","Manager",IF(A6="Licensed practical nurses","Manager","-")))))))))) -> Manager | C35: =IF(A6="Family medicine physicians","—",IF(A6="Specialists","—",IF(A6="All physicians","—",IF(A6="Occupational therapists",IFERROR(VLOOKUP(CONCATENATE($D$6,$A$6,$B$6,$C$6),OTProfileData!$A$2:$AR$1920,27,FALSE),"—"),IF(A6="Physiotherapists","—",IF(A6="Pharmacists",IFERROR(VLOOKUP(CONCATENATE($D$6,$A$6,$B$6,$C$6),PHProfileData!$A$3:$AO$1868,32,FALSE),"—"),IF(A6="nurse practitioners",IFERROR(VLOOKUP(CONCATENATE($D$6,$A$6,$B$6,$C$6),NursProfileData!$A$2:$BZ$2066,28,FALSE),"—"),IF(A6="Registered nurses",IFERROR(VLOOKUP(CONCATENATE($D$6,$A$6,$B$6,$C$6),NursProfileData!$A$2:$BZ$2066,28,FALSE),"—"),IF(A6="Registered psychiatric nurses",IFERROR(VLOOKUP(CONCATENATE($D$6,$A$6,$B$6,$C$6),NursProfileData!$A$2:$BZ$2066,28,FALSE),"—"),IF(A6="Licensed practical nurses",IFERROR(VLOOKUP(CONCATENATE($D$6,$A$6,$B$6,$C$6),NursProfileData!$A$2:$BZ$2066,28,FALSE),"—"),"—")))))))))) -> 5705 | D35: =IF(A6="Family medicine physicians","—",IF(A6="Specialists","—",IF(A6="All physicians","—",IF(A6="Occupational therapists",IFERROR(VLOOKUP(CONCATENATE($D$6,$A$6,$B$6,$C$6),OTProfileData!$A$2:$CB$1920,63,FALSE),"—"),IF(A6="Physiotherapists","—",IF(A6="Pharmacists",IFERROR(VLOOKUP(CONCATENATE($D$6,$A$6,$B$6,$C$6),PHProfileData!$A$3:$BR$1868,63,FALSE),"—"),IF(A6="nurse practitioners",IFERROR(VLOOKUP(CONCATENATE($D$6,$A$6,$B$6,$C$6),NursProfileData!$A$2:$BZ$2066,63,FALSE),"—"),IF(A6="Registered nurses",IFERROR(VLOOKUP(CONCATENATE($D$6,$A$6,$B$6,$C$6),NursProfileData!$A$2:$BZ$2066,63,FALSE),"—"),IF(A6="Registered psychiatric nurses",IFERROR(VLOOKUP(CONCATENATE($D$6,$A$6,$B$6,$C$6),NursProfileData!$A$2:$BZ$2066,63,FALSE),"—"),IF(A6="Licensed practical nurses",IFERROR(VLOOKUP(CONCATENATE($D$6,$A$6,$B$6,$C$6),NursProfileData!$A$2:$BZ$2066,63,FALSE),"—"),"—")))))))))) -> 0.056152127
B36: =IF(A6="Family medicine physicians","—",IF(A6="Specialists","—",IF(A6="All physicians","—",IF(A6="Occupational therapists","Other",IF(A6="Physiotherapists","—",IF(A6="Pharmacists","Other",IF(A6="nurse practitioners","Other",IF(A6="Registered nurses","Other",IF(A6="Registered psychiatric nurses","Other",IF(A6="Licensed practical nurses","Other","-")))))))))) -> Other | C36: =IF(A6="Family medicine physicians","—",IF(A6="Specialists","—",IF(A6="All physicians","—",IF(A6="Occupational therapists",IFERROR(VLOOKUP(CONCATENATE($D$6,$A$6,$B$6,$C$6),OTProfileData!$A$2:$AR$1920,29,FALSE),"—"),IF(A6="Physiotherapists","—",IF(A6="Pharmacists",IFERROR(VLOOKUP(CONCATENATE($D$6,$A$6,$B$6,$C$6),PHProfileData!$A$3:$AO$1868,31,FALSE),"—"),IF(A6="nurse practitioners",IFERROR(VLOOKUP(CONCATENATE($D$6,$A$6,$B$6,$C$6),NursProfileData!$A$2:$BZ$2066,31,FALSE),"—"),IF(A6="Registered nurses",IFERROR(VLOOKUP(CONCATENATE($D$6,$A$6,$B$6,$C$6),NursProfileData!$A$2:$BZ$2066,31,FALSE),"—"),IF(A6="Registered psychiatric nurses",IFERROR(VLOOKUP(CONCATENATE($D$6,$A$6,$B$6,$C$6),NursProfileData!$A$2:$BZ$2066,31,FALSE),"—"),IF(A6="Licensed practical nurses",IFERROR(VLOOKUP(CONCATENATE($D$6,$A$6,$B$6,$C$6),NursProfileData!$A$2:$BZ$2066,31,FALSE),"—"),"—")))))))))) -> 19195 | D36: =IF(A6="Family medicine physicians","—",IF(A6="Specialists","—",IF(A6="All physicians","—",IF(A6="Occupational therapists",IFERROR(VLOOKUP(CONCATENATE($D$6,$A$6,$B$6,$C$6),OTProfileData!$A$2:$CB$1920,65,FALSE),"—"),IF(A6="Physiotherapists","—",IF(A6="Pharmacists",IFERROR(VLOOKUP(CONCATENATE($D$6,$A$6,$B$6,$C$6),PHProfileData!$A$3:$BR$1868,62,FALSE),"—"),IF(A6="nurse practitioners",IFERROR(VLOOKUP(CONCATENATE($D$6,$A$6,$B$6,$C$6),NursProfileData!$A$2:$BZ$2066,65,FALSE),"—"),IF(A6="Registered nurses",IFERROR(VLOOKUP(CONCATENATE($D$6,$A$6,$B$6,$C$6),NursProfileData!$A$2:$BZ$2066,65,FALSE),"—"),IF(A6="Registered psychiatric nurses",IFERROR(VLOOKUP(CONCATENATE($D$6,$A$6,$B$6,$C$6),NursProfileData!$A$2:$BZ$2066,65,FALSE),"—"),IF(A6="Licensed practical nurses",IFERROR(VLOOKUP(CONCATENATE($D$6,$A$6,$B$6,$C$6),NursProfileData!$A$2:$BZ$2066,65,FALSE),"—"),"—")))))))))) -> 0.00024606541
B37: =IF(A6="Family medicine physicians","—",IF(A6="Specialists","—",IF(A6="All physicians","—",IF(A6="Occupational therapists","Not stated",IF(A6="Physiotherapists","—",IF(A6="Pharmacists","Not stated",IF(A6="nurse practitioners","Not stated",IF(A6="Registered nurses","Not stated",IF(A6="Registered psychiatric nurses","Not stated",IF(A6="Licensed practical nurses","Not stated","-")))))))))) -> Not stated | C37: =IF(A6="Family medicine physicians","—",IF(A6="Specialists","—",IF(A6="All physicians","—",IF(A6="Occupational therapists",IFERROR(VLOOKUP(CONCATENATE($D$6,$A$6,$B$6,$C$6),OTProfileData!$A$2:$AR$1920,28,FALSE),"—"),IF(A6="Physiotherapists","—",IF(A6="Pharmacists",IFERROR(VLOOKUP(CONCATENATE($D$6,$A$6,$B$6,$C$6),PHProfileData!$A$3:$AO$1868,30,FALSE),"—"),IF(A6="nurse practitioners",IFERROR(VLOOKUP(CONCATENATE($D$6,$A$6,$B$6,$C$6),NursProfileData!$A$2:$BZ$2066,30,FALSE),"—"),IF(A6="Registered nurses",IFERROR(VLOOKUP(CONCATENATE($D$6,$A$6,$B$6,$C$6),NursProfileData!$A$2:$BZ$2066,30,FALSE),"—"),IF(A6="Registered psychiatric nurses",IFERROR(VLOOKUP(CONCATENATE($D$6,$A$6,$B$6,$C$6),NursProfileData!$A$2:$BZ$2066,30,FALSE),"—"),IF(A6="Licensed practical nurses",IFERROR(VLOOKUP(CONCATENATE($D$6,$A$6,$B$6,$C$6),NursProfileData!$A$2:$BZ$2066,30,FALSE),"—"),"—")))))))))) -> 25 | D37: =IF(A6="Family medicine physicians","—",IF(A6="Specialists","—",IF(A6="All physicians","—",IF(A6="Occupational therapists",IFERROR(VLOOKUP(CONCATENATE($D$6,$A$6,$B$6,$C$6),OTProfileData!$A$2:$CB$1920,64,FALSE),"—"),IF(A6="Physiotherapists","—",IF(A6="Pharmacists",IFERROR(VLOOKUP(CONCATENATE($D$6,$A$6,$B$6,$C$6),PHProfileData!$A$3:$BR$1868,61,FALSE),"—"),IF(A6="nurse practitioners",IFERROR(VLOOKUP(CONCATENATE($D$6,$A$6,$B$6,$C$6),NursProfileData!$A$2:$BZ$2066,64,FALSE),"—"),IF(A6="Registered nurses",IFERROR(VLOOKUP(CONCATENATE($D$6,$A$6,$B$6,$C$6),NursProfileData!$A$2:$BZ$2066,64,FALSE),"—"),IF(A6="Registered psychiatric nurses",IFERROR(VLOOKUP(CONCATENATE($D$6,$A$6,$B$6,$C$6),NursProfileData!$A$2:$BZ$2066,64,FALSE),"—"),IF(A6="Licensed practical nurses",IFERROR(VLOOKUP(CONCATENATE($D$6,$A$6,$B$6,$C$6),NursProfileData!$A$2:$BZ$2066,64,FALSE),"—"),"—")))))))))) -> 0.75467278
A38: =IF(OR(A6="Family medicine physicians",A6="Specialists",A6="All physicians",A6="Pharmacists"),"—","Area of Responsibility") -> Area of Responsibility | B38: =IF(A6="Family medicine physicians","—",IF(A6="Specialists","—",IF(A6="All physicians","—",IF(A6="Occupational therapists","Direct service",IF(A6="Physiotherapists","Direct service",IF(A6="Pharmacists","—",IF(A6="nurse practitioners","Direct care",IF(A6="Registered nurses","Direct care",IF(A6="Registered psychiatric nurses","Direct care",IF(A6="Licensed practical nurses","Direct care","—")))))))))) -> Direct care | C38: =IF(A6="Family medicine physicians","—",IF(A6="Specialists","—",IF(A6="All physicians","—",IF(A6="Occupational therapists",IFERROR(VLOOKUP(CONCATENATE($D$6,$A$6,$B$6,$C$6),OTProfileData!$A$2:$AR$1920,32,FALSE),"—"),IF(A6="Physiotherapists",IFERROR(VLOOKUP(CONCATENATE($D$6,$A$6,$B$6,$C$6),PTProfileData!$A$3:$BV$1803,31,FALSE),"—"),IF(A6="Pharmacists","—",IF(A6="nurse practitioners",IFERROR(VLOOKUP(CONCATENATE($D$6,$A$6,$B$6,$C$6),NursProfileData!$A$2:$BZ$2066,33,FALSE),"—"),IF(A6="Registered nurses",IFERROR(VLOOKUP(CONCATENATE($D$6,$A$6,$B$6,$C$6),NursProfileData!$A$2:$BZ$2066,33,FALSE),"—"),IF(A6="Registered psychiatric nurses",IFERROR(VLOOKUP(CONCATENATE($D$6,$A$6,$B$6,$C$6),NursProfileData!$A$2:$BZ$2066,33,FALSE),"—"),IF(A6="Licensed practical nurses",IFERROR(VLOOKUP(CONCATENATE($D$6,$A$6,$B$6,$C$6),NursProfileData!$A$2:$BZ$2066,33,FALSE),"—"),"-")))))))))) -> 92238 | D38: =IF(A6="Family medicine physicians","—",IF(A6="Specialists","—",IF(A6="All physicians","—",IF(A6="Occupational therapists",IFERROR(VLOOKUP(CONCATENATE($D$6,$A$6,$B$6,$C$6),OTProfileData!$A$2:$CB$1920,68,FALSE),"—"),IF(A6="Physiotherapists",IFERROR(VLOOKUP(CONCATENATE($D$6,$A$6,$B$6,$C$6),PTProfileData!$A$2:$BW$1802,64,FALSE),"—"),IF(A6="Pharmacists","—",IF(A6="nurse practitioners",IFERROR(VLOOKUP(CONCATENATE($D$6,$A$6,$B$6,$C$6),NursProfileData!$A$2:$BZ$2066,68,FALSE),"—"),IF(A6="Registered nurses",IFERROR(VLOOKUP(CONCATENATE($D$6,$A$6,$B$6,$C$6),NursProfileData!$A$2:$BZ$2066,68,FALSE),"—"),IF(A6="Registered psychiatric nurses",IFERROR(VLOOKUP(CONCATENATE($D$6,$A$6,$B$6,$C$6),NursProfileData!$A$2:$BZ$2066,68,FALSE),"—"),IF(A6="Licensed practical nurses",IFERROR(VLOOKUP(CONCATENATE($D$6,$A$6,$B$6,$C$6),NursProfileData!$A$2:$BZ$2066,68,FALSE),"—"),"-")))))))))) -> 0.90786327
B39: =IF(A6="Family medicine physicians","—",IF(A6="Specialists","—",IF(A6="All physicians","—",IF(A6="Occupational therapists","Client management",IF(A6="Physiotherapists","Client management",IF(A6="Pharmacists","—",IF(A6="nurse practitioners","Administration",IF(A6="Registered nurses","Administration",IF(A6="Registered psychiatric nurses","Administration",IF(A6="Licensed practical nurses","Administration","—")))))))))) -> Administration | C39: =IF(A6="Family medicine physicians","—",IF(A6="Specialists","—",IF(A6="All physicians","—",IF(A6="Occupational therapists",IFERROR(VLOOKUP(CONCATENATE($D$6,$A$6,$B$6,$C$6),OTProfileData!$A$2:$AR$1920,33,FALSE),"—"),IF(A6="Physiotherapists",IFERROR(VLOOKUP(CONCATENATE($D$6,$A$6,$B$6,$C$6),PTProfileData!$A$2:$AR$1802,29,FALSE),"—"),IF(A6="Pharmacists","—",IF(A6="nurse practitioners",IFERROR(VLOOKUP(CONCATENATE($D$6,$A$6,$B$6,$C$6),NursProfileData!$A$2:$BZ$2066,32,FALSE),"—"),IF(A6="Registered nurses",IFERROR(VLOOKUP(CONCATENATE($D$6,$A$6,$B$6,$C$6),NursProfileData!$A$2:$BZ$2066,32,FALSE),"—"),IF(A6="Registered psychiatric nurses",IFERROR(VLOOKUP(CONCATENATE($D$6,$A$6,$B$6,$C$6),NursProfileData!$A$2:$BZ$2066,32,FALSE),"—"),IF(A6="Licensed practical nurses",IFERROR(VLOOKUP(CONCATENATE($D$6,$A$6,$B$6,$C$6),NursProfileData!$A$2:$BZ$2066,32,FALSE),"—"),"—")))))))))) -> 6942 | D39: =IF(A6="Family medicine physicians","—",IF(A6="Specialists","—",IF(A6="All physicians","—",IF(A6="Occupational therapists",IFERROR(VLOOKUP(CONCATENATE($D$6,$A$6,$B$6,$C$6),OTProfileData!$A$2:$CB$1920,69,FALSE),"—"),IF(A6="Physiotherapists",IFERROR(VLOOKUP(CONCATENATE($D$6,$A$6,$B$6,$C$6),PTProfileData!$A$2:$BW$1802,62,FALSE),"—"),IF(A6="Pharmacists","—",IF(A6="nurse practitioners",IFERROR(VLOOKUP(CONCATENATE($D$6,$A$6,$B$6,$C$6),NursProfileData!$A$2:$BZ$2066,67,FALSE),"—"),IF(A6="Registered nurses",IFERROR(VLOOKUP(CONCATENATE($D$6,$A$6,$B$6,$C$6),NursProfileData!$A$2:$BZ$2066,67,FALSE),"—"),IF(A6="Registered psychiatric nurses",IFERROR(VLOOKUP(CONCATENATE($D$6,$A$6,$B$6,$C$6),NursProfileData!$A$2:$BZ$2066,67,FALSE),"—"),IF(A6="Licensed practical nurses",IFERROR(VLOOKUP(CONCATENATE($D$6,$A$6,$B$6,$C$6),NursProfileData!$A$2:$BZ$2066,67,FALSE),"—"),"—")))))))))) -> 0.068327444
B40: =IF(A6="Family medicine physicians","—",IF(A6="Specialists","—",IF(A6="All physicians","—",IF(A6="Occupational therapists","Administration",IF(A6="Physiotherapists","Administration",IF(A6="Pharmacists","—",IF(A6="nurse practitioners","Education",IF(A6="Registered nurses","Education",IF(A6="Registered psychiatric nurses","Education",IF(A6="Licensed practical nurses","Education","-")))))))))) -> Education | C40: =IF(A6="Family medicine physicians","—",IF(A6="Specialists","—",IF(A6="All physicians","—",IF(A6="Occupational therapists",IFERROR(VLOOKUP(CONCATENATE($D$6,$A$6,$B$6,$C$6),OTProfileData!$A$2:$AR$1920,31,FALSE),"—"),IF(A6="Physiotherapists",IFERROR(VLOOKUP(CONCATENATE($D$6,$A$6,$B$6,$C$6),PTProfileData!$A$2:$AR$1802,30,FALSE),"—"),IF(A6="Pharmacists","—",IF(A6="nurse practitioners",IFERROR(VLOOKUP(CONCATENATE($D$6,$A$6,$B$6,$C$6),NursProfileData!$A$2:$BZ$2066,34,FALSE),"—"),IF(A6="Registered nurses",IFERROR(VLOOKUP(CONCATENATE($D$6,$A$6,$B$6,$C$6),NursProfileData!$A$2:$BZ$2066,34,FALSE),"—"),IF(A6="Registered psychiatric nurses",IFERROR(VLOOKUP(CONCATENATE($D$6,$A$6,$B$6,$C$6),NursProfileData!$A$2:$BZ$2066,34,FALSE),"—"),IF(A6="Licensed practical nurses",IFERROR(VLOOKUP(CONCATENATE($D$6,$A$6,$B$6,$C$6),NursProfileData!$A$2:$BZ$2066,34,FALSE),"—"),"-")))))))))) -> 2329 | D40: =IF(A6="Family medicine physicians","—",IF(A6="Specialists","—",IF(A6="All physicians","—",IF(A6="Occupational therapists",IFERROR(VLOOKUP(CONCATENATE($D$6,$A$6,$B$6,$C$6),OTProfileData!$A$2:$CB$1920,67,FALSE),"—"),IF(A6="Physiotherapists",IFERROR(VLOOKUP(CONCATENATE($D$6,$A$6,$B$6,$C$6),PTProfileData!$A$2:$BW$1802,63,FALSE),"—"),IF(A6="Pharmacists","—",IF(A6="nurse practitioners",IFERROR(VLOOKUP(CONCATENATE($D$6,$A$6,$B$6,$C$6),NursProfileData!$A$2:$BZ$2066,69,FALSE),"—"),IF(A6="Registered nurses",IFERROR(VLOOKUP(CONCATENATE($D$6,$A$6,$B$6,$C$6),NursProfileData!$A$2:$BZ$2066,69,FALSE),"—"),IF(A6="Registered psychiatric nurses",IFERROR(VLOOKUP(CONCATENATE($D$6,$A$6,$B$6,$C$6),NursProfileData!$A$2:$BZ$2066,69,FALSE),"—"),IF(A6="Licensed practical nurses",IFERROR(VLOOKUP(CONCATENATE($D$6,$A$6,$B$6,$C$6),NursProfileData!$A$2:$BZ$2066,69,FALSE),"—"),"—")))))))))) -> 0.022923454
B41: =IF(A6="Family medicine physicians","—",IF(A6="Specialists","—",IF(A6="All physicians","—",IF(A6="Occupational therapists","Education",IF(A6="Physiotherapists","Education",IF(A6="Pharmacists","—",IF(A6="nurse practitioners","Research",IF(A6="Registered nurses","Research",IF(A6="Registered psychiatric nurses","Research",IF(A6="Licensed practical nurses","Research","-")))))))))) -> Research | C41: =IF(A6="Family medicine physicians","—",IF(A6="Specialists","—",IF(A6="All physicians","—",IF(A6="Occupational therapists",IFERROR(VLOOKUP(CONCATENATE($D$6,$A$6,$B$6,$C$6),OTProfileData!$A$2:$AR$1920,34,FALSE),"—"),IF(A6="Physiotherapists",IFERROR(VLOOKUP(CONCATENATE($D$6,$A$6,$B$6,$C$6),PTProfileData!$A$2:$AR$1802,32,FALSE),"—"),IF(A6="Pharmacists","—",IF(A6="nurse practitioners",IFERROR(VLOOKUP(CONCATENATE($D$6,$A$6,$B$6,$C$6),NursProfileData!$A$2:$BZ$2066,35,FALSE),"—"),IF(A6="Registered nurses",IFERROR(VLOOKUP(CONCATENATE($D$6,$A$6,$B$6,$C$6),NursProfileData!$A$2:$BZ$2066,35,FALSE),"—"),IF(A6="Registered psychiatric nurses",IFERROR(VLOOKUP(CONCATENATE($D$6,$A$6,$B$6,$C$6),NursProfileData!$A$2:$BZ$2066,35,FALSE),"—"),IF(A6="Licensed practical nurses",IFERROR(VLOOKUP(CONCATENATE($D$6,$A$6,$B$6,$C$6),NursProfileData!$A$2:$BZ$2066,35,FALSE),"—"),"-")))))))))) -> — | D41: =IF(A6="Family medicine physicians","—",IF(A6="Specialists","—",IF(A6="All physicians","—",IF(A6="Occupational therapists",IFERROR(VLOOKUP(CONCATENATE($D$6,$A$6,$B$6,$C$6),OTProfileData!$A$2:$CB$1920,70,FALSE),"—"),IF(A6="Physiotherapists",IFERROR(VLOOKUP(CONCATENATE($D$6,$A$6,$B$6,$C$6),PTProfileData!$A$2:$BW$1802,65,FALSE),"—"),IF(A6="Pharmacists","—",IF(A6="nurse practitioners",IFERROR(VLOOKUP(CONCATENATE($D$6,$A$6,$B$6,$C$6),NursProfileData!$A$2:$BZ$2066,70,FALSE),"—"),IF(A6="Registered nurses",IFERROR(VLOOKUP(CONCATENATE($D$6,$A$6,$B$6,$C$6),NursProfileData!$A$2:$BZ$2066,70,FALSE),"—"),IF(A6="Registered psychiatric nurses",IFERROR(VLOOKUP(CONCATENATE($D$6,$A$6,$B$6,$C$6),NursProfileData!$A$2:$BZ$2066,70,FALSE),"—"),IF(A6="Licensed practical nurses",IFERROR(VLOOKUP(CONCATENATE($D$6,$A$6,$B$6,$C$6),NursProfileData!$A$2:$BZ$2066,70,FALSE),"—"),"-")))))))))) -> 0
B42: =IF(A6="Family medicine physicians","—",IF(A6="Specialists","—",IF(A6="All physicians","—",IF(A6="Occupational therapists","Research",IF(A6="Physiotherapists","Research",IF(A6="Pharmacists","—",IF(A6="nurse practitioners","Not stated",IF(A6="Registered nurses","Not stated",IF(A6="Registered psychiatric nurses","Not stated",IF(A6="Licensed practical nurses","Not stated","-")))))))))) -> Not stated | C42: =IF(A6="Family medicine physicians","—",IF(A6="Specialists","—",IF(A6="All physicians","—",IF(A6="Occupational therapists",IFERROR(VLOOKUP(CONCATENATE($D$6,$A$6,$B$6,$C$6),OTProfileData!$A$2:$AR$1920,35,FALSE),"—"),IF(A6="Physiotherapists",IFERROR(VLOOKUP(CONCATENATE($D$6,$A$6,$B$6,$C$6),PTProfileData!$A$2:$AR$1802,33,FALSE),"—"),IF(A6="Pharmacists","—",IF(A6="nurse practitioners",IFERROR(VLOOKUP(CONCATENATE($D$6,$A$6,$B$6,$C$6),NursProfileData!$A$2:$BZ$2066,36,FALSE),"—"),IF(A6="Registered nurses",IFERROR(VLOOKUP(CONCATENATE($D$6,$A$6,$B$6,$C$6),NursProfileData!$A$2:$BZ$2066,36,FALSE),"—"),IF(A6="Registered psychiatric nurses",IFERROR(VLOOKUP(CONCATENATE($D$6,$A$6,$B$6,$C$6),NursProfileData!$A$2:$BZ$2066,36,FALSE),"—"),IF(A6="Licensed practical nurses",IFERROR(VLOOKUP(CONCATENATE($D$6,$A$6,$B$6,$C$6),NursProfileData!$A$2:$BZ$2066,36,FALSE),"—"),"-")))))))))) -> 90 | D42: =IF(A6="Family medicine physicians","—",IF(A6="Specialists","—",IF(A6="All physicians","—",IF(A6="Occupational therapists",IFERROR(VLOOKUP(CONCATENATE($D$6,$A$6,$B$6,$C$6),OTProfileData!$A$2:$CB$1920,71,FALSE),"—"),IF(A6="Physiotherapists",IFERROR(VLOOKUP(CONCATENATE($D$6,$A$6,$B$6,$C$6),PTProfileData!$A$2:$BW$1802,66,FALSE),"—"),IF(A6="Pharmacists","—",IF(A6="nurse practitioners",IFERROR(VLOOKUP(CONCATENATE($D$6,$A$6,$B$6,$C$6),NursProfileData!$A$2:$BZ$2066,71,FALSE),"—"),IF(A6="Registered nurses",IFERROR(VLOOKUP(CONCATENATE($D$6,$A$6,$B$6,$C$6),NursProfileData!$A$2:$BZ$2066,71,FALSE),"—"),IF(A6="Registered psychiatric nurses",IFERROR(VLOOKUP(CONCATENATE($D$6,$A$6,$B$6,$C$6),NursProfileData!$A$2:$BZ$2066,71,FALSE),"—"),IF(A6="Licensed practical nurses",IFERROR(VLOOKUP(CONCATENATE($D$6,$A$6,$B$6,$C$6),NursProfileData!$A$2:$BZ$2066,71,FALSE),"—"),"-")))))))))) -> 0.00088583549
B43: =IF(A6="Family medicine physicians","—",IF(A6="Specialists","—",IF(A6="All physicians","—",IF(A6="Occupational therapists","Other",IF(A6="Physiotherapists","Sales",IF(A6="Pharmacists","—",IF(A6="nurse practitioners","—",IF(A6="Registered nurses","—",IF(A6="Registered psychiatric nurses","—",IF(A6="Licensed practical nurses","—","-")))))))))) -> — | C43: =IF(A6="Family medicine physicians","—",IF(A6="Specialists","—",IF(A6="All physicians","—",IF(A6="Occupational therapists",IFERROR(VLOOKUP(CONCATENATE($D$6,$A$6,$B$6,$C$6),OTProfileData!$A$2:$AR$1920,36,FALSE),"—"),IF(A6="Physiotherapists",IFERROR(VLOOKUP(CONCATENATE($D$6,$A$6,$B$6,$C$6),PTProfileData!$A$2:$AR$1802,28,FALSE),"—"),IF(A6="Pharmacists","—",IF(A6="nurse practitioners","—",IF(A6="Registered nurses","—",IF(A6="Registered psychiatric nurses","—",IF(A6="Licensed practical nurses","—","-")))))))))) -> — | D43: =IF(A6="Family medicine physicians","—",IF(A6="Specialists","—",IF(A6="All physicians","—",IF(A6="Occupational therapists",IFERROR(VLOOKUP(CONCATENATE($D$6,$A$6,$B$6,$C$6),OTProfileData!$A$2:$CB$1920,72,FALSE),"—"),IF(A6="Physiotherapists",IFERROR(VLOOKUP(CONCATENATE($D$6,$A$6,$B$6,$C$6),PTProfileData!$A$2:$BW$1802,61,FALSE),"—"),IF(A6="Pharmacists","—",IF(A6="nurse practitioners","—",IF(A6="Registered nurses","—",IF(A6="Registered psychiatric nurses","—",IF(A6="Licensed practical nurses","—","-")))))))))) -> —
B44: =IF(A6="Family medicine physicians","—",IF(A6="Specialists","—",IF(A6="All physicians","—",IF(A6="Occupational therapists","Not stated",IF(A6="Physiotherapists","Other",IF(A6="Pharmacists","—",IF(A6="nurse practitioners","—",IF(A6="Registered nurses","—",IF(A6="Registered psychiatric nurses","—",IF(A6="Licensed practical nurses","—","-")))))))))) -> — | C44: =IF(A6="Family medicine physicians","—",IF(A6="Specialists","—",IF(A6="All physicians","—",IF(A6="Occupational therapists",IFERROR(VLOOKUP(CONCATENATE($D$6,$A$6,$B$6,$C$6),OTProfileData!$A$2:$AR$1920,37,FALSE),"—"),IF(A6="Physiotherapists",IFERROR(VLOOKUP(CONCATENATE($D$6,$A$6,$B$6,$C$6),PTProfileData!$A$2:$AR$1802,27,FALSE),"—"),IF(A6="Pharmacists","—",IF(A6="nurse practitioners","—",IF(A6="Registered nurses","—",IF(A6="Registered psychiatric nurses","—",IF(A6="Licensed practical nurses","—","-")))))))))) -> — | D44: =IF(A6="Family medicine physicians","—",IF(A6="Specialists","—",IF(A6="All physicians","—",IF(A6="Occupational therapists",IFERROR(VLOOKUP(CONCATENATE($D$6,$A$6,$B$6,$C$6),OTProfileData!$A$2:$CB$1920,73,FALSE),"—"),IF(A6="Physiotherapists",IFERROR(VLOOKUP(CONCATENATE($D$6,$A$6,$B$6,$C$6),PTProfileData!$A$2:$BW$1802,60,FALSE),"—"),IF(A6="Pharmacists","—",IF(A6="nurse practitioners","—",IF(A6="Registered nurses","—",IF(A6="Registered psychiatric nurses","—",IF(A6="Licensed practical nurses","—","-")))))))))) -> —
B45: =IF(A6="Family medicine physicians","—",IF(A6="Specialists","—",IF(A6="All physicians","—",IF(A6="Occupational therapists","—",IF(A6="Physiotherapists","Not stated",IF(A6="Pharmacists","—",IF(A6="nurse practitioners","—",IF(A6="Registered nurses","—",IF(A6="Registered psychiatric nurses","—",IF(A6="Licensed practical nurses","—","-")))))))))) -> — | C45: =IF(A6="Family medicine physicians","—",IF(A6="Specialists","—",IF(A6="All physicians","—",IF(A6="Occupational therapists","—",IF(A6="Physiotherapists",IFERROR(VLOOKUP(CONCATENATE($D$6,$A$6,$B$6,$C$6),PTProfileData!$A$2:$AR$1802,34,FALSE),"—"),IF(A6="Pharmacists","—",IF(A6="nurse practitioners","—",IF(A6="Registered nurses","—",IF(A6="Registered psychiatric nurses","—",IF(A6="Licensed practical nurses","—","-")))))))))) -> — | D45: =IF(A6="Family medicine physicians","—",IF(A6="Specialists","—",IF(A6="All physicians","—",IF(A6="Occupational therapists","—",IF(A6="Physiotherapists",IFERROR(VLOOKUP(CONCATENATE($D$6,$A$6,$B$6,$C$6),PTProfileData!$A$2:$BW$1802,67,FALSE),"—"),IF(A6="Pharmacists","—",IF(A6="nurse practitioners","—",IF(A6="Registered nurses","—",IF(A6="Registered psychiatric nurses","—",IF(A6="Licensed practical nurses","—","-")))))))))) -> —
A46: Geographic Designation | B46: Urban | C46: =IF(A6="Family medicine physicians",IFERROR(VLOOKUP(CONCATENATE($D$6,$A$6,$B$6),Phyprofile!A3:AU464,25,FALSE),"—"),IF(A6="Specialists",IFERROR(VLOOKUP(CONCATENATE($D$6,$A$6,$B$6),Phyprofile!A3:AU464,25,FALSE),"—"),IF(A6="All physicians",IFERROR(VLOOKUP(CONCATENATE($D$6,$A$6,$B$6),Phyprofile!A3:AU464,25,FALSE),"—"),IF(A6="Occupational therapists",IFERROR(VLOOKUP(CONCATENATE($D$6,$A$6,$B$6,$C$6),OTProfileData!$A$2:$AR$1920,39,FALSE),"—"),IF(A6="Physiotherapists",IFERROR(VLOOKUP(CONCATENATE($D$6,$A$6,$B$6,$C$6),PTProfileData!$A$2:$BW$1802,35,FALSE),"—"),IF(A6="Pharmacists",IFERROR(VLOOKUP(CONCATENATE($D$6,$A$6,$B$6,$C$6),PHProfileData!$A$3:$AO$1868,33,FALSE),"—"),IF(A6="nurse practitioners",IFERROR(VLOOKUP(CONCATENATE($D$6,$A$6,$B$6,$C$6),NursProfileData!$A$2:$BZ$2066,38,FALSE),"—"),IF(A6="Registered nurses",IFERROR(VLOOKUP(CONCATENATE($D$6,$A$6,$B$6,$C$6),NursProfileData!$A$2:$BZ$2066,38,FALSE),"—"),IF(A6="Registered psychiatric nurses",IFERROR(VLOOKUP(CONCATENATE($D$6,$A$6,$B$6,$C$6),NursProfileData!$A$2:$BZ$2066,38,FALSE),"—"),IF(A6="Licensed practical nurses",IFERROR(VLOOKUP(CONCATENATE($D$6,$A$6,$B$6,$C$6),NursProfileData!$A$2:$BZ$2066,38,FALSE),"—"),"-")))))))))) -> 96654 | D46: =IF(A6="Family medicine physicians",IFERROR(VLOOKUP(CONCATENATE($D$6,$A$6,$B$6),Phyprofile!A3:AU464,46,FALSE),"—"),IF(A6="Specialists",IFERROR(VLOOKUP(CONCATENATE($D$6,$A$6,$B$6),Phyprofile!A3:AU464,46,FALSE),"—"),IF(A6="All physicians",IFERROR(VLOOKUP(CONCATENATE($D$6,$A$6,$B$6),Phyprofile!A3:AU464,46,FALSE),"—"),IF(A6="Occupational therapists",IFERROR(VLOOKUP(CONCATENATE($D$6,$A$6,$B$6,$C$6),OTProfileData!$A$2:$CB$1920,75,FALSE),"—"),IF(A6="Physiotherapists",IFERROR(VLOOKUP(CONCATENATE($D$6,$A$6,$B$6,$C$6),PTProfileData!$A$2:$BW$1802,68,FALSE),"—"),IF(A6="Pharmacists",IFERROR(VLOOKUP(CONCATENATE($D$6,$A$6,$B$6,$C$6),PHProfileData!$A$3:$BR$1868,64,FALSE),"—"),IF(A6="nurse practitioners",IFERROR(VLOOKUP(CONCATENATE($D$6,$A$6,$B$6,$C$6),NursProfileData!$A$2:$BZ$2066,73,FALSE),"—"),IF(A6="Registered nurses",IFERROR(VLOOKUP(CONCATENATE($D$6,$A$6,$B$6,$C$6),NursProfileData!$A$2:$BZ$2066,73,FALSE),"—"),IF(A6="Registered psychiatric nurses",IFERROR(VLOOKUP(CONCATENATE($D$6,$A$6,$B$6,$C$6),NursProfileData!$A$2:$BZ$2066,73,FALSE),"—"),IF(A6="Licensed practical nurses",IFERROR(VLOOKUP(CONCATENATE($D$6,$A$6,$B$6,$C$6),NursProfileData!$A$2:$BZ$2066,73,FALSE),"—"),"—")))))))))) -> 0.95132826
B47: Rural/remote | C47: =IF(A6="Family medicine physicians",IFERROR(VLOOKUP(CONCATENATE($D$6,$A$6,$B$6),Phyprofile!A3:AU464,24,FALSE),"—"),IF(A6="Specialists",IFERROR(VLOOKUP(CONCATENATE($D$6,$A$6,$B$6),Phyprofile!A3:AU464,24,FALSE),"—"),IF(A6="All physicians",IFERROR(VLOOKUP(CONCATENATE($D$6,$A$6,$B$6),Phyprofile!A3:AU464,24,FALSE),"—"),IF(A6="Occupational therapists",IFERROR(VLOOKUP(CONCATENATE($D$6,$A$6,$B$6,$C$6),OTProfileData!$A$2:$AR$1920,38,FALSE),"—"),IF(A6="Physiotherapists",IFERROR(VLOOKUP(CONCATENATE($D$6,$A$6,$B$6,$C$6),PTProfileData!$A$2:$BW$1802,36,FALSE),"—"),IF(A6="Pharmacists",IFERROR(VLOOKUP(CONCATENATE($D$6,$A$6,$B$6,$C$6),PHProfileData!$A$3:$AO$1868,34,FALSE),"—"),IF(A6="nurse practitioners",IFERROR(VLOOKUP(CONCATENATE($D$6,$A$6,$B$6,$C$6),NursProfileData!$A$2:$BZ$2066,37,FALSE),"—"),IF(A6="Registered nurses",IFERROR(VLOOKUP(CONCATENATE($D$6,$A$6,$B$6,$C$6),NursProfileData!$A$2:$BZ$2066,37,FALSE),"—"),IF(A6="Registered psychiatric nurses",IFERROR(VLOOKUP(CONCATENATE($D$6,$A$6,$B$6,$C$6),NursProfileData!$A$2:$BZ$2066,37,FALSE),"—"),IF(A6="Licensed practical nurses",IFERROR(VLOOKUP(CONCATENATE($D$6,$A$6,$B$6,$C$6),NursProfileData!$A$2:$BZ$2066,37,FALSE),"—"),"-")))))))))) -> 4922 | D47: =IF(A6="Family medicine physicians",IFERROR(VLOOKUP(CONCATENATE($D$6,$A$6,$B$6),Phyprofile!A3:AU464,45,FALSE),"—"),IF(A6="Specialists",IFERROR(VLOOKUP(CONCATENATE($D$6,$A$6,$B$6),Phyprofile!A3:AU464,45,FALSE),"—"),IF(A6="All physicians",IFERROR(VLOOKUP(CONCATENATE($D$6,$A$6,$B$6),Phyprofile!A3:AU464,45,FALSE),"—"),IF(A6="Occupational therapists",IFERROR(VLOOKUP(CONCATENATE($D$6,$A$6,$B$6,$C$6),OTProfileData!$A$2:$CB$1920,74,FALSE),"—"),IF(A6="Physiotherapists",IFERROR(VLOOKUP(CONCATENATE($D$6,$A$6,$B$6,$C$6),PTProfileData!$A$2:$BW$1802,69,FALSE),"—"),IF(A6="Pharmacists",IFERROR(VLOOKUP(CONCATENATE($D$6,$A$6,$B$6,$C$6),PHProfileData!$A$3:$BR$1868,65,FALSE),"—"),IF(A6="nurse practitioners",IFERROR(VLOOKUP(CONCATENATE($D$6,$A$6,$B$6,$C$6),NursProfileData!$A$2:$BZ$2066,72,FALSE),"—"),IF(A6="Registered nurses",IFERROR(VLOOKUP(CONCATENATE($D$6,$A$6,$B$6,$C$6),NursProfileData!$A$2:$BZ$2066,72,FALSE),"—"),IF(A6="Registered psychiatric nurses",IFERROR(VLOOKUP(CONCATENATE($D$6,$A$6,$B$6,$C$6),NursProfileData!$A$2:$BZ$2066,72,FALSE),"—"),IF(A6="Licensed practical nurses",IFERROR(VLOOKUP(CONCATENATE($D$6,$A$6,$B$6,$C$6),NursProfileData!$A$2:$BZ$2066,72,FALSE),"—"),"—")))))))))) -> 0.048445359
B48: Not stated | C48: =IF(A6="Family medicine physicians",IFERROR(VLOOKUP(CONCATENATE($D$6,$A$6,$B$6),Phyprofile!A3:AU464,26,FALSE),"—"),IF(A6="Specialists",IFERROR(VLOOKUP(CONCATENATE($D$6,$A$6,$B$6),Phyprofile!A3:AU464,26,FALSE),"—"),IF(A6="All physicians",IFERROR(VLOOKUP(CONCATENATE($D$6,$A$6,$B$6),Phyprofile!A3:AU464,26,FALSE),"—"),IF(A6="Occupational therapists",IFERROR(VLOOKUP(CONCATENATE($D$6,$A$6,$B$6,$C$6),OTProfileData!$A$2:$AR$1920,40,FALSE),"—"),IF(A6="Physiotherapists",IFERROR(VLOOKUP(CONCATENATE($D$6,$A$6,$B$6,$C$6),PTProfileData!$A$2:$BW$1802,37,FALSE),"—"),IF(A6="Pharmacists",IFERROR(VLOOKUP(CONCATENATE($D$6,$A$6,$B$6,$C$6),PHProfileData!$A$3:$AO$1868,35,FALSE),"—"),IF(A6="nurse practitioners",IFERROR(VLOOKUP(CONCATENATE($D$6,$A$6,$B$6,$C$6),NursProfileData!$A$2:$BZ$2066,39,FALSE),"—"),IF(A6="Registered nurses",IFERROR(VLOOKUP(CONCATENATE($D$6,$A$6,$B$6,$C$6),NursProfileData!$A$2:$BZ$2066,39,FALSE),"—"),IF(A6="Registered psychiatric nurses",IFERROR(VLOOKUP(CONCATENATE($D$6,$A$6,$B$6,$C$6),NursProfileData!$A$2:$BZ$2066,39,FALSE),"—"),IF(A6="Licensed practical nurses",IFERROR(VLOOKUP(CONCATENATE($D$6,$A$6,$B$6,$C$6),NursProfileData!$A$2:$BZ$2066,39,FALSE),"—"),"-")))))))))) -> 23 | D48: =IF(A6="Family medicine physicians",IFERROR(VLOOKUP(CONCATENATE($D$6,$A$6,$B$6),Phyprofile!A3:AU464,47,FALSE),"—"),IF(A6="Specialists",IFERROR(VLOOKUP(CONCATENATE($D$6,$A$6,$B$6),Phyprofile!A3:AU464,47,FALSE),"—"),IF(A6="All physicians",IFERROR(VLOOKUP(CONCATENATE($D$6,$A$6,$B$6),Phyprofile!A3:AU464,47,FALSE),"—"),IF(A6="Occupational therapists",IFERROR(VLOOKUP(CONCATENATE($D$6,$A$6,$B$6,$C$6),OTProfileData!$A$2:$CB$1920,76,FALSE),"—"),IF(A6="Physiotherapists",IFERROR(VLOOKUP(CONCATENATE($D$6,$A$6,$B$6,$C$6),PTProfileData!$A$2:$BW$1802,70,FALSE),"—"),IF(A6="Pharmacists",IFERROR(VLOOKUP(CONCATENATE($D$6,$A$6,$B$6,$C$6),PHProfileData!$A$3:$BR$1868,66,FALSE),"—"),IF(A6="nurse practitioners",IFERROR(VLOOKUP(CONCATENATE($D$6,$A$6,$B$6,$C$6),NursProfileData!$A$2:$BZ$2066,74,FALSE),"—"),IF(A6="Registered nurses",IFERROR(VLOOKUP(CONCATENATE($D$6,$A$6,$B$6,$C$6),NursProfileData!$A$2:$BZ$2066,74,FALSE),"—"),IF(A6="Registered psychiatric nurses",IFERROR(VLOOKUP(CONCATENATE($D$6,$A$6,$B$6,$C$6),NursProfileData!$A$2:$BZ$2066,74,FALSE),"—"),IF(A6="Licensed practical nurses",IFERROR(VLOOKUP(CONCATENATE($D$6,$A$6,$B$6,$C$6),NursProfileData!$A$2:$BZ$2066,74,FALSE),"—"),"—")))))))))) -> 0.00022638018
A49: =IF(OR(A6="Family medicine physicians",A6="Specialists",A6="All physicians"),"Supply","Workforce") -> Workforce | B49: Total | C49: =IF(A6="Family medicine physicians",IFERROR(VLOOKUP(CONCATENATE($D$6,$A$6,$B$6),Phyprofile!A3:AU464,5,FALSE),"—"),IF(A6="Specialists",IFERROR(VLOOKUP(CONCATENATE($D$6,$A$6,$B$6),Phyprofile!A3:AU464,5,FALSE),"—"),IF(A6="All physicians",IFERROR(VLOOKUP(CONCATENATE($D$6,$A$6,$B$6),Phyprofile!A3:AU464,5,FALSE),"—"),IF(A6="Occupational therapists",IFERROR(VLOOKUP(CONCATENATE($D$6,$A$6,$B$6,$C$6),OTProfileData!$A$2:$AR$1920,41,FALSE),"—"),IF(A6="Physiotherapists",IFERROR(VLOOKUP(CONCATENATE($D$6,$A$6,$B$6,$C$6),PTProfileData!$A$2:$BW$1802,38,FALSE),"—"),IF(A6="Pharmacists",IFERROR(VLOOKUP(CONCATENATE($D$6,$A$6,$B$6,$C$6),PHProfileData!$A$3:$AO$1868,36,FALSE),"—"),IF(A6="nurse practitioners",IFERROR(VLOOKUP(CONCATENATE($D$6,$A$6,$B$6,$C$6),NursProfileData!$A$2:$BZ$2066,40,FALSE),"—"),IF(A6="Registered nurses",IFERROR(VLOOKUP(CONCATENATE($D$6,$A$6,$B$6,$C$6),NursProfileData!$A$2:$BZ$2066,40,FALSE),"—"),IF(A6="Registered psychiatric nurses",IFERROR(VLOOKUP(CONCATENATE($D$6,$A$6,$B$6,$C$6),NursProfileData!$A$2:$BZ$2066,40,FALSE),"—"),IF(A6="Licensed practical nurses",IFERROR(VLOOKUP(CONCATENATE($D$6,$A$6,$B$6,$C$6),NursProfileData!$A$2:$BZ$2066,40,FALSE),"—"),"-")))))))))) -> 101599 | D49: —
A50: =CONCATENATE(,A6," in ",B6," by place of work, ",D6) -> Registered nurses in Ontario by place of work, 2023 | B50: Category | C50: Count | D50: Percentage
A51: =IF(OR(A6="Family medicine physicians",A6="Specialists",A6="All physicians"),"—","Place of Work") -> Place of Work | B51: =IF(OR(A6="Family medicine physicians",A6="Specialists",A6="All physicians"),"—","All places of work") -> All places of work | C51: =IF(A6="Family medicine physicians","—",IF(A6="Specialists","—",IF(A6="All physicians","—",IF(A6="Occupational therapists",IFERROR(VLOOKUP(CONCATENATE($D$6,$A$6,$B$6,$B$51),OTProfileData!$A$2:$AR$1920,41,FALSE),"—"),IF(A6="Physiotherapists",IFERROR(VLOOKUP(CONCATENATE($D$6,$A$6,$B$6,$B$51),PTProfileData!$A$2:$BW$1802,38,FALSE),"—"),IF(A6="Pharmacists",IFERROR(VLOOKUP(CONCATENATE($D$6,$A$6,$B$6,$B$51),PHProfileData!$A$3:$AO$1868,36,FALSE),"—"),IF(A6="nurse practitioners",IFERROR(VLOOKUP(CONCATENATE($D$6,$A$6,$B$6,$B$51),NursProfileData!$A$2:$BZ$2066,40,FALSE),"—"),IF(A6="Registered nurses",IFERROR(VLOOKUP(CONCATENATE($D$6,$A$6,$B$6,$B$51),NursProfileData!$A$2:$BZ$2066,40,FALSE),"—"),IF(A6="Registered psychiatric nurses",IFERROR(VLOOKUP(CONCATENATE($D$6,$A$6,$B$6,$B$51),NursProfileData!$A$2:$BZ$2066,40,FALSE),"—"),IF(A6="Licensed practical nurses",IFERROR(VLOOKUP(CONCATENATE($D$6,$A$6,$B$6,$B$51),NursProfileData!$A$2:$BZ$2066,40,FALSE),"—"),"-")))))))))) -> 101599 | D51: =IFERROR(C51/C51,"—") -> 1
B52: =IF(OR(A6="Family medicine physicians",A6="Specialists",A6="All physicians"),"—","Hospital") -> Hospital | C52: =IF(A6="Family medicine physicians","—",IF(A6="Specialists","—",IF(A6="All physicians","—",IF(A6="Occupational therapists",IFERROR(VLOOKUP(CONCATENATE($D$6,$A$6,$B$6,$B$52),OTProfileData!$A$2:$AR$1920,41,FALSE),"—"),IF(A6="Physiotherapists",IFERROR(VLOOKUP(CONCATENATE($D$6,$A$6,$B$6,$B$52),PTProfileData!$A$2:$BW$1802,38,FALSE),"—"),IF(A6="Pharmacists",IFERROR(VLOOKUP(CONCATENATE($D$6,$A$6,$B$6,$B$52),PHProfileData!$A$3:$AO$1868,36,FALSE),"—"),IF(A6="nurse practitioners",IFERROR(VLOOKUP(CONCATENATE($D$6,$A$6,$B$6,$B$52),NursProfileData!$A$2:$BZ$2066,40,FALSE),"—"),IF(A6="Registered nurses",IFERROR(VLOOKUP(CONCATENATE($D$6,$A$6,$B$6,$B$52),NursProfileData!$A$2:$BZ$2066,40,FALSE),"—"),IF(A6="Registered psychiatric nurses",IFERROR(VLOOKUP(CONCATENATE($D$6,$A$6,$B$6,$B$52),NursProfileData!$A$2:$BZ$2066,40,FALSE),"—"),IF(A6="Licensed practical nurses",IFERROR(VLOOKUP(CONCATENATE($D$6,$A$6,$B$6,$B$52),NursProfileData!$A$2:$BZ$2066,40,FALSE),"—"),"-")))))))))) -> 64742 | D52: =IF(A6="Family medicine physicians","—",IF(A6="Specialists","—",IF(A6="All physicians","—",IF(A6="Occupational therapists",IFERROR(VLOOKUP(CONCATENATE($D$6,$A$6,$B$6,$B$52),OTProfileData!$A$2:$CB$1920,80,FALSE),"—"),IF(A6="Physiotherapists",IFERROR(VLOOKUP(CONCATENATE($D$6,$A$6,$B$6,$B$52),PTProfileData!$A$2:$BW$1802,74,FALSE),"—"),IF(A6="Pharmacists",IFERROR(VLOOKUP(CONCATENATE($D$6,$A$6,$B$6,$B$52),PHProfileData!$A$3:$ZJ$1868,70,FALSE),"—"),IF(A6="nurse practitioners",IFERROR(VLOOKUP(CONCATENATE($D$6,$A$6,$B$6,$B$52),NursProfileData!$A$2:$BZ$2066,78,FALSE),"—"),IF(A6="Registered nurses",IFERROR(VLOOKUP(CONCATENATE($D$6,$A$6,$B$6,$B$52),NursProfileData!$A$2:$BZ$2066,78,FALSE),"—"),IF(A6="Registered psychiatric nurses",IFERROR(VLOOKUP(CONCATENATE($D$6,$A$6,$B$6,$B$52),NursProfileData!$A$2:$BZ$2066,78,FALSE),"—"),IF(A6="Licensed practical nurses",IFERROR(VLOOKUP(CONCATENATE($D$6,$A$6,$B$6,$B$52),NursProfileData!$A$2:$BZ$2066,78,FALSE),"—"),"—")))))))))) -> 0.63723068
B53: =IF(OR(A6="Family medicine physicians",A6="Specialists",A6="All physicians"),"—","Community health") -> Community health | C53: =IF(A6="Family medicine physicians","—",IF(A6="Specialists","—",IF(A6="All physicians","—",IF(A6="Occupational therapists",IFERROR(VLOOKUP(CONCATENATE($D$6,$A$6,$B$6,$B$53),OTProfileData!$A$2:$AR$1920,41,FALSE),"—"),IF(A6="Physiotherapists",IFERROR(VLOOKUP(CONCATENATE($D$6,$A$6,$B$6,$B$53),PTProfileData!$A$2:$BW$1802,38,FALSE),"—"),IF(A6="Pharmacists",IFERROR(VLOOKUP(CONCATENATE($D$6,$A$6,$B$6,$B$53),PHProfileData!$A$3:$AO$1868,36,FALSE),"—"),IF(A6="nurse practitioners",IFERROR(VLOOKUP(CONCATENATE($D$6,$A$6,$B$6,$B$53),NursProfileData!$A$2:$BZ$2066,40,FALSE),"—"),IF(A6="Registered nurses",IFERROR(VLOOKUP(CONCATENATE($D$6,$A$6,$B$6,$B$53),NursProfileData!$A$2:$BZ$2066,40,FALSE),"—"),IF(A6="Registered psychiatric nurses",IFERROR(VLOOKUP(CONCATENATE($D$6,$A$6,$B$6,$B$53),NursProfileData!$A$2:$BZ$2066,40,FALSE),"—"),IF(A6="Licensed practical nurses",IFERROR(VLOOKUP(CONCATENATE($D$6,$A$6,$B$6,$B$53),NursProfileData!$A$2:$BZ$2066,40,FALSE),"—"),"-")))))))))) -> 16988 | D53: =IF(A6="Family medicine physicians","—",IF(A6="Specialists","—",IF(A6="All physicians","—",IF(A6="Occupational therapists",IFERROR(VLOOKUP(CONCATENATE($D$6,$A$6,$B$6,$B$53),OTProfileData!$A$2:$CB$1920,80,FALSE),"—"),IF(A6="Physiotherapists",IFERROR(VLOOKUP(CONCATENATE($D$6,$A$6,$B$6,$B$53),PTProfileData!$A$2:$BW$1802,74,FALSE),"—"),IF(A6="Pharmacists",IFERROR(VLOOKUP(CONCATENATE($D$6,$A$6,$B$6,$B$53),PHProfileData!$A$3:$BR$1868,70,FALSE),"—"),IF(A6="nurse practitioners",IFERROR(VLOOKUP(CONCATENATE($D$6,$A$6,$B$6,$B$53),NursProfileData!$A$2:$BZ$2066,78,FALSE),"—"),IF(A6="Registered nurses",IFERROR(VLOOKUP(CONCATENATE($D$6,$A$6,$B$6,$B$53),NursProfileData!$A$2:$BZ$2066,78,FALSE),"—"),IF(A6="Registered psychiatric nurses",IFERROR(VLOOKUP(CONCATENATE($D$6,$A$6,$B$6,$B$53),NursProfileData!$A$2:$BZ$2066,78,FALSE),"—"),IF(A6="Licensed practical nurses",IFERROR(VLOOKUP(CONCATENATE($D$6,$A$6,$B$6,$B$53),NursProfileData!$A$2:$BZ$2066,78,FALSE),"—"),"-")))))))))) -> 0.16720637
B54: =IF(OR(A6="Family medicine physicians",A6="Specialists",A6="All physicians"),"—","Nursing home/long-term care") -> Nursing home/long-term care | C54: =IF(A6="Family medicine physicians","—",IF(A6="Specialists","—",IF(A6="All physicians","—",IF(A6="Occupational therapists",IFERROR(VLOOKUP(CONCATENATE($D$6,$A$6,$B$6,$B$54),OTProfileData!$A$2:$AR$1920,41,FALSE),"—"),IF(A6="Physiotherapists",IFERROR(VLOOKUP(CONCATENATE($D$6,$A$6,$B$6,$B$54),PTProfileData!$A$2:$BW$1802,38,FALSE),"—"),IF(A6="Pharmacists",IFERROR(VLOOKUP(CONCATENATE($D$6,$A$6,$B$6,$B$54),PHProfileData!$A$3:$AO$1868,36,FALSE),"—"),IF(A6="nurse practitioners",IFERROR(VLOOKUP(CONCATENATE($D$6,$A$6,$B$6,$B$54),NursProfileData!$A$2:$BZ$2066,40,FALSE),"—"),IF(A6="Registered nurses",IFERROR(VLOOKUP(CONCATENATE($D$6,$A$6,$B$6,$B$54),NursProfileData!$A$2:$BZ$2066,40,FALSE),"—"),IF(A6="Registered psychiatric nurses",IFERROR(VLOOKUP(CONCATENATE($D$6,$A$6,$B$6,$B$54),NursProfileData!$A$2:$BZ$2066,40,FALSE),"—"),IF(A6="Licensed practical nurses",IFERROR(VLOOKUP(CONCATENATE($D$6,$A$6,$B$6,$B$54),NursProfileData!$A$2:$BZ$2066,40,FALSE),"—"),"-")))))))))) -> 7718 | D54: =IF(A6="Family medicine physicians","—",IF(A6="Specialists","—",IF(A6="All physicians","—",IF(A6="Occupational therapists",IFERROR(VLOOKUP(CONCATENATE($D$6,$A$6,$B$6,$B$54),OTProfileData!$A$2:$CB$1920,80,FALSE),"—"),IF(A6="Physiotherapists",IFERROR(VLOOKUP(CONCATENATE($D$6,$A$6,$B$6,$B$54),PTProfileData!$A$2:$BW$1802,74,FALSE),"—"),IF(A6="Pharmacists",IFERROR(VLOOKUP(CONCATENATE($D$6,$A$6,$B$6,$B$54),PHProfileData!$A$3:$BR$1868,70,FALSE),"—"),IF(A6="nurse practitioners",IFERROR(VLOOKUP(CONCATENATE($D$6,$A$6,$B$6,$B$54),NursProfileData!$A$2:$BZ$2066,78,FALSE),"—"),IF(A6="Registered nurses",IFERROR(VLOOKUP(CONCATENATE($D$6,$A$6,$B$6,$B$54),NursProfileData!$A$2:$BZ$2066,78,FALSE),"—"),IF(A6="Registered psychiatric nurses",IFERROR(VLOOKUP(CONCATENATE($D$6,$A$6,$B$6,$B$54),NursProfileData!$A$2:$BZ$2066,78,FALSE),"—"),IF(A6="Licensed practical nurses",IFERROR(VLOOKUP(CONCATENATE($D$6,$A$6,$B$6,$B$54),NursProfileData!$A$2:$BZ$2066,78,FALSE),"—"),"-")))))))))) -> 0.075965315
B55: =IF(OR(A6="Family medicine physicians",A6="Specialists",A6="All physicians"),"—","Other places of work") -> Other places of work | C55: =IF(A6="Family medicine physicians","—",IF(A6="Specialists","—",IF(A6="All physicians","—",IF(A6="Occupational therapists",IFERROR(VLOOKUP(CONCATENATE($D$6,$A$6,$B$6,$B$55),OTProfileData!$A$2:$AR$1920,41,FALSE),"—"),IF(A6="Physiotherapists",IFERROR(VLOOKUP(CONCATENATE($D$6,$A$6,$B$6,$B$55),PTProfileData!$A$2:$BW$1802,38,FALSE),"—"),IF(A6="Pharmacists",IFERROR(VLOOKUP(CONCATENATE($D$6,$A$6,$B$6,$B$55),PHProfileData!$A$3:$AO$1868,36,FALSE),"—"),IF(A6="nurse practitioners",IFERROR(VLOOKUP(CONCATENATE($D$6,$A$6,$B$6,$B$55),NursProfileData!$A$2:$BZ$2066,40,FALSE),"—"),IF(A6="Registered nurses",IFERROR(VLOOKUP(CONCATENATE($D$6,$A$6,$B$6,$B$55),NursProfileData!$A$2:$BZ$2066,40,FALSE),"—"),IF(A6="Registered psychiatric nurses",IFERROR(VLOOKUP(CONCATENATE($D$6,$A$6,$B$6,$B$55),NursProfileData!$A$2:$BZ$2066,40,FALSE),"—"),IF(A6="Licensed practical nurses",IFERROR(VLOOKUP(CONCATENATE($D$6,$A$6,$B$6,$B$55),NursProfileData!$A$2:$BZ$2066,40,FALSE),"—"),"-")))))))))) -> 12137 | D55: =IF(A6="Family medicine physicians","—",IF(A6="Specialists","—",IF(A6="All physicians","—",IF(A6="Occupational therapists",IFERROR(VLOOKUP(CONCATENATE($D$6,$A$6,$B$6,$B$55),OTProfileData!$A$2:$CB$1920,80,FALSE),"—"),IF(A6="Physiotherapists",IFERROR(VLOOKUP(CONCATENATE($D$6,$A$6,$B$6,$B$55),PTProfileData!$A$2:$BW$1802,74,FALSE),"—"),IF(A6="Pharmacists",IFERROR(VLOOKUP(CONCATENATE($D$6,$A$6,$B$6,$B$55),PHProfileData!$A$3:$BR$1868,70,FALSE),"—"),IF(A6="nurse practitioners",IFERROR(VLOOKUP(CONCATENATE($D$6,$A$6,$B$6,$B$55),NursProfileData!$A$2:$BZ$2066,78,FALSE),"—"),IF(A6="Registered nurses",IFERROR(VLOOKUP(CONCATENATE($D$6,$A$6,$B$6,$B$55),NursProfileData!$A$2:$BZ$2066,78,FALSE),"—"),IF(A6="Registered psychiatric nurses",IFERROR(VLOOKUP(CONCATENATE($D$6,$A$6,$B$6,$B$55),NursProfileData!$A$2:$BZ$2066,78,FALSE),"—"),IF(A6="Licensed practical nurses",IFERROR(VLOOKUP(CONCATENATE($D$6,$A$6,$B$6,$B$55),NursProfileData!$A$2:$BZ$2066,78,FALSE),"—"),"-")))))))))) -> 0.11945984
B56: =IF(OR(A6="Family medicine physicians",A6="Specialists",A6="All physicians"),"—","Unknown places of work") -> Unknown places of work | C56: =IF(A6="Family medicine physicians","—",IF(A6="Specialists","—",IF(A6="All physicians","—",IF(A6="Occupational therapists",IFERROR(VLOOKUP(CONCATENATE($D$6,$A$6,$B$6,$B$56),OTProfileData!$A$2:$AR$1920,41,FALSE),"—"),IF(A6="Physiotherapists",IFERROR(VLOOKUP(CONCATENATE($D$6,$A$6,$B$6,$B$56),PTProfileData!$A$2:$BW$1802,38,FALSE),"—"),IF(A6="Pharmacists",IFERROR(VLOOKUP(CONCATENATE($D$6,$A$6,$B$6,$B$56),PHProfileData!$A$3:$AO$1868,36,FALSE),"—"),IF(A6="nurse practitioners",IFERROR(VLOOKUP(CONCATENATE($D$6,$A$6,$B$6,$B$56),NursProfileData!$A$2:$BZ$2066,40,FALSE),"—"),IF(A6="Registered nurses",IFERROR(VLOOKUP(CONCATENATE($D$6,$A$6,$B$6,$B$56),NursProfileData!$A$2:$BZ$2066,40,FALSE),"—"),IF(A6="Registered psychiatric nurses",IFERROR(VLOOKUP(CONCATENATE($D$6,$A$6,$B$6,$B$56),NursProfileData!$A$2:$BZ$2066,40,FALSE),"—"),IF(A6="Licensed practical nurses",IFERROR(VLOOKUP(CONCATENATE($D$6,$A$6,$B$6,$B$56),NursProfileData!$A$2:$BZ$2066,40,FALSE),"—"),"-")))))))))) -> 14 | D56: =IF(A6="Family medicine physicians","—",IF(A6="Specialists","—",IF(A6="All physicians","—",IF(A6="Occupational therapists",IFERROR(VLOOKUP(CONCATENATE($D$6,$A$6,$B$6,$B$56),OTProfileData!$A$2:$CB$1920,80,FALSE),"—"),IF(A6="Physiotherapists",IFERROR(VLOOKUP(CONCATENATE($D$6,$A$6,$B$6,$B$56),PTProfileData!$A$2:$BW$1802,74,FALSE),"—"),IF(A6="Pharmacists",IFERROR(VLOOKUP(CONCATENATE($D$6,$A$6,$B$6,$B$56),PHProfileData!$A$3:$BR$1868,70,FALSE),"—"),IF(A6="nurse practitioners",IFERROR(VLOOKUP(CONCATENATE($D$6,$A$6,$B$6,$B$56),NursProfileData!$A$2:$BZ$2066,78,FALSE),"—"),IF(A6="Registered nurses",IFERROR(VLOOKUP(CONCATENATE($D$6,$A$6,$B$6,$B$56),NursProfileData!$A$2:$BZ$2066,78,FALSE),"—"),IF(A6="Registered psychiatric nurses",IFERROR(VLOOKUP(CONCATENATE($D$6,$A$6,$B$6,$B$56),NursProfileData!$A$2:$BZ$2066,78,FALSE),"—"),IF(A6="Licensed practical nurses",IFERROR(VLOOKUP(CONCATENATE($D$6,$A$6,$B$6,$B$56),NursProfileData!$A$2:$BZ$2066,78,FALSE),"—"),"-")))))))))) -> 0.00013779663
A57: Notes
A58: — Data is not applicable, does not exist or is not reported due to data quality issues or privacy reasons.
A59: * For physicians, place of work data is not available. See professional-specific notes.
A60: Percentages may not equal 100 due to rounding.
A61: When a figure does not populate, it indicates that data for the selection is unavailable, does not exist or is not applicable.
A62: For more information regarding collection and comparability of data as well as notes specific to individual provinces and territories, refer to professional-specific methodology notes.
A63: Additional historical data is available upon request.
A64: Professional-specific notes
A65: Nurse practitioners (NPs) and registered nurses (RNs)
A66: Employment data for NPs and RNs in Manitoba for 2019 to 2023 has been suppressed due to significant under-coverage as a result of voluntary reporting. The corresponding information for 2014 to 2018 should be used with caution, as it was also reported voluntarily and may also be understated.
A67: Profile data is not available for the Northwest Territories and Nunavut, as data for NPs and for RNs is reported together in those territories.
A68: In the Yukon, NPs were first regulated in 2013. Data is not available prior to that year.
... A100: End of worksheet (back to Table of contents)

Sheet 2 Supply
A1: This tab provides the supply counts and percentage changes for different types of providers for a given province or territory from 2014 to 2023. You can compare up to 3 jurisdictions. The figures and table will populate information based on your selections. Select the type of provider in cell A6. Select the main province or territory in cell B6. Select the comparator province or territory in cells C6 and D6. The table begins at cell A11 and ends at cell G21. The notes and sources begin in cell A22 and end in cell A58. The figures are located in cells A8 and A9. A link back to the Table of contents is in cell A2 and A59.
A2: Back to the Table of contents
A3: =IF(A6="Specialists",CONCATENATE("Supply of specialist"," ","physicians",","," ",TRIM(B6),", 2014 to 2023"),IF(A6="Family medicine",CONCATENATE("Supply of ",LOWER(A6)," ","physicians",","," ",TRIM(B6),", 2014 to 2023"),CONCATENATE("Supply of ",LOWER(A6),", ",TRIM(B6),", 2014 to 2023"))) -> Supply of registered nurses, Ontario, 2014 to 2023
A4: Instructions: Select a provider and jurisdiction from the drop-down lists in cells A6, B6, C6 and D6.
A5: Type of provider | B5: Province/territory/Canada (main) | C5: Province/territory/Canada (comparator 1) | D5: Province/territory/Canada (comparator 2)
A6: Registered nurses | B6: Ontario | C6: British Columbia | D6: Alberta
A7: Data will change in the figures and table below based on your selections above. Hover over the chart area to show values and categories. When a figure does not populate, it indicates that data for the selection is unavailable, does not exist or is not applicable.
A8: The information can be found in the table below.
A10: =CONCATENATE("Table 2 Supply of ",LOWER(A6),", ",TRIM(B6),", 2014 to 2023") -> Table 2 Supply of registered nurses, Ontario, 2014 to 2023
A11: Year | B11: =CONCATENATE(A6," supply count in ", TRIM(B6)) -> Registered nurses supply count in Ontario | C11: =CONCATENATE(A6," supply count in ", TRIM(C6)) -> Registered nurses supply count in British Columbia | D11: =CONCATENATE(A6," supply count in ", TRIM(D6)) -> Registered nurses supply count in Alberta | E11: =CONCATENATE("Percentage change from previous year of ", LOWER(A6), " supply in ", B6) -> Percentage change from previous year of registered nurses supply in Ontario | F11: =CONCATENATE("Percentage change from previous year of ", LOWER(A6), " supply in ", C6) -> Percentage change from previous year of registered nurses supply in British Columbia | G11: =CONCATENATE("Percentage change from previous year of ", LOWER(A6), " supply in ", D6) -> Percentage change from previous year of registered nurses supply in Alberta
A12: 2014 | B12: =IFERROR(VLOOKUP(CONCATENATE($A12,$B$6,$A$6),Supply_WF_Flow!$A$2:$K$4380,5,FALSE),"—") -> 102247 | C12: =IFERROR(VLOOKUP(CONCATENATE($A12,$C$6,$A$6),Supply_WF_Flow!$A$2:$K$4380,5,FALSE),"—") -> 35088 | D12: =IFERROR(VLOOKUP(CONCATENATE($A12,$D$6,$A$6),Supply_WF_Flow!$A$2:$K$4380,5,FALSE),"—") -> 32537 | E12: — | F12: — | G12: —
A13: 2015 | B13: =IFERROR(VLOOKUP(CONCATENATE($A13,$B$6,$A$6),Supply_WF_Flow!$A$2:$K$4380,5,FALSE),"—") -> 102490 | C13: =IFERROR(VLOOKUP(CONCATENATE($A13,$C$6,$A$6),Supply_WF_Flow!$A$2:$K$4380,5,FALSE),"—") -> 35397 | D13: =IFERROR(VLOOKUP(CONCATENATE($A13,$D$6,$A$6),Supply_WF_Flow!$A$2:$K$4380,5,FALSE),"—") -> 34764 | E13: =IFERROR(IF(OR(B12=0,B12="—",B13="—"),"—",(B13-B12)/B12),"—") -> 0.0023765978 | F13: =IFERROR(IF(OR(C12=0,C12="—",C13="—"),"—",(C13-C12)/C12),"—") -> 0.0088064295 | G13: =IFERROR(IF(OR(D12=0,D12="—",D13="—"),"—",(D13-D12)/D12),"—") -> 0.068445155
A14: 2016 | B14: =IFERROR(VLOOKUP(CONCATENATE($A14,$B$6,$A$6),Supply_WF_Flow!$A$2:$K$4380,5,FALSE),"—") -> 102006 | C14: =IFERROR(VLOOKUP(CONCATENATE($A14,$C$6,$A$6),Supply_WF_Flow!$A$2:$K$4380,5,FALSE),"—") -> 36506 | D14: =IFERROR(VLOOKUP(CONCATENATE($A14,$D$6,$A$6),Supply_WF_Flow!$A$2:$K$4380,5,FALSE),"—") -> 34992 | E14: =IFERROR(IF(OR(B13=0,B13="—",B14="—"),"—",(B14-B13)/B13),"—") -> -0.0047224119 | F14: =IFERROR(IF(OR(C13=0,C13="—",C14="—"),"—",(C14-C13)/C13),"—") -> 0.031330339 | G14: =IFERROR(IF(OR(D13=0,D13="—",D14="—"),"—",(D14-D13)/D13),"—") -> 0.0065585088
A15: 2017 | B15: =IFERROR(VLOOKUP(CONCATENATE($A15,$B$6,$A$6),Supply_WF_Flow!$A$2:$K$4380,5,FALSE),"—") -> 101912 | C15: =IFERROR(VLOOKUP(CONCATENATE($A15,$C$6,$A$6),Supply_WF_Flow!$A$2:$K$4380,5,FALSE),"—") -> 37355 | D15: =IFERROR(VLOOKUP(CONCATENATE($A15,$D$6,$A$6),Supply_WF_Flow!$A$2:$K$4380,5,FALSE),"—") -> 35448 | E15: =IFERROR(IF(OR(B14=0,B14="—",B15="—"),"—",(B15-B14)/B14),"—") -> -0.00092151442 | F15: =IFERROR(IF(OR(C14=0,C14="—",C15="—"),"—",(C15-C14)/C14),"—") -> 0.023256451 | G15: =IFERROR(IF(OR(D14=0,D14="—",D15="—"),"—",(D15-D14)/D14),"—") -> 0.01303155
A16: 2018 | B16: =IFERROR(VLOOKUP(CONCATENATE($A16,$B$6,$A$6),Supply_WF_Flow!$A$2:$K$4380,5,FALSE),"—") -> 102396 | C16: =IFERROR(VLOOKUP(CONCATENATE($A16,$C$6,$A$6),Supply_WF_Flow!$A$2:$K$4380,5,FALSE),"—") -> 37592 | D16: =IFERROR(VLOOKUP(CONCATENATE($A16,$D$6,$A$6),Supply_WF_Flow!$A$2:$K$4380,5,FALSE),"—") -> 35691 | E16: =IFERROR(IF(OR(B15=0,B15="—",B16="—"),"—",(B16-B15)/B15),"—") -> 0.0047491954 | F16: =IFERROR(IF(OR(C15=0,C15="—",C16="—"),"—",(C16-C15)/C15),"—") -> 0.0063445322 | G16: =IFERROR(IF(OR(D15=0,D15="—",D16="—"),"—",(D16-D15)/D15),"—") -> 0.0068551117
A17: 2019 | B17: =IFERROR(VLOOKUP(CONCATENATE($A17,$B$6,$A$6),Supply_WF_Flow!$A$2:$K$4380,5,FALSE),"—") -> 103877 | C17: =IFERROR(VLOOKUP(CONCATENATE($A17,$C$6,$A$6),Supply_WF_Flow!$A$2:$K$4380,5,FALSE),"—") -> 38041 | D17: =IFERROR(VLOOKUP(CONCATENATE($A17,$D$6,$A$6),Supply_WF_Flow!$A$2:$K$4380,5,FALSE),"—") -> 35907 | E17: =IFERROR(IF(OR(B16=0,B16="—",B17="—"),"—",(B17-B16)/B16),"—") -> 0.014463456 | F17: =IFERROR(IF(OR(C16=0,C16="—",C17="—"),"—",(C17-C16)/C16),"—") -> 0.011944031 | G17: =IFERROR(IF(OR(D16=0,D16="—",D17="—"),"—",(D17-D16)/D16),"—") -> 0.0060519459
A18: 2020 | B18: =IFERROR(VLOOKUP(CONCATENATE($A18,$B$6,$A$6),Supply_WF_Flow!$A$2:$K$4380,5,FALSE),"—") -> 104976 | C18: =IFERROR(VLOOKUP(CONCATENATE($A18,$C$6,$A$6),Supply_WF_Flow!$A$2:$K$4380,5,FALSE),"—") -> 38863 | D18: =IFERROR(VLOOKUP(CONCATENATE($A18,$D$6,$A$6),Supply_WF_Flow!$A$2:$K$4380,5,FALSE),"—") -> 36394 | E18: =IFERROR(IF(OR(B17=0,B17="—",B18="—"),"—",(B18-B17)/B17),"—") -> 0.01057982 | F18: =IFERROR(IF(OR(C17=0,C17="—",C18="—"),"—",(C18-C17)/C17),"—") -> 0.021608265 | G18: =IFERROR(IF(OR(D17=0,D17="—",D18="—"),"—",(D18-D17)/D17),"—") -> 0.013562815
A19: 2021 | B19: =IFERROR(VLOOKUP(CONCATENATE($A19,$B$6,$A$6),Supply_WF_Flow!$A$2:$K$4380,5,FALSE),"—") -> 106595 | C19: =IFERROR(VLOOKUP(CONCATENATE($A19,$C$6,$A$6),Supply_WF_Flow!$A$2:$K$4380,5,FALSE),"—") -> 40343 | D19: =IFERROR(VLOOKUP(CONCATENATE($A19,$D$6,$A$6),Supply_WF_Flow!$A$2:$K$4380,5,FALSE),"—") -> 36288 | E19: =IFERROR(IF(OR(B18=0,B18="—",B19="—"),"—",(B19-B18)/B18),"—") -> 0.015422573 | F19: =IFERROR(IF(OR(C18=0,C18="—",C19="—"),"—",(C19-C18)/C18),"—") -> 0.038082495 | G19: =IFERROR(IF(OR(D18=0,D18="—",D19="—"),"—",(D19-D18)/D18),"—") -> -0.002912568
A20: 2022 | B20: =IFERROR(VLOOKUP(CONCATENATE($A20,$B$6,$A$6),Supply_WF_Flow!$A$2:$K$4380,5,FALSE),"—") -> 108040 | C20: =IFERROR(VLOOKUP(CONCATENATE($A20,$C$6,$A$6),Supply_WF_Flow!$A$2:$K$4380,5,FALSE),"—") -> 40891 | D20: =IFERROR(VLOOKUP(CONCATENATE($A20,$D$6,$A$6),Supply_WF_Flow!$A$2:$K$4380,5,FALSE),"—") -> 36302 | E20: =IFERROR(IF(OR(B19=0,B19="—",B20="—"),"—",(B20-B19)/B19),"—") -> 0.013555983 | F20: =IFERROR(IF(OR(C19=0,C19="—",C20="—"),"—",(C20-C19)/C19),"—") -> 0.013583521 | G20: =IFERROR(IF(OR(D19=0,D19="—",D20="—"),"—",(D20-D19)/D19),"—") -> 0.00038580247
A21: 2023 | B21: =IFERROR(VLOOKUP(CONCATENATE($A21,$B$6,$A$6),Supply_WF_Flow!$A$2:$K$4380,5,FALSE),"—") -> 110510 | C21: =IFERROR(VLOOKUP(CONCATENATE($A21,$C$6,$A$6),Supply_WF_Flow!$A$2:$K$4380,5,FALSE),"—") -> 41893 | D21: =IFERROR(VLOOKUP(CONCATENATE($A21,$D$6,$A$6),Supply_WF_Flow!$A$2:$K$4380,5,FALSE),"—") -> 37202 | E21: =IFERROR(IF(OR(B20=0,B20="—",B21="—"),"—",(B21-B20)/B20),"—") -> 0.022861903 | F21: =IFERROR(IF(OR(C20=0,C20="—",C21="—"),"—",(C21-C20)/C20),"—") -> 0.02450417 | G21: =IFERROR(IF(OR(D20=0,D20="—",D21="—"),"—",(D21-D20)/D20),"—") -> 0.024792022
A22: Notes
A23: — Data is not applicable, does not exist or is not reported due to data quality issues.
A24: Percentages may not equal 100 due to rounding.
A25: The dotted line in the percentage change figure represents a linear trend.
A26: Supply refers to all professionals who are eligible to practise in the given year (including those employed and those not employed at the time of registration). Note that secondary registrants (also known as interprovincial duplicates) are excluded from the supply. For regulated nurses, secondary registrants in the territories are not removed.
A27: For more data on the supply of health care professionals in Canada, refer to professional-specific data tables.
A28: For more information regarding collection and comparability of data as well as notes specific to individual provinces and territories, refer to professional-specific methodology notes.
A29: Professional-specific notes
A30: Nurse practitioners (NPs) and registered nurses (RNs)
A31: For both NPs and RNs, data is reported collectively for the Northwest Territories and Nunavut; please select Northwest Territories/Nunavut to see supply data for NPs or RNs.
A32: In the Yukon, NPs were first regulated in 2013. Data is not available prior to that year.
A33: According to the Northwest Territories Registered Nurses Association (NWTRNA), an error in the submission process in 2019 resulted in a number of NPs and RNs being excluded from supply and workforce counts. Please interpret 2018 and 2019 with caution when comparing with other years.
... A59: End of worksheet (back to Table of contents)

Sheet 3 Inflow and outflow
A1: This tab provides the percentage inflow and outflow for different types of providers in a given province or territory from 2014 to 2023. You can compare up to 2 jurisdictions. The figure and table will populate information based on your selections. Select the type of provider in cell A6. Select the main province or territory in cell B6. Select the comparator province or territory in cell C6. The table begins at cell A10 and ends at cell E20. The notes and source begin in cell A21 and end in cell A48. The figure is located in cell A8. A link back to the Table of contents is in cell A2 and A49.
A2: Back to the Table of contents
A3: =CONCATENATE("Inflow and outflow for ",LOWER(A6),", ",TRIM(B6),", 2014 to 2023") -> Inflow and outflow for registered nurses, Ontario, 2014 to 2023
A4: Instructions: Select a provider and jurisdictions from the drop-down lists in cells A6, B6 and C6.
A5: Type of provider | B5: Province/territory (main) | C5: Province/territory (comparator)
A6: Registered nurses | B6: Ontario | C6: British Columbia
A7: Data will change in the figures and table below based on your selections above. Hover over the chart area to show values and categories. When a figure does not populate, it indicates that data for the selection is unavailable, does not exist or is not applicable.
A8: The information can be found in the table below.
A9: =CONCATENATE("Table 3 Inflow and outflow for ",LOWER(A6),", ",TRIM(B6), " and ", TRIM(C6), ", 2014 to 2023") -> Table 3 Inflow and outflow for registered nurses, Ontario and British Columbia, 2014 to 2023
A10: Year | B10: =CONCATENATE("Percentage inflow of ", LOWER($A$6)," in ", TRIM($B$6)) -> Percentage inflow of registered nurses in Ontario | C10: =CONCATENATE("Percentage outflow of ", LOWER($A$6)," in ", TRIM($B$6)) -> Percentage outflow of registered nurses in Ontario | D10: =CONCATENATE("Percentage inflow of ", LOWER($A$6)," in ", TRIM($C$6)) -> Percentage inflow of registered nurses in British Columbia | E10: =CONCATENATE("Percentage outflow of ", LOWER($A$6)," in ", TRIM(C$6)) -> Percentage outflow of registered nurses in British Columbia
A11: 2014 | B11: =IFERROR(VLOOKUP(CONCATENATE($A11,$B$6,$A$6),Supply_WF_Flow!$A$2:$K$4380,10,FALSE),"—") -> 0.041986562 | C11: =IFERROR(VLOOKUP(CONCATENATE($A11,$B$6,$A$6),Supply_WF_Flow!$A$2:$K$4380,11,FALSE),"—") -> 0.046377889 | D11: =IFERROR(VLOOKUP(CONCATENATE($A11,$C$6,$A$6),Supply_WF_Flow!$A$2:$K$4380,10,FALSE),"—") -> 0.076521888 | E11: =IFERROR(VLOOKUP(CONCATENATE($A11,$C$6,$A$6),Supply_WF_Flow!$A$2:$K$4380,11,FALSE),"—") -> 0.070935933
A12: 2015 | B12: =IFERROR(VLOOKUP(CONCATENATE($A12,$B$6,$A$6),Supply_WF_Flow!$A$2:$K$4380,10,FALSE),"—") -> 0.048638892 | C12: =IFERROR(VLOOKUP(CONCATENATE($A12,$B$6,$A$6),Supply_WF_Flow!$A$2:$K$4380,11,FALSE),"—") -> 0.045838618 | D12: =IFERROR(VLOOKUP(CONCATENATE($A12,$C$6,$A$6),Supply_WF_Flow!$A$2:$K$4380,10,FALSE),"—") -> 0.079046247 | E12: =IFERROR(VLOOKUP(CONCATENATE($A12,$C$6,$A$6),Supply_WF_Flow!$A$2:$K$4380,11,FALSE),"—") -> 0.061332881
A13: 2016 | B13: =IFERROR(VLOOKUP(CONCATENATE($A13,$B$6,$A$6),Supply_WF_Flow!$A$2:$K$4380,10,FALSE),"—") -> 0.041311295 | C13: =IFERROR(VLOOKUP(CONCATENATE($A13,$B$6,$A$6),Supply_WF_Flow!$A$2:$K$4380,11,FALSE),"—") -> 0.047810913 | D13: =IFERROR(VLOOKUP(CONCATENATE($A13,$C$6,$A$6),Supply_WF_Flow!$A$2:$K$4380,10,FALSE),"—") -> 0.089848244 | E13: =IFERROR(VLOOKUP(CONCATENATE($A13,$C$6,$A$6),Supply_WF_Flow!$A$2:$K$4380,11,FALSE),"—") -> 0.056374295
A14: 2017 | B14: =IFERROR(VLOOKUP(CONCATENATE($A14,$B$6,$A$6),Supply_WF_Flow!$A$2:$K$4380,10,FALSE),"—") -> 0.046932648 | C14: =IFERROR(VLOOKUP(CONCATENATE($A14,$B$6,$A$6),Supply_WF_Flow!$A$2:$K$4380,11,FALSE),"—") -> 0.049032499 | D14: =IFERROR(VLOOKUP(CONCATENATE($A14,$C$6,$A$6),Supply_WF_Flow!$A$2:$K$4380,10,FALSE),"—") -> 0.077820908 | E14: =IFERROR(VLOOKUP(CONCATENATE($A14,$C$6,$A$6),Supply_WF_Flow!$A$2:$K$4380,11,FALSE),"—") -> 0.0706465
A15: 2018 | B15: =IFERROR(VLOOKUP(CONCATENATE($A15,$B$6,$A$6),Supply_WF_Flow!$A$2:$K$4380,10,FALSE),"—") -> 0.053527482 | C15: =IFERROR(VLOOKUP(CONCATENATE($A15,$B$6,$A$6),Supply_WF_Flow!$A$2:$K$4380,11,FALSE),"—") -> 0.046818235 | D15: =IFERROR(VLOOKUP(CONCATENATE($A15,$C$6,$A$6),Supply_WF_Flow!$A$2:$K$4380,10,FALSE),"—") -> 0.076505639 | E15: =IFERROR(VLOOKUP(CONCATENATE($A15,$C$6,$A$6),Supply_WF_Flow!$A$2:$K$4380,11,FALSE),"—") -> 0.074590338
A16: 2019 | B16: =IFERROR(VLOOKUP(CONCATENATE($A16,$B$6,$A$6),Supply_WF_Flow!$A$2:$K$4380,10,FALSE),"—") -> 0.060407983 | C16: =IFERROR(VLOOKUP(CONCATENATE($A16,$B$6,$A$6),Supply_WF_Flow!$A$2:$K$4380,11,FALSE),"—") -> 0.04777766 | D16: =IFERROR(VLOOKUP(CONCATENATE($A16,$C$6,$A$6),Supply_WF_Flow!$A$2:$K$4380,10,FALSE),"—") -> 0.085512999 | E16: =IFERROR(VLOOKUP(CONCATENATE($A16,$C$6,$A$6),Supply_WF_Flow!$A$2:$K$4380,11,FALSE),"—") -> 0.065087669
A17: 2020 | B17: =IFERROR(VLOOKUP(CONCATENATE($A17,$B$6,$A$6),Supply_WF_Flow!$A$2:$K$4380,10,FALSE),"—") -> 0.057746533 | C17: =IFERROR(VLOOKUP(CONCATENATE($A17,$B$6,$A$6),Supply_WF_Flow!$A$2:$K$4380,11,FALSE),"—") -> 0.047125057 | D17: =IFERROR(VLOOKUP(CONCATENATE($A17,$C$6,$A$6),Supply_WF_Flow!$A$2:$K$4380,10,FALSE),"—") -> 0.084862208 | E17: =IFERROR(VLOOKUP(CONCATENATE($A17,$C$6,$A$6),Supply_WF_Flow!$A$2:$K$4380,11,FALSE),"—") -> 0.052492088
A18: 2021 | B18: =IFERROR(VLOOKUP(CONCATENATE($A18,$B$6,$A$6),Supply_WF_Flow!$A$2:$K$4380,10,FALSE),"—") -> 0.061597636 | C18: =IFERROR(VLOOKUP(CONCATENATE($A18,$B$6,$A$6),Supply_WF_Flow!$A$2:$K$4380,11,FALSE),"—") -> 0.048895352 | D18: =IFERROR(VLOOKUP(CONCATENATE($A18,$C$6,$A$6),Supply_WF_Flow!$A$2:$K$4380,10,FALSE),"—") -> 0.087251816 | E18: =IFERROR(VLOOKUP(CONCATENATE($A18,$C$6,$A$6),Supply_WF_Flow!$A$2:$K$4380,11,FALSE),"—") -> 0.065761099
A19: 2022 | B19: =IFERROR(VLOOKUP(CONCATENATE($A19,$B$6,$A$6),Supply_WF_Flow!$A$2:$K$4380,10,FALSE),"—") -> 0.061616068 | C19: =IFERROR(VLOOKUP(CONCATENATE($A19,$B$6,$A$6),Supply_WF_Flow!$A$2:$K$4380,11,FALSE),"—") -> 0.05284154 | D19: =IFERROR(VLOOKUP(CONCATENATE($A19,$C$6,$A$6),Supply_WF_Flow!$A$2:$K$4380,10,FALSE),"—") -> 0.078281284 | E19: =IFERROR(VLOOKUP(CONCATENATE($A19,$C$6,$A$6),Supply_WF_Flow!$A$2:$K$4380,11,FALSE),"—") -> 0.054559683
A20: 2023 | B20: =IFERROR(VLOOKUP(CONCATENATE($A20,$B$6,$A$6),Supply_WF_Flow!$A$2:$K$4380,10,FALSE),"—") -> 0.074011402 | C20: =IFERROR(VLOOKUP(CONCATENATE($A20,$B$6,$A$6),Supply_WF_Flow!$A$2:$K$4380,11,FALSE),"—") -> — | D20: =IFERROR(VLOOKUP(CONCATENATE($A20,$C$6,$A$6),Supply_WF_Flow!$A$2:$K$4380,10,FALSE),"—") -> 0.077172797 | E20: =IFERROR(VLOOKUP(CONCATENATE($A20,$C$6,$A$6),Supply_WF_Flow!$A$2:$K$4380,11,FALSE),"—") -> —
A21: Notes
A22: — Data is not applicable, does not exist or is not reported due to data quality issues.
A23: † Number suppressed to prevent disclosure of small cells.
A24: For more information regarding collection and comparability of data as well as notes specific to individual provinces and territories, refer to professional-specific methodology notes.
A25: Professional-specific notes
A26: Nurse practitioners (NPs) and registered nurses (RNs)
A27: In 2016, the Association of Registered Nurses of Newfoundland and Labrador provided aggregate counts for inflow/outflow numbers containing 95 secondary registration numbers. As a result, 2016 inflow and 2015 outflow data represents RNs including NPs.
A28: For both NPs and RNs, data is reported collectively for the Northwest Territories and Nunavut; please select Northwest Territories/Nunavut to see inflow and outflow data for NPs or RNs.
A29: In the Yukon, NPs were first regulated in 2013. Data is not available prior to that year.
A30: According to the Northwest Territories Registered Nurses Association (NWTRNA), an error in the submission process in 2019 resulted in a number of NPs and RNs being excluded from supply and workforce counts. Please interpret 2018 and 2019 with caution when comparing with other years.
A31: Registered psychiatric nurses (RPNs)
A32: Record-level data for RPNs licensed in the Yukon is not submitted to the Health Workforce Database. The Yukon government provided aggregate counts.
... A49: End of worksheet (back to Table of contents)

Sheet 4 Workforce
A1: This tab provides the workforce counts and percentage changes for different types of providers for a given province or territory from 2014 to 2023. You can compare up to 3 jurisdictions. The figures and table will populate information based on your selections. Select the type of provider in cell A6. Select the main province or territory in cell B6. Select the comparator province or territory in cells C6 and D6. The table begins at cell A11 and ends at cell G21. The notes and source begin in cell A22 and end in cell A53. The figures are located in cells A8 and A9. A link back to the Table of contents is in cell A2 and A54.
A2: Back to the Table of contents
A3: =CONCATENATE("Workforce of ",LOWER(A6),", ",TRIM(B6),", 2014 to 2023") -> Workforce of registered nurses, Ontario, 2014 to 2023
A4: Instructions: Select a provider and jurisdiction from the drop-down lists in cells A6, B6, C6 and D6.
A5: Type of provider | B5: Province/territory/Canada (main) | C5: Province/territory/Canada (comparator 1) | D5: Province/territory/Canada (comparator 2)
A6: Registered nurses | B6: Ontario | C6: British Columbia | D6: Alberta
A7: Data will change in the figures and table below based on your selections above. Hover over the chart area to show values and categories. When a figure does not populate, it indicates that data for the selection is unavailable, does not exist or is not applicable.
A8: The information can be found in the table below.
A10: =CONCATENATE("Table 4 Workforce of ",LOWER(A6),", ",TRIM(B6),", 2014 to 2023") -> Table 4 Workforce of registered nurses, Ontario, 2014 to 2023
A11: Year | B11: =CONCATENATE(A6," workforce count in ", TRIM(B6)) -> Registered nurses workforce count in Ontario | C11: =CONCATENATE(A6," workforce count in ", TRIM(C6)) -> Registered nurses workforce count in British Columbia | D11: =CONCATENATE(A6," workforce count in ", TRIM(D6)) -> Registered nurses workforce count in Alberta | E11: =CONCATENATE("Percentage change from previous year for ", LOWER(A6), " workforce in ", (B6)) -> Percentage change from previous year for registered nurses workforce in Ontario | F11: =CONCATENATE("Percentage change from previous year for ", LOWER(A6), " workforce in ", (C6)) -> Percentage change from previous year for registered nurses workforce in British Columbia | G11: =CONCATENATE("Percentage change from previous year for ", LOWER(A6), " workforce in ", (D6)) -> Percentage change from previous year for registered nurses workforce in Alberta
A12: 2014 | B12: =IFERROR(VLOOKUP(CONCATENATE($A12,$B$6,$A$6),Supply_WF_Flow!$A$2:$K$4380,9,FALSE),"—") -> 95458 | C12: =IFERROR(VLOOKUP(CONCATENATE($A12,$C$6,$A$6),Supply_WF_Flow!$A$2:$K$4380,9,FALSE),"—") -> 32249 | D12: =IFERROR(VLOOKUP(CONCATENATE($A12,$D$6,$A$6),Supply_WF_Flow!$A$2:$K$4380,9,FALSE),"—") -> 32050 | E12: — | F12: — | G12: —
A13: =1+A12 -> 2015 | B13: =IFERROR(VLOOKUP(CONCATENATE($A13,$B$6,$A$6),Supply_WF_Flow!$A$2:$K$4380,9,FALSE),"—") -> 95659 | C13: =IFERROR(VLOOKUP(CONCATENATE($A13,$C$6,$A$6),Supply_WF_Flow!$A$2:$K$4380,9,FALSE),"—") -> 33545 | D13: =IFERROR(VLOOKUP(CONCATENATE($A13,$D$6,$A$6),Supply_WF_Flow!$A$2:$K$4380,9,FALSE),"—") -> 33773 | E13: =IFERROR(IF(OR(B12=0,B12="—",B13="—"),"—",(B13-B12)/B12),"—") -> 0.0021056381 | F13: =IFERROR(IF(OR(C12=0,C12="—",C13="—"),"—",(C13-C12)/C12),"—") -> 0.040187293 | G13: =IFERROR(IF(OR(D12=0,D12="—",D13="—"),"—",(D13-D12)/D12),"—") -> 0.05375975
A14: =1+A13 -> 2016 | B14: =IFERROR(VLOOKUP(CONCATENATE($A14,$B$6,$A$6),Supply_WF_Flow!$A$2:$K$4380,9,FALSE),"—") -> 95609 | C14: =IFERROR(VLOOKUP(CONCATENATE($A14,$C$6,$A$6),Supply_WF_Flow!$A$2:$K$4380,9,FALSE),"—") -> 34405 | D14: =IFERROR(VLOOKUP(CONCATENATE($A14,$D$6,$A$6),Supply_WF_Flow!$A$2:$K$4380,9,FALSE),"—") -> 34651 | E14: =IFERROR(IF(OR(B13=0,B13="—",B14="—"),"—",(B14-B13)/B13),"—") -> -0.00052268997 | F14: =IFERROR(IF(OR(C13=0,C13="—",C14="—"),"—",(C14-C13)/C13),"—") -> 0.025637204 | G14: =IFERROR(IF(OR(D13=0,D13="—",D14="—"),"—",(D14-D13)/D13),"—") -> 0.025997098
A15: =1+A14 -> 2017 | B15: =IFERROR(VLOOKUP(CONCATENATE($A15,$B$6,$A$6),Supply_WF_Flow!$A$2:$K$4380,9,FALSE),"—") -> 94948 | C15: =IFERROR(VLOOKUP(CONCATENATE($A15,$C$6,$A$6),Supply_WF_Flow!$A$2:$K$4380,9,FALSE),"—") -> 35207 | D15: =IFERROR(VLOOKUP(CONCATENATE($A15,$D$6,$A$6),Supply_WF_Flow!$A$2:$K$4380,9,FALSE),"—") -> 34356 | E15: =IFERROR(IF(OR(B14=0,B14="—",B15="—"),"—",(B15-B14)/B14),"—") -> -0.0069135751 | F15: =IFERROR(IF(OR(C14=0,C14="—",C15="—"),"—",(C15-C14)/C14),"—") -> 0.023310565 | G15: =IFERROR(IF(OR(D14=0,D14="—",D15="—"),"—",(D15-D14)/D14),"—") -> -0.0085134628
A16: =1+A15 -> 2018 | B16: =IFERROR(VLOOKUP(CONCATENATE($A16,$B$6,$A$6),Supply_WF_Flow!$A$2:$K$4380,9,FALSE),"—") -> 95814 | C16: =IFERROR(VLOOKUP(CONCATENATE($A16,$C$6,$A$6),Supply_WF_Flow!$A$2:$K$4380,9,FALSE),"—") -> 35495 | D16: =IFERROR(VLOOKUP(CONCATENATE($A16,$D$6,$A$6),Supply_WF_Flow!$A$2:$K$4380,9,FALSE),"—") -> 34079 | E16: =IFERROR(IF(OR(B15=0,B15="—",B16="—"),"—",(B16-B15)/B15),"—") -> 0.0091207819 | F16: =IFERROR(IF(OR(C15=0,C15="—",C16="—"),"—",(C16-C15)/C15),"—") -> 0.0081801914 | G16: =IFERROR(IF(OR(D15=0,D15="—",D16="—"),"—",(D16-D15)/D15),"—") -> -0.0080626383
A17: =1+A16 -> 2019 | B17: =IFERROR(VLOOKUP(CONCATENATE($A17,$B$6,$A$6),Supply_WF_Flow!$A$2:$K$4380,9,FALSE),"—") -> 97575 | C17: =IFERROR(VLOOKUP(CONCATENATE($A17,$C$6,$A$6),Supply_WF_Flow!$A$2:$K$4380,9,FALSE),"—") -> 35516 | D17: =IFERROR(VLOOKUP(CONCATENATE($A17,$D$6,$A$6),Supply_WF_Flow!$A$2:$K$4380,9,FALSE),"—") -> 34372 | E17: =IFERROR(IF(OR(B16=0,B16="—",B17="—"),"—",(B17-B16)/B16),"—") -> 0.01837936 | F17: =IFERROR(IF(OR(C16=0,C16="—",C17="—"),"—",(C17-C16)/C16),"—") -> 0.00059163262 | G17: =IFERROR(IF(OR(D16=0,D16="—",D17="—"),"—",(D17-D16)/D16),"—") -> 0.0085976701
A18: =1+A17 -> 2020 | B18: =IFERROR(VLOOKUP(CONCATENATE($A18,$B$6,$A$6),Supply_WF_Flow!$A$2:$K$4380,9,FALSE),"—") -> 97920 | C18: =IFERROR(VLOOKUP(CONCATENATE($A18,$C$6,$A$6),Supply_WF_Flow!$A$2:$K$4380,9,FALSE),"—") -> 35880 | D18: =IFERROR(VLOOKUP(CONCATENATE($A18,$D$6,$A$6),Supply_WF_Flow!$A$2:$K$4380,9,FALSE),"—") -> 34627 | E18: =IFERROR(IF(OR(B17=0,B17="—",B18="—"),"—",(B18-B17)/B17),"—") -> 0.0035357417 | F18: =IFERROR(IF(OR(C17=0,C17="—",C18="—"),"—",(C18-C17)/C17),"—") -> 0.010248902 | G18: =IFERROR(IF(OR(D17=0,D17="—",D18="—"),"—",(D18-D17)/D17),"—") -> 0.0074188293
A19: =1+A18 -> 2021 | B19: =IFERROR(VLOOKUP(CONCATENATE($A19,$B$6,$A$6),Supply_WF_Flow!$A$2:$K$4380,9,FALSE),"—") -> 98899 | C19: =IFERROR(VLOOKUP(CONCATENATE($A19,$C$6,$A$6),Supply_WF_Flow!$A$2:$K$4380,9,FALSE),"—") -> 38288 | D19: =IFERROR(VLOOKUP(CONCATENATE($A19,$D$6,$A$6),Supply_WF_Flow!$A$2:$K$4380,9,FALSE),"—") -> 34380 | E19: =IFERROR(IF(OR(B18=0,B18="—",B19="—"),"—",(B19-B18)/B18),"—") -> 0.0099979575 | F19: =IFERROR(IF(OR(C18=0,C18="—",C19="—"),"—",(C19-C18)/C18),"—") -> 0.067112598 | G19: =IFERROR(IF(OR(D18=0,D18="—",D19="—"),"—",(D19-D18)/D18),"—") -> -0.007133162
A20: =1+A19 -> 2022 | B20: =IFERROR(VLOOKUP(CONCATENATE($A20,$B$6,$A$6),Supply_WF_Flow!$A$2:$K$4380,9,FALSE),"—") -> 99839 | C20: =IFERROR(VLOOKUP(CONCATENATE($A20,$C$6,$A$6),Supply_WF_Flow!$A$2:$K$4380,9,FALSE),"—") -> 38935 | D20: =IFERROR(VLOOKUP(CONCATENATE($A20,$D$6,$A$6),Supply_WF_Flow!$A$2:$K$4380,9,FALSE),"—") -> 34399 | E20: =IFERROR(IF(OR(B19=0,B19="—",B20="—"),"—",(B20-B19)/B19),"—") -> 0.0095046462 | F20: =IFERROR(IF(OR(C19=0,C19="—",C20="—"),"—",(C20-C19)/C19),"—") -> 0.016898245 | G20: =IFERROR(IF(OR(D19=0,D19="—",D20="—"),"—",(D20-D19)/D19),"—") -> 0.00055264689
A21: =1+A20 -> 2023 | B21: =IFERROR(VLOOKUP(CONCATENATE($A21,$B$6,$A$6),Supply_WF_Flow!$A$2:$K$4380,9,FALSE),"—") -> 101599 | C21: =IFERROR(VLOOKUP(CONCATENATE($A21,$C$6,$A$6),Supply_WF_Flow!$A$2:$K$4380,9,FALSE),"—") -> 39516 | D21: =IFERROR(VLOOKUP(CONCATENATE($A21,$D$6,$A$6),Supply_WF_Flow!$A$2:$K$4380,9,FALSE),"—") -> 34471 | E21: =IFERROR(IF(OR(B20=0,B20="—",B21="—"),"—",(B21-B20)/B20),"—") -> 0.017628382 | F21: =IFERROR(IF(OR(C20=0,C20="—",C21="—"),"—",(C21-C20)/C20),"—") -> 0.014922306 | G21: =IFERROR(IF(OR(D20=0,D20="—",D21="—"),"—",(D21-D20)/D20),"—") -> 0.0020930841
A22: Notes
A23: — Data is not applicable, does not exist or is not reported due to data quality issues.
A24: The dotted line in the percentage change figure represents a linear trend.
A25: Workforce refers to only those professionals who were employed at the time of annual registration.
A26: For more data on the workforce of health care professionals in Canada, refer to professional-specific data tables.
A27: For more information regarding collection and comparability of data as well as notes specific to individual provinces and territories, refer to professional-specific methodology notes.
A28: Professional-specific notes
A29: Nurse practitioners (NPs) and registered nurses (RNs)
A30: Employment data for NPs and RNs in Manitoba for 2019 to 2020 has been suppressed due to significant under-coverage as a result of voluntary reporting. The corresponding information for 2014 to 2018 should be used with caution, as it was also reported voluntarily and may also be understated. Workforce data for NPs and RNs in Manitoba for 2021 and 2022 is not available.
A31: For both NPs and RNs, data is reported collectively for the Northwest Territories and Nunavut; please select Northwest Territories/Nunavut to see workforce data for NPs or RNs.
A32: According to the Northwest Territories Registered Nurses Association (NWTRNA), an error in the submission process in 2019 resulted in a number of NPs and RNs being excluded from supply and workforce counts. Please interpret 2018 and 2019 with caution when comparing with other years.
A33: Workforce data for Prince Edward Island is not available for RNs (2021 and 2022) and NPs (2021).
... A54: End of worksheet (back to Table of contents)

Sheet 5 Direct care
A1: This tab provides the count and percentage changes for different types of providers working in direct care for a given province or territory from 2019 to 2023. You can compare up to 2 jurisdictions. The figures and tables will populate information based on your selections. Select the type of provider in cell A6. Select the main province or territory in cell B6. Select the comparator province or territory in cell C6. There are 2 tables on this tab. The first table begins at cell A11 and ends at cell C16. The second table begins at cell A18 and ends at cell C23. The notes and source begin in cell A24 and end in cell A54. The figures are located in cells A8 and A9. A link back to the Table of contents is in cell A2 and A55.
A2: Back to the Table of contents
A3: =CONCATENATE(A6," working in direct care, ",TRIM(B6),", 2019 to 2023") -> Registered nurses working in direct care, Ontario, 2019 to 2023
A4: Instructions: Select a provider and jurisdictions from the drop-down lists in cells A6, B6 and C6.
A5: Type of provider | B5: Province/territory/Canada (main) | C5: Province/territory/Canada (comparator)
A6: Registered nurses | B6: Ontario | C6: British Columbia
A7: Data will change in the figures and table below based on your selections above. Hover over the chart area to show values and categories. When a figure does not populate, it indicates that data for the selection is unavailable, does not exist or is not applicable.
A8: The information can be found in the table below.
A10: =CONCATENATE("Table 5a ",A6," working in direct care, ",TRIM(B6),", 2019 to 2023") -> Table 5a Registered nurses working in direct care, Ontario, 2019 to 2023
A11: Year | B11: =CONCATENATE(A6," working in direct care, ",TRIM(B6)) -> Registered nurses working in direct care, Ontario | C11: =CONCATENATE("Percentage change from previous year for ",LOWER(A6)," working in direct care, ",TRIM(B6)) -> Percentage change from previous year for registered nurses working in direct care, Ontario
A12: 2019 | B12: =IFERROR(VLOOKUP(CONCATENATE($A12,$B$6,$A$6),DirectCareData!$A$2:$J$9051,6,FALSE),"—") -> 88380 | C12: =IFERROR(IF(OR(#REF!=0,B12="—",#REF!="—"),"—",(B12-#REF!)/B12),"—") -> —
A13: 2020 | B13: =IFERROR(VLOOKUP(CONCATENATE($A13,$B$6,$A$6),DirectCareData!$A$2:$J$9051,6,FALSE),"—") -> 88752 | C13: =IFERROR(IF(OR(B12=0,B13="—",B12="—"),"—",(B13-B12)/B12),"—") -> 0.0042090971
A14: 2021 | B14: =IFERROR(VLOOKUP(CONCATENATE($A14,$B$6,$A$6),DirectCareData!$A$2:$J$9051,6,FALSE),"—") -> 89915 | C14: =IFERROR(IF(OR(B13=0,B14="—",B13="—"),"—",(B14-B13)/B13),"—") -> 0.01310393
A15: 2022 | B15: =IFERROR(VLOOKUP(CONCATENATE($A15,$B$6,$A$6),DirectCareData!$A$2:$J$9051,6,FALSE),"—") -> 90692 | C15: =IFERROR(IF(OR(B14=0,B15="—",B14="—"),"—",(B15-B14)/B14),"—") -> 0.0086414947
A16: 2023 | B16: =IFERROR(VLOOKUP(CONCATENATE($A16,$B$6,$A$6),DirectCareData!$A$2:$J$9051,6,FALSE),"—") -> 92238 | C16: =IFERROR(IF(OR(B15=0,B16="—",B15="—"),"—",(B16-B15)/B15),"—") -> 0.017046708
A17: =CONCATENATE("Table 5b Percentage of ",LOWER(A6)," supply working in direct care, ",TRIM(B6)," and ", TRIM(C6),", 2019 to 2023") -> Table 5b Percentage of registered nurses supply working in direct care, Ontario and British Columbia, 2019 to 2023
A18: Year | B18: =CONCATENATE("Percentage of ",LOWER(A6)," supply working in direct care, ",TRIM(B6)) -> Percentage of registered nurses supply working in direct care, Ontario | C18: =CONCATENATE("Percentage of ",LOWER(A6)," supply working in direct care, ",TRIM(C6)) -> Percentage of registered nurses supply working in direct care, British Columbia
A19: 2019 | B19: =IFERROR(VLOOKUP(CONCATENATE($A19,$B$6,$A$6),DirectCareData!$A$2:$J$9051,7,FALSE),"—") -> 0.85081394 | C19: =IFERROR(VLOOKUP(CONCATENATE($A19,$C$6,$A$6),DirectCareData!$A$2:$J$9051,7,FALSE),"—") -> 0.82476801
A20: 2020 | B20: =IFERROR(VLOOKUP(CONCATENATE($A20,$B$6,$A$6),DirectCareData!$A$2:$J$9051,7,FALSE),"—") -> 0.84545039 | C20: =IFERROR(VLOOKUP(CONCATENATE($A20,$C$6,$A$6),DirectCareData!$A$2:$J$9051,7,FALSE),"—") -> 0.84862208
A21: =A20+1 -> 2021 | B21: =IFERROR(VLOOKUP(CONCATENATE($A21,$B$6,$A$6),DirectCareData!$A$2:$J$9051,7,FALSE),"—") -> 0.84351986 | C21: =IFERROR(VLOOKUP(CONCATENATE($A21,$C$6,$A$6),DirectCareData!$A$2:$J$9051,7,FALSE),"—") -> 0.86518107
A22: =A21+1 -> 2022 | B22: =IFERROR(VLOOKUP(CONCATENATE($A22,$B$6,$A$6),DirectCareData!$A$2:$J$9051,7,FALSE),"—") -> 0.83942984 | C22: =IFERROR(VLOOKUP(CONCATENATE($A22,$C$6,$A$6),DirectCareData!$A$2:$J$9051,7,FALSE),"—") -> 0.86552053
A23: =A22+1 -> 2023 | B23: =IFERROR(VLOOKUP(CONCATENATE($A23,$B$6,$A$6),DirectCareData!$A$2:$J$9051,7,FALSE),"—") -> 0.8346575 | C23: =IFERROR(VLOOKUP(CONCATENATE($A23,$C$6,$A$6),DirectCareData!$A$2:$J$9051,7,FALSE),"—") -> 0.85582317
A24: Notes
A25: — Data is not applicable, does not exist or is not reported due to data quality issues.
A26: † Number suppressed to prevent disclosure of small cells.
A27: If more than 30% of records in a province/territory have a not stated value (i.e., unknown, not applicable or not collected) for a data element, statistics based on that element are not reported. When the population of provinces/territories for which the data is unavailable exceeds 35% of the total Canadian population, no overall result is reported for provinces/territories with available data.
A28: When direct care data is not available for a province/territory, that province/territory is also excluded from the Provinces/territories with available data supply total used to calculated Percentage of supply working in direct care.
A29: The dotted line in the percentage change figure represents a linear trend.
A30: Direct care refers to only those registrants who provided services directly to clients.
A31: For more data on health care professionals working in direct care in Canada, including the number working in direct care per 100,000 population, refer to professional-specific data tables.
A32: For more information regarding collection and comparability of data as well as notes specific to individual provinces and territories, refer to professional-specific methodology notes.
A33: Professional-specific notes
A34: Nurse practitioners (NPs) and registered nurses (RNs)
A35: Employment data for NPs and RNs in Manitoba for 2019 to 2021 has been suppressed due to significant under-coverage as a result of voluntary reporting. The corresponding information for 2014 to 2018 should be used with caution, as it was also reported voluntarily and may also be understated.
... A55: End of worksheet (back to Table of contents)

Sheet 6 New graduate migrations
A1: This tab provides a snapshot of the migration of recent graduates of different types of providers. The figures and table will populate information based on your selections. Select the province/territory of graduation in cell A6. Select the type of provider in cell B6. The table begins at cell A10 and ends at D24. The notes and sources begin in cell A25 and end in cell A48. There is 1 figure in cell A8. A link back to the Table of contents is in cell A2 and A49.
A2: Back to the Table of contents
A3: =IF(B6="Family medicine physicians",CONCATENATE("Family medicine physicians who obtained their MD degree (2017 to 2021) in"," ",A6," ","and their province/territory in 2023"),IF(B6="Specialists",CONCATENATE("Specialists who obtained their MD degree (2014 to 2018) in"," ",A6," ","and their province/territory in 2023"),CONCATENATE(A6," ",LOWER(LEFT(B6,(LEN(B6)-1)))," graduates (2019 to 2023) and their province/territory in 2023"))) -> Ontario nurse practitioners/registered nurses graduates (2019 to 2023) and their province/territory in 2023
A4: Instructions: Select a jurisdiction of graduation and provider from the drop-down lists in cells A6 and B6.
A5: Province/territory of graduation | B5: Provider type
A6: Ontario | B6: Nurse practitioners/registered nurses*
A7: Data will change in the figure and table below based on your selections above. Hover over the chart area to show values and categories. When a figure does not populate, it indicates that data for the selection is unavailable, does not exist or is not applicable.
A8: The information can be found in the table below.
A9: =IF(B6="Family medicine physicians",CONCATENATE("Table 6"," ",A6," ",LOWER(B6)," graduates (2017 to 2021) and their province/territory in 2023"),IF(B6="Specialists",CONCATENATE("Table 6"," ",A6," ",LOWER(B6)," graduates (2014 to 2018) and their province/territory in 2023"),CONCATENATE("Table 6 ",A6," ",LOWER(B6)," graduates (2019 to 2023) and their province/territory of registration in 2023"))) -> Table 6 Ontario nurse practitioners/registered nurses* graduates (2019 to 2023) and their province/territory of registration in 2023
A10: Year | B10: =IF(B6="Family medicine physicians","Province/territory ","Province of registration") -> Province of registration | C10: =CONCATENATE("Number of ",LOWER(B6), " graduated from"," ",A6) -> Number of nurse practitioners/registered nurses* graduated from Ontario | D10: =CONCATENATE("Percentage of total graduates from"," ",A6) -> Percentage of total graduates from Ontario
A11: 2023 | B11: =IFERROR(VLOOKUP(CONCATENATE($A$11,$B$6,$A$6),GradsData!$A$2:$AZ$50,5,FALSE),"—") -> Ontario | C11: =IFERROR(VLOOKUP(CONCATENATE($A$11,$B$6,$A$6),GradsData!$A$2:$AZ$50,18,FALSE),"—") -> 15798 | D11: =IFERROR(VLOOKUP(CONCATENATE($A$17,$B$6,$A$6),GradsData!$A$2:$AZ$50,32,FALSE),"—") -> 0.9512856
A12: 2023 | B12: =IFERROR(VLOOKUP(CONCATENATE($A$12,$B$6,$A$6),GradsData!$A$2:$AZ$50,6,FALSE),"—") -> British Columbia | C12: =IFERROR(VLOOKUP(CONCATENATE($A$17,$B$6,$A$6),GradsData!$A$2:$AZ$50,19,FALSE),"—") -> 369 | D12: =IFERROR(VLOOKUP(CONCATENATE($A$17,$B$6,$A$6),GradsData!$A$2:$AZ$50,33,FALSE),"—") -> 0.022219546
A13: 2023 | B13: =IFERROR(VLOOKUP(CONCATENATE($A$12,$B$6,$A$6),GradsData!$A$2:$AZ$50,7,FALSE),"—") -> Alberta | C13: =IFERROR(VLOOKUP(CONCATENATE($A$17,$B$6,$A$6),GradsData!$A$2:$AZ$50,20,FALSE),"—") -> 122 | D13: =IFERROR(VLOOKUP(CONCATENATE($A$17,$B$6,$A$6),GradsData!$A$2:$AZ$50,34,FALSE),"—") -> 0.0073462998
A14: 2023 | B14: =IFERROR(VLOOKUP(CONCATENATE($A$14,$B$6,$A$6),GradsData!$A$2:$AZ$50,8,FALSE),"—") -> Nova Scotia | C14: =IFERROR(VLOOKUP(CONCATENATE($A$17,$B$6,$A$6),GradsData!$A$2:$AZ$50,21,FALSE),"—") -> 93 | D14: =IFERROR(VLOOKUP(CONCATENATE($A$17,$B$6,$A$6),GradsData!$A$2:$AZ$50,35,FALSE),"—") -> 0.0056000482
A15: 2023 | B15: =IFERROR(VLOOKUP(CONCATENATE($A$12,$B$6,$A$6),GradsData!$A$2:$AZ$50,9,FALSE),"—") -> Manitoba | C15: =IFERROR(VLOOKUP(CONCATENATE($A$17,$B$6,$A$6),GradsData!$A$2:$AZ$50,22,FALSE),"—") -> 44 | D15: =IFERROR(VLOOKUP(CONCATENATE($A$17,$B$6,$A$6),GradsData!$A$2:$AZ$50,36,FALSE),"—") -> 0.0026494852
A16: 2023 | B16: =IFERROR(VLOOKUP(CONCATENATE($A$16,$B$6,$A$6),GradsData!$A$2:$AZ$50,10,FALSE),"—") -> Northwest Territories/Nunavut | C16: =IFERROR(VLOOKUP(CONCATENATE($A$17,$B$6,$A$6),GradsData!$A$2:$AZ$50,23,FALSE),"—") -> 43 | D16: =IFERROR(VLOOKUP(CONCATENATE($A$17,$B$6,$A$6),GradsData!$A$2:$AZ$50,37,FALSE),"—") -> 0.0025892696
A17: 2023 | B17: =IFERROR(VLOOKUP(CONCATENATE($A$16,$B$6,$A$6),GradsData!$A$2:$AZ$50,11,FALSE),"—") -> Quebec | C17: =IFERROR(VLOOKUP(CONCATENATE($A$17,$B$6,$A$6),GradsData!$A$2:$AZ$50,24,FALSE),"—") -> 41 | D17: =IFERROR(VLOOKUP(CONCATENATE($A$17,$B$6,$A$6),GradsData!$A$2:$AZ$50,38,FALSE),"—") -> 0.0024688384
A18: 2023 | B18: =IFERROR(VLOOKUP(CONCATENATE($A$16,$B$6,$A$6),GradsData!$A$2:$AZ$50,12,FALSE),"—") -> New Brunswick | C18: =IFERROR(VLOOKUP(CONCATENATE($A$17,$B$6,$A$6),GradsData!$A$2:$AZ$50,25,FALSE),"—") -> 24 | D18: =IFERROR(VLOOKUP(CONCATENATE($A$17,$B$6,$A$6),GradsData!$A$2:$AZ$50,39,FALSE),"—") -> 0.0014451737
A19: 2023 | B19: =IFERROR(VLOOKUP(CONCATENATE($A$16,$B$6,$A$6),GradsData!$A$2:$AZ$50,13,FALSE),"—") -> Prince Edward Island | C19: =IFERROR(VLOOKUP(CONCATENATE($A$17,$B$6,$A$6),GradsData!$A$2:$AZ$50,26,FALSE),"—") -> 22 | D19: =IFERROR(VLOOKUP(CONCATENATE($A$17,$B$6,$A$6),GradsData!$A$2:$AZ$50,40,FALSE),"—") -> 0.0013247426
A20: 2023 | B20: =IFERROR(VLOOKUP(CONCATENATE($A$17,$B$6,$A$6),GradsData!$A$2:$AZ$50,14,FALSE),"—") -> Saskatchewan | C20: =IFERROR(VLOOKUP(CONCATENATE($A$17,$B$6,$A$6),GradsData!$A$2:$AZ$50,27,FALSE),"—") -> 19 | D20: =IFERROR(VLOOKUP(CONCATENATE($A$17,$B$6,$A$6),GradsData!$A$2:$AZ$50,41,FALSE),"—") -> 0.0011440959
A21: 2023 | B21: =IFERROR(VLOOKUP(CONCATENATE($A$17,$B$6,$A$6),GradsData!$A$2:$AZ$50,15,FALSE),"—") -> Yukon | C21: =IFERROR(VLOOKUP(CONCATENATE($A$17,$B$6,$A$6),GradsData!$A$2:$AZ$50,28,FALSE),"—") -> 19 | D21: =IFERROR(VLOOKUP(CONCATENATE($A$17,$B$6,$A$6),GradsData!$A$2:$AZ$50,42,FALSE),"—") -> 0.0011440959
A22: 2023 | B22: =IFERROR(VLOOKUP(CONCATENATE($A$17,$B$6,$A$6),GradsData!$A$2:$AZ$50,16,FALSE),"—") -> Newfoundland and Labrador | C22: =IFERROR(VLOOKUP(CONCATENATE($A$17,$B$6,$A$6),GradsData!$A$2:$AZ$50,29,FALSE),"—") -> 13 | D22: =IFERROR(VLOOKUP(CONCATENATE($A$17,$B$6,$A$6),GradsData!$A$2:$AZ$50,43,FALSE),"—") -> 0.00078280243
A23: 2023 | B23: =IFERROR(VLOOKUP(CONCATENATE($A$17,$B$6,$A$6),GradsData!$A$2:$AZ$50,17,FALSE),"—") -> — | C23: =IFERROR(VLOOKUP(CONCATENATE($A$17,$B$6,$A$6),GradsData!$A$2:$AZ$50,30,FALSE),"—") -> — | D23: =IFERROR(VLOOKUP(CONCATENATE($A$17,$B$6,$A$6),GradsData!$A$2:$AZ$50,44,FALSE),"—") -> —
A24: 2023 | B24: =IFERROR(VLOOKUP(CONCATENATE($A$17,$B$6,$A$6),GradsData!$A$2:$AZ$50,49,FALSE),"—") -> Other provinces and territories^ | C24: =IFERROR(VLOOKUP(CONCATENATE($A$17,$B$6,$A$6),GradsData!$A$2:$AZ$50,47,FALSE),"—") -> 225 | D24: =IFERROR(VLOOKUP(CONCATENATE($A$17,$B$6,$A$6),GradsData!$A$2:$AZ$50,48,FALSE),"—") -> 0.013548504
A25: Notes
A26: — Data is not applicable, does not exist or is not reported due to data quality issues.
A27: ^ Other provinces and territories refers to the total of the non-top-4 provinces and territories of registration or practice.
A28: This tab presents the current province/territory of registration or practice of recent regulated nursing, family medicine physician and specialist physician graduates. While the data demonstrates recent graduate migration from the selected province/territory of graduation, it is important to note that not all provinces/territories may offer a nursing or MD program, which may also contribute to migration of graduates.
A29: Professional-specific notes
A30: Regulated nurses (nurse practitioners/registered nurses,* registered psychiatric nurses and licensed practical nurses)
A31: Data for nurse practitioners (NPs), registered nurses (RNs), registered psychiatric nurses (RPNs) and licensed practical nurses (LPNs) includes those who registered to practise in 2023 (supply) and graduated from a nursing program in the selected province/territory between 2019 and 2023, and is broken down according to the province/territory in which they registered to practise in 2023.
A32: * For NPs, year of graduation may reflect their initial RN education. Therefore, the number of new graduates may be understated.
A33: Excludes regulated nurses where province/territory of graduation is unknown.
A34: Location of graduation is not consistently available for RPNs in British Columbia in 2023. Therefore, the number of RPNs remaining in/migrating to British Columbia may be understated.
A35: RPNs are currently regulated in the 4 western provinces (Manitoba, Saskatchewan, Alberta and British Columbia) and the Yukon.
A36: Physicians
... A49: End of worksheet (back to Table of contents)

Sheet 7 Hospital Staffing indicators
A1: This tab provides data on selected Hospital Staffing indicators by hospital service area and province/territory. The figures and table will populate information based on your selections. Select the province/territory in cell A6. There are 7 tables on this tab. The first table begins at cell A11 and ends at cell H16. The second table begins at cell A18 and ends at cell H23. The third table begins at cell A25 and ends at cell H30. The fourth table begins at cell A32 and ends at cell H37. The fifth table begins at cell A39 and ends at cell H44. The sixth table begins at cell A46 and ends at cell H51. The last table begins at cell A53 and ends at cell H58. The notes and sources begin in cell A59 and end in cell A77. There are 6 figures in cells A8 and A9. A link back to the Table of contents is in cell A2 and A78.
A2: Back to the Table of contents
A3: =CONCATENATE("Selected Hospital Staffing indicators, ",A6,", 2019–2020 to 2023–2024") -> Selected Hospital Staffing indicators, Ontario, 2019–2020 to 2023–2024
A4: Instructions: Select a jurisdiction from the drop-down list in cell A6.
A5: Province/territory
A6: Ontario
A7: Data will change in the figures and table below based on your selections above. Hover over the chart area to show values and categories. When a figure does not populate, it indicates that data for the selection is unavailable, does not exist or is not applicable.
A8: The information can be found in the table below.
A10: =CONCATENATE("Table 7a Overtime hours as a percentage of worked hours, by hospital service area, ",A6, ", 2019–2020 to 2023–2024") -> Table 7a Overtime hours as a percentage of worked hours, by hospital service area, Ontario, 2019–2020 to 2023–2024
A11: Fiscal year | B11: Administrative and support services | C11: Nursing inpatient services | D11: Ambulatory care services | E11: Diagnostic and therapeutic services | F11: Community health services | G11: Research, education and other services | H11: Total
A12: 2019–2020 | B12: =IFERROR(VLOOKUP(CONCATENATE($A$6,$A12,$B$11,),StaffingData!$A$3:$AE$1001,24,FALSE),"—") -> 0.012609472 | C12: =IFERROR(VLOOKUP(CONCATENATE($A$6,$A12,$C$11,),StaffingData!$A$3:$AE$1001,24,FALSE),"—") -> 0.033519327 | D12: =IFERROR(VLOOKUP(CONCATENATE($A$6,$A12,$D$11,),StaffingData!$A$3:$AE$1001,24,FALSE),"—") -> 0.030170914 | E12: =IFERROR(VLOOKUP(CONCATENATE($A$6,$A12,$E$11,),StaffingData!$A$3:$AE$1001,24,FALSE),"—") -> 0.013222947 | F12: =IFERROR(VLOOKUP(CONCATENATE($A$6,$A12,$F$11,),StaffingData!$A$3:$AE$1001,24,FALSE),"—") -> 0.006453154 | G12: =IFERROR(VLOOKUP(CONCATENATE($A$6,$A12,$G$11,),StaffingData!$A$3:$AE$1001,24,FALSE),"—") -> 0.0055940467 | H12: =IFERROR(VLOOKUP(CONCATENATE($A$6,$A12,$H$11,),StaffingData!$A$3:$AE$1001,24,FALSE),"—") -> 0.022021144
A13: 2020–2021 | B13: =IFERROR(VLOOKUP(CONCATENATE($A$6,$A13,$B$11,),StaffingData!$A$3:$AE$1001,24,FALSE),"—") -> 0.015413627 | C13: =IFERROR(VLOOKUP(CONCATENATE($A$6,$A13,$C$11,),StaffingData!$A$3:$AE$1001,24,FALSE),"—") -> 0.03944467 | D13: =IFERROR(VLOOKUP(CONCATENATE($A$6,$A13,$D$11,),StaffingData!$A$3:$AE$1001,24,FALSE),"—") -> 0.032051633 | E13: =IFERROR(VLOOKUP(CONCATENATE($A$6,$A13,$E$11,),StaffingData!$A$3:$AE$1001,24,FALSE),"—") -> 0.018854565 | F13: =IFERROR(VLOOKUP(CONCATENATE($A$6,$A13,$F$11,),StaffingData!$A$3:$AE$1001,24,FALSE),"—") -> 0.021889509 | G13: =IFERROR(VLOOKUP(CONCATENATE($A$6,$A13,$G$11,),StaffingData!$A$3:$AE$1001,24,FALSE),"—") -> 0.0037313679 | H13: =IFERROR(VLOOKUP(CONCATENATE($A$6,$A13,$H$11,),StaffingData!$A$3:$AE$1001,24,FALSE),"—") -> 0.026111677
A14: 2021–2022 | B14: =IFERROR(VLOOKUP(CONCATENATE($A$6,$A14,$B$11,),StaffingData!$A$3:$AE$1001,24,FALSE),"—") -> 0.0203377 | C14: =IFERROR(VLOOKUP(CONCATENATE($A$6,$A14,$C$11,),StaffingData!$A$3:$AE$1001,24,FALSE),"—") -> 0.056544669 | D14: =IFERROR(VLOOKUP(CONCATENATE($A$6,$A14,$D$11,),StaffingData!$A$3:$AE$1001,24,FALSE),"—") -> 0.044392773 | E14: =IFERROR(VLOOKUP(CONCATENATE($A$6,$A14,$E$11,),StaffingData!$A$3:$AE$1001,24,FALSE),"—") -> 0.02056626 | F14: =IFERROR(VLOOKUP(CONCATENATE($A$6,$A14,$F$11,),StaffingData!$A$3:$AE$1001,24,FALSE),"—") -> 0.021437995 | G14: =IFERROR(VLOOKUP(CONCATENATE($A$6,$A14,$G$11,),StaffingData!$A$3:$AE$1001,24,FALSE),"—") -> 0.0061034522 | H14: =IFERROR(VLOOKUP(CONCATENATE($A$6,$A14,$H$11,),StaffingData!$A$3:$AE$1001,24,FALSE),"—") -> 0.035204495
A15: 2022–2023 | B15: =IFERROR(VLOOKUP(CONCATENATE($A$6,$A15,$B$11,),StaffingData!$A$3:$AE$1001,24,FALSE),"—") -> 0.024522211 | C15: =IFERROR(VLOOKUP(CONCATENATE($A$6,$A15,$C$11,),StaffingData!$A$3:$AE$1001,24,FALSE),"—") -> 0.073652699 | D15: =IFERROR(VLOOKUP(CONCATENATE($A$6,$A15,$D$11,),StaffingData!$A$3:$AE$1001,24,FALSE),"—") -> 0.054576274 | E15: =IFERROR(VLOOKUP(CONCATENATE($A$6,$A15,$E$11,),StaffingData!$A$3:$AE$1001,24,FALSE),"—") -> 0.025276372 | F15: =IFERROR(VLOOKUP(CONCATENATE($A$6,$A15,$F$11,),StaffingData!$A$3:$AE$1001,24,FALSE),"—") -> 0.014346088 | G15: =IFERROR(VLOOKUP(CONCATENATE($A$6,$A15,$G$11,),StaffingData!$A$3:$AE$1001,24,FALSE),"—") -> 0.0064026801 | H15: =IFERROR(VLOOKUP(CONCATENATE($A$6,$A15,$H$11,),StaffingData!$A$3:$AE$1001,24,FALSE),"—") -> 0.044911953
A16: 2023–2024 | B16: =IFERROR(VLOOKUP(CONCATENATE($A$6,$A16,$B$11,),StaffingData!$A$3:$AE$1001,24,FALSE),"—") -> 0.017987208 | C16: =IFERROR(VLOOKUP(CONCATENATE($A$6,$A16,$C$11,),StaffingData!$A$3:$AE$1001,24,FALSE),"—") -> 0.065439641 | D16: =IFERROR(VLOOKUP(CONCATENATE($A$6,$A16,$D$11,),StaffingData!$A$3:$AE$1001,24,FALSE),"—") -> 0.046662372 | E16: =IFERROR(VLOOKUP(CONCATENATE($A$6,$A16,$E$11,),StaffingData!$A$3:$AE$1001,24,FALSE),"—") -> 0.022089539 | F16: =IFERROR(VLOOKUP(CONCATENATE($A$6,$A16,$F$11,),StaffingData!$A$3:$AE$1001,24,FALSE),"—") -> 0.007384764 | G16: =IFERROR(VLOOKUP(CONCATENATE($A$6,$A16,$G$11,),StaffingData!$A$3:$AE$1001,24,FALSE),"—") -> 0.0052627948 | H16: =IFERROR(VLOOKUP(CONCATENATE($A$6,$A16,$H$11,),StaffingData!$A$3:$AE$1001,24,FALSE),"—") -> 0.03888858
A17: =CONCATENATE("Table 7b Calculated full-time equivalents (FTEs), by hospital service area, ",A6,", 2019–2020 to 2023–2024") -> Table 7b Calculated full-time equivalents (FTEs), by hospital service area, Ontario, 2019–2020 to 2023–2024
A18: Fiscal year | B18: Administrative and support services | C18: Nursing inpatient services | D18: Ambulatory care services | E18: Diagnostic and therapeutic services | F18: Community health services | G18: Research, education and other services | H18: Total
A19: 2019–2020 | B19: =IFERROR(VLOOKUP(CONCATENATE($A$6,$A12,B$11,),StaffingData!$A$3:$AE$1001,21,FALSE),"—") -> 42775.802 | C19: =IFERROR(VLOOKUP(CONCATENATE($A$6,$A12,C$11,),StaffingData!$A$3:$AE$1001,21,FALSE),"—") -> 60671.689 | D19: =IFERROR(VLOOKUP(CONCATENATE($A$6,$A12,D$11,),StaffingData!$A$3:$AE$1001,21,FALSE),"—") -> 23724.704 | E19: =IFERROR(VLOOKUP(CONCATENATE($A$6,$A12,E$11,),StaffingData!$A$3:$AE$1001,21,FALSE),"—") -> 32825.041 | F19: =IFERROR(VLOOKUP(CONCATENATE($A$6,$A12,F$11,),StaffingData!$A$3:$AE$1001,21,FALSE),"—") -> 10087.373 | G19: =IFERROR(VLOOKUP(CONCATENATE($A$6,$A12,G$11,),StaffingData!$A$3:$AE$1001,21,FALSE),"—") -> 8432.3045 | H19: =IFERROR(VLOOKUP(CONCATENATE($A$6,$A12,H$11,),StaffingData!$A$3:$AE$1001,21,FALSE),"—") -> 178516.91
A20: 2020–2021 | B20: =IFERROR(VLOOKUP(CONCATENATE($A$6,$A13,B$11,),StaffingData!$A$3:$AE$1001,21,FALSE),"—") -> 47731.483 | C20: =IFERROR(VLOOKUP(CONCATENATE($A$6,$A13,C$11,),StaffingData!$A$3:$AE$1001,21,FALSE),"—") -> 63225.721 | D20: =IFERROR(VLOOKUP(CONCATENATE($A$6,$A13,D$11,),StaffingData!$A$3:$AE$1001,21,FALSE),"—") -> 23938.328 | E20: =IFERROR(VLOOKUP(CONCATENATE($A$6,$A13,E$11,),StaffingData!$A$3:$AE$1001,21,FALSE),"—") -> 33381.293 | F20: =IFERROR(VLOOKUP(CONCATENATE($A$6,$A13,F$11,),StaffingData!$A$3:$AE$1001,21,FALSE),"—") -> 12810.189 | G20: =IFERROR(VLOOKUP(CONCATENATE($A$6,$A13,G$11,),StaffingData!$A$3:$AE$1001,21,FALSE),"—") -> 8432.08 | H20: =IFERROR(VLOOKUP(CONCATENATE($A$6,$A13,H$11,),StaffingData!$A$3:$AE$1001,21,FALSE),"—") -> 189519.09
A21: 2021–2022 | B21: =IFERROR(VLOOKUP(CONCATENATE($A$6,$A14,B$11,),StaffingData!$A$3:$AE$1001,21,FALSE),"—") -> 48880.308 | C21: =IFERROR(VLOOKUP(CONCATENATE($A$6,$A14,C$11,),StaffingData!$A$3:$AE$1001,21,FALSE),"—") -> 65729.136 | D21: =IFERROR(VLOOKUP(CONCATENATE($A$6,$A14,D$11,),StaffingData!$A$3:$AE$1001,21,FALSE),"—") -> 24698.099 | E21: =IFERROR(VLOOKUP(CONCATENATE($A$6,$A14,E$11,),StaffingData!$A$3:$AE$1001,21,FALSE),"—") -> 34622.946 | F21: =IFERROR(VLOOKUP(CONCATENATE($A$6,$A14,F$11,),StaffingData!$A$3:$AE$1001,21,FALSE),"—") -> 14503.342 | G21: =IFERROR(VLOOKUP(CONCATENATE($A$6,$A14,G$11,),StaffingData!$A$3:$AE$1001,21,FALSE),"—") -> 8676.3456 | H21: =IFERROR(VLOOKUP(CONCATENATE($A$6,$A14,H$11,),StaffingData!$A$3:$AE$1001,21,FALSE),"—") -> 197110.18
A22: 2022–2023 | B22: =IFERROR(VLOOKUP(CONCATENATE($A$6,$A15,B$11,),StaffingData!$A$3:$AE$1001,21,FALSE),"—") -> 47703.48 | C22: =IFERROR(VLOOKUP(CONCATENATE($A$6,$A15,C$11,),StaffingData!$A$3:$AE$1001,21,FALSE),"—") -> 67914.896 | D22: =IFERROR(VLOOKUP(CONCATENATE($A$6,$A15,D$11,),StaffingData!$A$3:$AE$1001,21,FALSE),"—") -> 25956.443 | E22: =IFERROR(VLOOKUP(CONCATENATE($A$6,$A15,E$11,),StaffingData!$A$3:$AE$1001,21,FALSE),"—") -> 35317.841 | F22: =IFERROR(VLOOKUP(CONCATENATE($A$6,$A15,F$11,),StaffingData!$A$3:$AE$1001,21,FALSE),"—") -> 12850.036 | G22: =IFERROR(VLOOKUP(CONCATENATE($A$6,$A15,G$11,),StaffingData!$A$3:$AE$1001,21,FALSE),"—") -> 8868.8667 | H22: =IFERROR(VLOOKUP(CONCATENATE($A$6,$A15,H$11,),StaffingData!$A$3:$AE$1001,21,FALSE),"—") -> 198611.56
A23: 2023–2024 | B23: =IFERROR(VLOOKUP(CONCATENATE($A$6,$A16,B$11,),StaffingData!$A$3:$AE$1001,21,FALSE),"—") -> 48051.901 | C23: =IFERROR(VLOOKUP(CONCATENATE($A$6,$A16,C$11,),StaffingData!$A$3:$AE$1001,21,FALSE),"—") -> 71314.133 | D23: =IFERROR(VLOOKUP(CONCATENATE($A$6,$A16,D$11,),StaffingData!$A$3:$AE$1001,21,FALSE),"—") -> 27181.412 | E23: =IFERROR(VLOOKUP(CONCATENATE($A$6,$A16,E$11,),StaffingData!$A$3:$AE$1001,21,FALSE),"—") -> 36565.857 | F23: =IFERROR(VLOOKUP(CONCATENATE($A$6,$A16,F$11,),StaffingData!$A$3:$AE$1001,21,FALSE),"—") -> 12725.885 | G23: =IFERROR(VLOOKUP(CONCATENATE($A$6,$A16,G$11,),StaffingData!$A$3:$AE$1001,21,FALSE),"—") -> 9570.6018 | H23: =IFERROR(VLOOKUP(CONCATENATE($A$6,$A16,H$11,),StaffingData!$A$3:$AE$1001,21,FALSE),"—") -> 205409.79
A24: =CONCATENATE("Table 7c Worked Hours — Overtime, by hospital service area, ",A6,", 2019–2020 to 2023–2024") -> Table 7c Worked Hours — Overtime, by hospital service area, Ontario, 2019–2020 to 2023–2024
A25: Fiscal year | B25: Administrative and support services | C25: Nursing inpatient services | D25: Ambulatory care services | E25: Diagnostic and therapeutic services | F25: Community health services | G25: Research, education and other services | H25: Total
A26: 2019–2020 | B26: =IFERROR(VLOOKUP(CONCATENATE($A$6,$A26,$B$25,),StaffingData!$A$3:$AE$1001,22,FALSE),"—") -> 880436 | C26: =IFERROR(VLOOKUP(CONCATENATE($A$6,$A26,$C$11,),StaffingData!$A$3:$AE$1001,22,FALSE),"—") -> 3294832 | D26: =IFERROR(VLOOKUP(CONCATENATE($A$6,$A26,$D$11,),StaffingData!$A$3:$AE$1001,22,FALSE),"—") -> 1180075 | E26: =IFERROR(VLOOKUP(CONCATENATE($A$6,$A26,$E$11,),StaffingData!$A$3:$AE$1001,22,FALSE),"—") -> 716718 | F26: =IFERROR(VLOOKUP(CONCATENATE($A$6,$A26,$F$11,),StaffingData!$A$3:$AE$1001,22,FALSE),"—") -> 34391 | G26: =IFERROR(VLOOKUP(CONCATENATE($A$6,$A26,$G$11,),StaffingData!$A$3:$AE$1001,22,FALSE),"—") -> 79000 | H26: =IFERROR(VLOOKUP(CONCATENATE($A$6,$A26,$H$11,),StaffingData!$A$3:$AE$1001,22,FALSE),"—") -> 6185452
A27: 2020–2021 | B27: =IFERROR(VLOOKUP(CONCATENATE($A$6,$A27,$B$25,),StaffingData!$A$3:$AE$1001,22,FALSE),"—") -> 1210058 | C27: =IFERROR(VLOOKUP(CONCATENATE($A$6,$A27,$C$11,),StaffingData!$A$3:$AE$1001,22,FALSE),"—") -> 4022831 | D27: =IFERROR(VLOOKUP(CONCATENATE($A$6,$A27,$D$11,),StaffingData!$A$3:$AE$1001,22,FALSE),"—") -> 1261057 | E27: =IFERROR(VLOOKUP(CONCATENATE($A$6,$A27,$E$11,),StaffingData!$A$3:$AE$1001,22,FALSE),"—") -> 1035651 | F27: =IFERROR(VLOOKUP(CONCATENATE($A$6,$A27,$F$11,),StaffingData!$A$3:$AE$1001,22,FALSE),"—") -> 225122 | G27: =IFERROR(VLOOKUP(CONCATENATE($A$6,$A27,$G$11,),StaffingData!$A$3:$AE$1001,22,FALSE),"—") -> 51950 | H27: =IFERROR(VLOOKUP(CONCATENATE($A$6,$A27,$H$11,),StaffingData!$A$3:$AE$1001,22,FALSE),"—") -> 7806669
A28: 2021–2022 | B28: =IFERROR(VLOOKUP(CONCATENATE($A$6,$A28,$B$25,),StaffingData!$A$3:$AE$1001,22,FALSE),"—") -> 1624967 | C28: =IFERROR(VLOOKUP(CONCATENATE($A$6,$A28,$C$11,),StaffingData!$A$3:$AE$1001,22,FALSE),"—") -> 5916698 | D28: =IFERROR(VLOOKUP(CONCATENATE($A$6,$A28,$D$11,),StaffingData!$A$3:$AE$1001,22,FALSE),"—") -> 1779813 | E28: =IFERROR(VLOOKUP(CONCATENATE($A$6,$A28,$E$11,),StaffingData!$A$3:$AE$1001,22,FALSE),"—") -> 1162784 | F28: =IFERROR(VLOOKUP(CONCATENATE($A$6,$A28,$F$11,),StaffingData!$A$3:$AE$1001,22,FALSE),"—") -> 270029 | G28: =IFERROR(VLOOKUP(CONCATENATE($A$6,$A28,$G$11,),StaffingData!$A$3:$AE$1001,22,FALSE),"—") -> 86514 | H28: =IFERROR(VLOOKUP(CONCATENATE($A$6,$A28,$H$11,),StaffingData!$A$3:$AE$1001,22,FALSE),"—") -> 10840805
A29: 2022–2023 | B29: =IFERROR(VLOOKUP(CONCATENATE($A$6,$A29,$B$25,),StaffingData!$A$3:$AE$1001,22,FALSE),"—") -> 1891387 | C29: =IFERROR(VLOOKUP(CONCATENATE($A$6,$A29,$C$11,),StaffingData!$A$3:$AE$1001,22,FALSE),"—") -> 7920718 | D29: =IFERROR(VLOOKUP(CONCATENATE($A$6,$A29,$D$11,),StaffingData!$A$3:$AE$1001,22,FALSE),"—") -> 2287863 | E29: =IFERROR(VLOOKUP(CONCATENATE($A$6,$A29,$E$11,),StaffingData!$A$3:$AE$1001,22,FALSE),"—") -> 1442107 | F29: =IFERROR(VLOOKUP(CONCATENATE($A$6,$A29,$F$11,),StaffingData!$A$3:$AE$1001,22,FALSE),"—") -> 117813 | G29: =IFERROR(VLOOKUP(CONCATENATE($A$6,$A29,$G$11,),StaffingData!$A$3:$AE$1001,22,FALSE),"—") -> 91779 | H29: =IFERROR(VLOOKUP(CONCATENATE($A$6,$A29,$H$11,),StaffingData!$A$3:$AE$1001,22,FALSE),"—") -> 13751667
A30: 2023–2024 | B30: =IFERROR(VLOOKUP(CONCATENATE($A$6,$A30,$B$25,),StaffingData!$A$3:$AE$1001,22,FALSE),"—") -> 1407767 | C30: =IFERROR(VLOOKUP(CONCATENATE($A$6,$A30,$C$11,),StaffingData!$A$3:$AE$1001,22,FALSE),"—") -> 7481957 | D30: =IFERROR(VLOOKUP(CONCATENATE($A$6,$A30,$D$11,),StaffingData!$A$3:$AE$1001,22,FALSE),"—") -> 2070760 | E30: =IFERROR(VLOOKUP(CONCATENATE($A$6,$A30,$E$11,),StaffingData!$A$3:$AE$1001,22,FALSE),"—") -> 1317151 | F30: =IFERROR(VLOOKUP(CONCATENATE($A$6,$A30,$F$11,),StaffingData!$A$3:$AE$1001,22,FALSE),"—") -> 52749 | G30: =IFERROR(VLOOKUP(CONCATENATE($A$6,$A30,$G$11,),StaffingData!$A$3:$AE$1001,22,FALSE),"—") -> 81088 | H30: =IFERROR(VLOOKUP(CONCATENATE($A$6,$A30,$H$11,),StaffingData!$A$3:$AE$1001,22,FALSE),"—") -> 12411472
A31: =CONCATENATE("Table 7d Worked Hours — Regular, by hospital service area, ",A6,", 2019–2020 to 2023–2024") -> Table 7d Worked Hours — Regular, by hospital service area, Ontario, 2019–2020 to 2023–2024
A32: Fiscal year | B32: Administrative and support services | C32: Nursing inpatient services | D32: Ambulatory care services | E32: Diagnostic and therapeutic services | F32: Community health services | G32: Research, education and other services | H32: Total
A33: 2019–2020 | B33: =IFERROR(VLOOKUP(CONCATENATE($A$6,$A33,$B$11,),StaffingData!$A$3:$AE$1001,23,FALSE),"—") -> 68942950 | C33: =IFERROR(VLOOKUP(CONCATENATE($A$6,$A33,$C$11,),StaffingData!$A$3:$AE$1001,23,FALSE),"—") -> 95001652 | D33: =IFERROR(VLOOKUP(CONCATENATE($A$6,$A33,$D$11,),StaffingData!$A$3:$AE$1001,23,FALSE),"—") -> 37932927 | E33: =IFERROR(VLOOKUP(CONCATENATE($A$6,$A33,$E$11,),StaffingData!$A$3:$AE$1001,23,FALSE),"—") -> 53485873 | F33: =IFERROR(VLOOKUP(CONCATENATE($A$6,$A33,$F$11,),StaffingData!$A$3:$AE$1001,23,FALSE),"—") -> 5294941 | G33: =IFERROR(VLOOKUP(CONCATENATE($A$6,$A33,$G$11,),StaffingData!$A$3:$AE$1001,23,FALSE),"—") -> 14043156 | H33: =IFERROR(VLOOKUP(CONCATENATE($A$6,$A33,$H$11,),StaffingData!$A$3:$AE$1001,23,FALSE),"—") -> 274701499
A34: 2020–2021 | B34: =IFERROR(VLOOKUP(CONCATENATE($A$6,$A34,$B$11,),StaffingData!$A$3:$AE$1001,23,FALSE),"—") -> 77295669 | C34: =IFERROR(VLOOKUP(CONCATENATE($A$6,$A34,$C$11,),StaffingData!$A$3:$AE$1001,23,FALSE),"—") -> 97963852 | D34: =IFERROR(VLOOKUP(CONCATENATE($A$6,$A34,$D$11,),StaffingData!$A$3:$AE$1001,23,FALSE),"—") -> 38083491 | E34: =IFERROR(VLOOKUP(CONCATENATE($A$6,$A34,$E$11,),StaffingData!$A$3:$AE$1001,23,FALSE),"—") -> 53892745 | F34: =IFERROR(VLOOKUP(CONCATENATE($A$6,$A34,$F$11,),StaffingData!$A$3:$AE$1001,23,FALSE),"—") -> 10059348 | G34: =IFERROR(VLOOKUP(CONCATENATE($A$6,$A34,$G$11,),StaffingData!$A$3:$AE$1001,23,FALSE),"—") -> 13870558 | H34: =IFERROR(VLOOKUP(CONCATENATE($A$6,$A34,$H$11,),StaffingData!$A$3:$AE$1001,23,FALSE),"—") -> 291165663
A35: 2021–2022 | B35: =IFERROR(VLOOKUP(CONCATENATE($A$6,$A35,$B$11,),StaffingData!$A$3:$AE$1001,23,FALSE),"—") -> 78274284 | C35: =IFERROR(VLOOKUP(CONCATENATE($A$6,$A35,$C$11,),StaffingData!$A$3:$AE$1001,23,FALSE),"—") -> 98720894 | D35: =IFERROR(VLOOKUP(CONCATENATE($A$6,$A35,$D$11,),StaffingData!$A$3:$AE$1001,23,FALSE),"—") -> 38312591 | E35: =IFERROR(VLOOKUP(CONCATENATE($A$6,$A35,$E$11,),StaffingData!$A$3:$AE$1001,23,FALSE),"—") -> 55375644 | F35: =IFERROR(VLOOKUP(CONCATENATE($A$6,$A35,$F$11,),StaffingData!$A$3:$AE$1001,23,FALSE),"—") -> 12325785 | G35: =IFERROR(VLOOKUP(CONCATENATE($A$6,$A35,$G$11,),StaffingData!$A$3:$AE$1001,23,FALSE),"—") -> 14088087 | H35: =IFERROR(VLOOKUP(CONCATENATE($A$6,$A35,$H$11,),StaffingData!$A$3:$AE$1001,23,FALSE),"—") -> 297097285
A36: 2022–2023 | B36: =IFERROR(VLOOKUP(CONCATENATE($A$6,$A36,$B$11,),StaffingData!$A$3:$AE$1001,23,FALSE),"—") -> 75238158 | C36: =IFERROR(VLOOKUP(CONCATENATE($A$6,$A36,$C$11,),StaffingData!$A$3:$AE$1001,23,FALSE),"—") -> 99620732 | D36: =IFERROR(VLOOKUP(CONCATENATE($A$6,$A36,$D$11,),StaffingData!$A$3:$AE$1001,23,FALSE),"—") -> 39632606 | E36: =IFERROR(VLOOKUP(CONCATENATE($A$6,$A36,$E$11,),StaffingData!$A$3:$AE$1001,23,FALSE),"—") -> 55611453 | F36: =IFERROR(VLOOKUP(CONCATENATE($A$6,$A36,$F$11,),StaffingData!$A$3:$AE$1001,23,FALSE),"—") -> 8094391 | G36: =IFERROR(VLOOKUP(CONCATENATE($A$6,$A36,$G$11,),StaffingData!$A$3:$AE$1001,23,FALSE),"—") -> 14242687 | H36: =IFERROR(VLOOKUP(CONCATENATE($A$6,$A36,$H$11,),StaffingData!$A$3:$AE$1001,23,FALSE),"—") -> 292440027
A37: 2023–2024 | B37: =IFERROR(VLOOKUP(CONCATENATE($A$6,$A37,$B$11,),StaffingData!$A$3:$AE$1001,23,FALSE),"—") -> 76857131 | C37: =IFERROR(VLOOKUP(CONCATENATE($A$6,$A37,$C$11,),StaffingData!$A$3:$AE$1001,23,FALSE),"—") -> 106851754 | D37: =IFERROR(VLOOKUP(CONCATENATE($A$6,$A37,$D$11,),StaffingData!$A$3:$AE$1001,23,FALSE),"—") -> 42306753 | E37: =IFERROR(VLOOKUP(CONCATENATE($A$6,$A37,$E$11,),StaffingData!$A$3:$AE$1001,23,FALSE),"—") -> 58310666 | F37: =IFERROR(VLOOKUP(CONCATENATE($A$6,$A37,$F$11,),StaffingData!$A$3:$AE$1001,23,FALSE),"—") -> 7090201 | G37: =IFERROR(VLOOKUP(CONCATENATE($A$6,$A37,$G$11,),StaffingData!$A$3:$AE$1001,23,FALSE),"—") -> 15326695 | H37: =IFERROR(VLOOKUP(CONCATENATE($A$6,$A37,$H$11,),StaffingData!$A$3:$AE$1001,23,FALSE),"—") -> 306743200
A38: =CONCATENATE("Table 7e Worked Hours — Undifferentiated, by hospital service area, ",A6,", 2019–2020 to 2023–2024") -> Table 7e Worked Hours — Undifferentiated, by hospital service area, Ontario, 2019–2020 to 2023–2024
A39: Fiscal year | B39: Administrative and support services | C39: Nursing inpatient services | D39: Ambulatory care services | E39: Diagnostic and therapeutic services | F39: Community health services | G39: Research, education and other services | H39: Total
A40: 2019–2020 | B40: =IFERROR(VLOOKUP(CONCATENATE($A$6,$A33,B$11,),StaffingData!$A$3:$AE$1001,19,FALSE),"—") -> 1604137 | C40: =IFERROR(VLOOKUP(CONCATENATE($A$6,$A33,C$11,),StaffingData!$A$3:$AE$1001,19,FALSE),"—") -> 182480 | D40: =IFERROR(VLOOKUP(CONCATENATE($A$6,$A33,D$11,),StaffingData!$A$3:$AE$1001,19,FALSE),"—") -> 63286 | E40: =IFERROR(VLOOKUP(CONCATENATE($A$6,$A33,E$11,),StaffingData!$A$3:$AE$1001,19,FALSE),"—") -> 533967 | F40: =IFERROR(VLOOKUP(CONCATENATE($A$6,$A33,F$11,),StaffingData!$A$3:$AE$1001,19,FALSE),"—") -> 10866006 | G40: =IFERROR(VLOOKUP(CONCATENATE($A$6,$A33,G$11,),StaffingData!$A$3:$AE$1001,19,FALSE),"—") -> 450318 | H40: =IFERROR(VLOOKUP(CONCATENATE($A$6,$A33,H$11,),StaffingData!$A$3:$AE$1001,19,FALSE),"—") -> 13700194
A41: 2020–2021 | B41: =IFERROR(VLOOKUP(CONCATENATE($A$6,$A34,B$11,),StaffingData!$A$3:$AE$1001,19,FALSE),"—") -> 2033356 | C41: =IFERROR(VLOOKUP(CONCATENATE($A$6,$A34,C$11,),StaffingData!$A$3:$AE$1001,19,FALSE),"—") -> 264635 | D41: =IFERROR(VLOOKUP(CONCATENATE($A$6,$A34,D$11,),StaffingData!$A$3:$AE$1001,19,FALSE),"—") -> 69317 | E41: =IFERROR(VLOOKUP(CONCATENATE($A$6,$A34,E$11,),StaffingData!$A$3:$AE$1001,19,FALSE),"—") -> 650218 | F41: =IFERROR(VLOOKUP(CONCATENATE($A$6,$A34,F$11,),StaffingData!$A$3:$AE$1001,19,FALSE),"—") -> 11004152 | G41: =IFERROR(VLOOKUP(CONCATENATE($A$6,$A34,G$11,),StaffingData!$A$3:$AE$1001,19,FALSE),"—") -> 674651 | H41: =IFERROR(VLOOKUP(CONCATENATE($A$6,$A34,H$11,),StaffingData!$A$3:$AE$1001,19,FALSE),"—") -> 14696329
A42: 2021–2022 | B42: =IFERROR(VLOOKUP(CONCATENATE($A$6,$A35,B$11,),StaffingData!$A$3:$AE$1001,19,FALSE),"—") -> 2028006 | C42: =IFERROR(VLOOKUP(CONCATENATE($A$6,$A35,C$11,),StaffingData!$A$3:$AE$1001,19,FALSE),"—") -> 282661 | D42: =IFERROR(VLOOKUP(CONCATENATE($A$6,$A35,D$11,),StaffingData!$A$3:$AE$1001,19,FALSE),"—") -> 73644 | E42: =IFERROR(VLOOKUP(CONCATENATE($A$6,$A35,E$11,),StaffingData!$A$3:$AE$1001,19,FALSE),"—") -> 685995 | F42: =IFERROR(VLOOKUP(CONCATENATE($A$6,$A35,F$11,),StaffingData!$A$3:$AE$1001,19,FALSE),"—") -> 11391022 | G42: =IFERROR(VLOOKUP(CONCATENATE($A$6,$A35,G$11,),StaffingData!$A$3:$AE$1001,19,FALSE),"—") -> 657519 | H42: =IFERROR(VLOOKUP(CONCATENATE($A$6,$A35,H$11,),StaffingData!$A$3:$AE$1001,19,FALSE),"—") -> 15118847
A43: 2022–2023 | B43: =IFERROR(VLOOKUP(CONCATENATE($A$6,$A36,B$11,),StaffingData!$A$3:$AE$1001,19,FALSE),"—") -> 2122548 | C43: =IFERROR(VLOOKUP(CONCATENATE($A$6,$A36,C$11,),StaffingData!$A$3:$AE$1001,19,FALSE),"—") -> 274805 | D43: =IFERROR(VLOOKUP(CONCATENATE($A$6,$A36,D$11,),StaffingData!$A$3:$AE$1001,19,FALSE),"—") -> 63198 | E43: =IFERROR(VLOOKUP(CONCATENATE($A$6,$A36,E$11,),StaffingData!$A$3:$AE$1001,19,FALSE),"—") -> 629772 | F43: =IFERROR(VLOOKUP(CONCATENATE($A$6,$A36,F$11,),StaffingData!$A$3:$AE$1001,19,FALSE),"—") -> 12262177 | G43: =IFERROR(VLOOKUP(CONCATENATE($A$6,$A36,G$11,),StaffingData!$A$3:$AE$1001,19,FALSE),"—") -> 686015 | H43: =IFERROR(VLOOKUP(CONCATENATE($A$6,$A36,H$11,),StaffingData!$A$3:$AE$1001,19,FALSE),"—") -> 16038515
A44: 2023–2024 | B44: =IFERROR(VLOOKUP(CONCATENATE($A$6,$A37,B$11,),StaffingData!$A$3:$AE$1001,19,FALSE),"—") -> 2034781 | C44: =IFERROR(VLOOKUP(CONCATENATE($A$6,$A37,C$11,),StaffingData!$A$3:$AE$1001,19,FALSE),"—") -> 277370 | D44: =IFERROR(VLOOKUP(CONCATENATE($A$6,$A37,D$11,),StaffingData!$A$3:$AE$1001,19,FALSE),"—") -> 73848 | E44: =IFERROR(VLOOKUP(CONCATENATE($A$6,$A37,E$11,),StaffingData!$A$3:$AE$1001,19,FALSE),"—") -> 677716 | F44: =IFERROR(VLOOKUP(CONCATENATE($A$6,$A37,F$11,),StaffingData!$A$3:$AE$1001,19,FALSE),"—") -> 13082664 | G44: =IFERROR(VLOOKUP(CONCATENATE($A$6,$A37,G$11,),StaffingData!$A$3:$AE$1001,19,FALSE),"—") -> 882302 | H44: =IFERROR(VLOOKUP(CONCATENATE($A$6,$A37,H$11,),StaffingData!$A$3:$AE$1001,19,FALSE),"—") -> 17028681
A45: =CONCATENATE("Table 7f Purchased hours by hospital service area,* ",A6,", 2019–2020 to 2023–2024") -> Table 7f Purchased hours by hospital service area,* Ontario, 2019–2020 to 2023–2024
A46: Fiscal year | B46: Administrative and support services | C46: Nursing inpatient services | D46: Ambulatory care services | E46: Diagnostic and therapeutic services | F46: Community health services | G46: Research, education and other services | H46: Total
A47: 2019–2020 | B47: =IFERROR(VLOOKUP(CONCATENATE($A$6,$A33,B$11,),StaffingData!$A$3:$AE$1001,26,FALSE),"—") -> 166040 | C47: =IFERROR(VLOOKUP(CONCATENATE($A$6,$A33,C$11,),StaffingData!$A$3:$AE$1001,26,FALSE),"—") -> 4967 | D47: =IFERROR(VLOOKUP(CONCATENATE($A$6,$A33,D$11,),StaffingData!$A$3:$AE$1001,26,FALSE),"—") -> 3141 | E47: =IFERROR(VLOOKUP(CONCATENATE($A$6,$A33,E$11,),StaffingData!$A$3:$AE$1001,26,FALSE),"—") -> 20664 | F47: =IFERROR(VLOOKUP(CONCATENATE($A$6,$A33,F$11,),StaffingData!$A$3:$AE$1001,26,FALSE),"—") -> 769134 | G47: =IFERROR(VLOOKUP(CONCATENATE($A$6,$A33,G$11,),StaffingData!$A$3:$AE$1001,26,FALSE),"—") -> 15853 | H47: =IFERROR(VLOOKUP(CONCATENATE($A$6,$A33,H$11,),StaffingData!$A$3:$AE$1001,26,FALSE),"—") -> 979799
A48: 2020–2021 | B48: =IFERROR(VLOOKUP(CONCATENATE($A$6,$A34,B$11,),StaffingData!$A$3:$AE$1001,26,FALSE),"—") -> 185563 | C48: =IFERROR(VLOOKUP(CONCATENATE($A$6,$A34,C$11,),StaffingData!$A$3:$AE$1001,26,FALSE),"—") -> 13045 | D48: =IFERROR(VLOOKUP(CONCATENATE($A$6,$A34,D$11,),StaffingData!$A$3:$AE$1001,26,FALSE),"—") -> 1118 | E48: =IFERROR(VLOOKUP(CONCATENATE($A$6,$A34,E$11,),StaffingData!$A$3:$AE$1001,26,FALSE),"—") -> 21904 | F48: =IFERROR(VLOOKUP(CONCATENATE($A$6,$A34,F$11,),StaffingData!$A$3:$AE$1001,26,FALSE),"—") -> 616763 | G48: =IFERROR(VLOOKUP(CONCATENATE($A$6,$A34,G$11,),StaffingData!$A$3:$AE$1001,26,FALSE),"—") -> 15557 | H48: =IFERROR(VLOOKUP(CONCATENATE($A$6,$A34,H$11,),StaffingData!$A$3:$AE$1001,26,FALSE),"—") -> 853950
A49: 2021–2022 | B49: =IFERROR(VLOOKUP(CONCATENATE($A$6,$A35,B$11,),StaffingData!$A$3:$AE$1001,26,FALSE),"—") -> 193965 | C49: =IFERROR(VLOOKUP(CONCATENATE($A$6,$A35,C$11,),StaffingData!$A$3:$AE$1001,26,FALSE),"—") -> 10548 | D49: =IFERROR(VLOOKUP(CONCATENATE($A$6,$A35,D$11,),StaffingData!$A$3:$AE$1001,26,FALSE),"—") -> n/r | E49: =IFERROR(VLOOKUP(CONCATENATE($A$6,$A35,E$11,),StaffingData!$A$3:$AE$1001,26,FALSE),"—") -> 18718 | F49: =IFERROR(VLOOKUP(CONCATENATE($A$6,$A35,F$11,),StaffingData!$A$3:$AE$1001,26,FALSE),"—") -> 954594 | G49: =IFERROR(VLOOKUP(CONCATENATE($A$6,$A35,G$11,),StaffingData!$A$3:$AE$1001,26,FALSE),"—") -> 13919 | H49: =IFERROR(VLOOKUP(CONCATENATE($A$6,$A35,H$11,),StaffingData!$A$3:$AE$1001,26,FALSE),"—") -> 1191744
A50: 2022–2023 | B50: =IFERROR(VLOOKUP(CONCATENATE($A$6,$A36,B$11,),StaffingData!$A$3:$AE$1001,26,FALSE),"—") -> 194734 | C50: =IFERROR(VLOOKUP(CONCATENATE($A$6,$A36,C$11,),StaffingData!$A$3:$AE$1001,26,FALSE),"—") -> 30941 | D50: =IFERROR(VLOOKUP(CONCATENATE($A$6,$A36,D$11,),StaffingData!$A$3:$AE$1001,26,FALSE),"—") -> n/r | E50: =IFERROR(VLOOKUP(CONCATENATE($A$6,$A36,E$11,),StaffingData!$A$3:$AE$1001,26,FALSE),"—") -> 17269 | F50: =IFERROR(VLOOKUP(CONCATENATE($A$6,$A36,F$11,),StaffingData!$A$3:$AE$1001,26,FALSE),"—") -> 1036766 | G50: =IFERROR(VLOOKUP(CONCATENATE($A$6,$A36,G$11,),StaffingData!$A$3:$AE$1001,26,FALSE),"—") -> 18355 | H50: =IFERROR(VLOOKUP(CONCATENATE($A$6,$A36,H$11,),StaffingData!$A$3:$AE$1001,26,FALSE),"—") -> 1298065
A51: 2023–2024 | B51: =IFERROR(VLOOKUP(CONCATENATE($A$6,$A37,B$11,),StaffingData!$A$3:$AE$1001,26,FALSE),"—") -> 158729 | C51: =IFERROR(VLOOKUP(CONCATENATE($A$6,$A37,C$11,),StaffingData!$A$3:$AE$1001,26,FALSE),"—") -> 67678 | D51: =IFERROR(VLOOKUP(CONCATENATE($A$6,$A37,D$11,),StaffingData!$A$3:$AE$1001,26,FALSE),"—") -> n/r | E51: =IFERROR(VLOOKUP(CONCATENATE($A$6,$A37,E$11,),StaffingData!$A$3:$AE$1001,26,FALSE),"—") -> 17301 | F51: =IFERROR(VLOOKUP(CONCATENATE($A$6,$A37,F$11,),StaffingData!$A$3:$AE$1001,26,FALSE),"—") -> 1116363 | G51: =IFERROR(VLOOKUP(CONCATENATE($A$6,$A37,G$11,),StaffingData!$A$3:$AE$1001,26,FALSE),"—") -> 11653 | H51: =IFERROR(VLOOKUP(CONCATENATE($A$6,$A37,H$11,),StaffingData!$A$3:$AE$1001,26,FALSE),"—") -> 1371724
A52: =CONCATENATE("Table 7g Benefit Hours — Sick Leave by hospital service area, ",A6,", 2019–2020 to 2023–2024") -> Table 7g Benefit Hours — Sick Leave by hospital service area, Ontario, 2019–2020 to 2023–2024
A53: Fiscal year | B53: Administrative and support services | C53: Nursing inpatient services | D53: Ambulatory care services | E53: Diagnostic and therapeutic services | F53: Community health services | G53: Research, education and other services | H53: Total
A54: 2019–2020 | B54: =IFERROR(VLOOKUP(CONCATENATE($A$6,$A33,B$11,),StaffingData!$A$3:$AE$1001,27,FALSE),"—") -> 2551342 | C54: =IFERROR(VLOOKUP(CONCATENATE($A$6,$A33,C$11,),StaffingData!$A$3:$AE$1001,27,FALSE),"—") -> 5208239 | D54: =IFERROR(VLOOKUP(CONCATENATE($A$6,$A33,D$11,),StaffingData!$A$3:$AE$1001,27,FALSE),"—") -> 1639853 | E54: =IFERROR(VLOOKUP(CONCATENATE($A$6,$A33,E$11,),StaffingData!$A$3:$AE$1001,27,FALSE),"—") -> 1776870 | F54: =IFERROR(VLOOKUP(CONCATENATE($A$6,$A33,F$11,),StaffingData!$A$3:$AE$1001,27,FALSE),"—") -> 186645 | G54: =IFERROR(VLOOKUP(CONCATENATE($A$6,$A33,G$11,),StaffingData!$A$3:$AE$1001,27,FALSE),"—") -> 259900 | H54: =IFERROR(VLOOKUP(CONCATENATE($A$6,$A33,H$11,),StaffingData!$A$3:$AE$1001,27,FALSE),"—") -> 11622849
A55: 2020–2021 | B55: =IFERROR(VLOOKUP(CONCATENATE($A$6,$A34,B$11,),StaffingData!$A$3:$AE$1001,27,FALSE),"—") -> 2422943 | C55: =IFERROR(VLOOKUP(CONCATENATE($A$6,$A34,C$11,),StaffingData!$A$3:$AE$1001,27,FALSE),"—") -> 5649335 | D55: =IFERROR(VLOOKUP(CONCATENATE($A$6,$A34,D$11,),StaffingData!$A$3:$AE$1001,27,FALSE),"—") -> 1715513 | E55: =IFERROR(VLOOKUP(CONCATENATE($A$6,$A34,E$11,),StaffingData!$A$3:$AE$1001,27,FALSE),"—") -> 1766813 | F55: =IFERROR(VLOOKUP(CONCATENATE($A$6,$A34,F$11,),StaffingData!$A$3:$AE$1001,27,FALSE),"—") -> 187056 | G55: =IFERROR(VLOOKUP(CONCATENATE($A$6,$A34,G$11,),StaffingData!$A$3:$AE$1001,27,FALSE),"—") -> 220151 | H55: =IFERROR(VLOOKUP(CONCATENATE($A$6,$A34,H$11,),StaffingData!$A$3:$AE$1001,27,FALSE),"—") -> 11961811
A56: 2021–2022 | B56: =IFERROR(VLOOKUP(CONCATENATE($A$6,$A35,B$11,),StaffingData!$A$3:$AE$1001,27,FALSE),"—") -> 2914759 | C56: =IFERROR(VLOOKUP(CONCATENATE($A$6,$A35,C$11,),StaffingData!$A$3:$AE$1001,27,FALSE),"—") -> 6729056 | D56: =IFERROR(VLOOKUP(CONCATENATE($A$6,$A35,D$11,),StaffingData!$A$3:$AE$1001,27,FALSE),"—") -> 2067830 | E56: =IFERROR(VLOOKUP(CONCATENATE($A$6,$A35,E$11,),StaffingData!$A$3:$AE$1001,27,FALSE),"—") -> 2133978 | F56: =IFERROR(VLOOKUP(CONCATENATE($A$6,$A35,F$11,),StaffingData!$A$3:$AE$1001,27,FALSE),"—") -> 253916 | G56: =IFERROR(VLOOKUP(CONCATENATE($A$6,$A35,G$11,),StaffingData!$A$3:$AE$1001,27,FALSE),"—") -> 258992 | H56: =IFERROR(VLOOKUP(CONCATENATE($A$6,$A35,H$11,),StaffingData!$A$3:$AE$1001,27,FALSE),"—") -> 14358531
A57: 2022–2023 | B57: =IFERROR(VLOOKUP(CONCATENATE($A$6,$A36,B$11,),StaffingData!$A$3:$AE$1001,27,FALSE),"—") -> 3272502 | C57: =IFERROR(VLOOKUP(CONCATENATE($A$6,$A36,C$11,),StaffingData!$A$3:$AE$1001,27,FALSE),"—") -> 7440614 | D57: =IFERROR(VLOOKUP(CONCATENATE($A$6,$A36,D$11,),StaffingData!$A$3:$AE$1001,27,FALSE),"—") -> 2330025 | E57: =IFERROR(VLOOKUP(CONCATENATE($A$6,$A36,E$11,),StaffingData!$A$3:$AE$1001,27,FALSE),"—") -> 2701324 | F57: =IFERROR(VLOOKUP(CONCATENATE($A$6,$A36,F$11,),StaffingData!$A$3:$AE$1001,27,FALSE),"—") -> 290904 | G57: =IFERROR(VLOOKUP(CONCATENATE($A$6,$A36,G$11,),StaffingData!$A$3:$AE$1001,27,FALSE),"—") -> 329072 | H57: =IFERROR(VLOOKUP(CONCATENATE($A$6,$A36,H$11,),StaffingData!$A$3:$AE$1001,27,FALSE),"—") -> 16364441
A58: 2023–2024 | B58: =IFERROR(VLOOKUP(CONCATENATE($A$6,$A37,B$11,),StaffingData!$A$3:$AE$1001,27,FALSE),"—") -> 3034233 | C58: =IFERROR(VLOOKUP(CONCATENATE($A$6,$A37,C$11,),StaffingData!$A$3:$AE$1001,27,FALSE),"—") -> 6716650 | D58: =IFERROR(VLOOKUP(CONCATENATE($A$6,$A37,D$11,),StaffingData!$A$3:$AE$1001,27,FALSE),"—") -> 2127387 | E58: =IFERROR(VLOOKUP(CONCATENATE($A$6,$A37,E$11,),StaffingData!$A$3:$AE$1001,27,FALSE),"—") -> 2304986 | F58: =IFERROR(VLOOKUP(CONCATENATE($A$6,$A37,F$11,),StaffingData!$A$3:$AE$1001,27,FALSE),"—") -> 265074 | G58: =IFERROR(VLOOKUP(CONCATENATE($A$6,$A37,G$11,),StaffingData!$A$3:$AE$1001,27,FALSE),"—") -> 299057 | H58: =IFERROR(VLOOKUP(CONCATENATE($A$6,$A37,H$11,),StaffingData!$A$3:$AE$1001,27,FALSE),"—") -> 14747387
A59: Notes
A60: — Data is not available, does not exist or is suppressed due to data quality issues.
A61: * In some instances, purchased salaries are reported in the Canadian MIS Database (CMDB) without the associated hours. This may indicate under-reporting of purchased hours.
A62: † Value is suppressed due to low volumes.
A63: n/r: Data is not reported to the CMDB. As such, n/r should not be interpreted to mean there were no services, only that the hours have not been reported in the CMDB.
A64: For overtime hours as a percentage of worked hours, worked hours represents the sum of Worked Hours — Regular and Worked Hours — Overtime.
A65: Full-time equivalents (FTEs) is calculated by dividing total earned hours by the standard number of earned hours of 1 full-time staff in a year (1,950 hours; 1,957.5 hours in a leap year).
A66: Data is available for all provinces and territories except Quebec, Saskatchewan (for 2022–2023 and 2023–2024) and Nunavut.
A67: Calculated FTEs include purchased hours reported by provinces and territories, which can impact the FTE calculation.
A68: Province-/territory-specific notes
A69: Prince Edward Island: Data is under review. Purchased hours were not reported; as such, calculated FTEs may be impacted.
A70: Ontario: Most purchased hours are reported under Worked Hours — Regular. As such, overtime hours as a percentage of worked hours may be understated due to the denominator being overstated when compared with other jurisdictions.
... A78: End of worksheet (back to Table of contents)

Sheet 8 Vacancy metrics
A1: This tab provides data on health occupation vacancies. The figures and tables will populate information based on your selections. Select the occupation in cell A6 and the province/territory in cell B6. There are 2 tables on this tab. The first table begins at cell A11 and ends at cell D20. The notes and sources begin in cell A21 and end in cell A33. The second table begins at cell A35 and ends at cell C44. The notes and sources begin in cell A45 and end in cell A79. There are 4 figures located in cells A8 and A9. A link back to the Table of contents is in cell A2 and A80.
A2: Back to the Table of contents
A3: =CONCATENATE("Vacancy metrics, ",LOWER(A6),", ",TRIM(B6),", 2015 to 2023") -> Vacancy metrics, registered nurses, registered psychiatric nurses*, nursing coordinators and supervisors, Canada, 2015 to 2023
A4: Instructions: Select a National Occupational Classification and a jurisdiction from the drop-down lists in cells A6 and B6.
A5: National Occupational Classification | B5: Province/territory/Canada
A6: Registered nurses, registered psychiatric nurses*, nursing coordinators and supervisors | B6: Canada
A7: Data will change in the figures and tables below based on your selections above. Hover over the chart area to show values and categories. When a figure does not populate, it indicates that data for the selection is unavailable, does not exist or is not applicable.
A8: The information can be found in the table below.
A10: =CONCATENATE("Table 8a Vacancy metrics for ",LOWER(A6),", ",TRIM(B6),", 2015 to 2023") -> Table 8a Vacancy metrics for registered nurses, registered psychiatric nurses*, nursing coordinators and supervisors, Canada, 2015 to 2023
A11: Year | B11: =CONCATENATE(A6,", average number of vacancies in ", TRIM(B6)) -> Registered nurses, registered psychiatric nurses*, nursing coordinators and supervisors, average number of vacancies in Canada | C11: =CONCATENATE(A6,", percentage change from previous year in average number of vacancies in ", TRIM(B6)) -> Registered nurses, registered psychiatric nurses*, nursing coordinators and supervisors, percentage change from previous year in average number of vacancies in Canada | D11: =CONCATENATE(A6,", vacancies as a percentage of total vacancies for health care occupations,^ ", TRIM(B6)) -> Registered nurses, registered psychiatric nurses*, nursing coordinators and supervisors, vacancies as a percentage of total vacancies for health care occupations,^ Canada
A12: 2015 | B12: =IFERROR(VLOOKUP(CONCATENATE($A12,$B$6,$A$6),VacancyData!$A$3:$I$9009,7,FALSE),"—") -> 7125 | C12: =IFERROR(VLOOKUP(CONCATENATE($A12,$B$6,$A$6),VacancyData!$A$3:$I$9009,9,FALSE),"—") -> — | D12: =IFERROR(VLOOKUP(CONCATENATE($A12,$B$6,$A$6),VacancyData!$A$3:$I$9009,8,FALSE),"—") -> 0.238
A13: 2016 | B13: =IFERROR(VLOOKUP(CONCATENATE($A13,$B$6,$A$6),VacancyData!$A$3:$I$9009,7,FALSE),"—") -> 7585 | C13: =IFERROR(VLOOKUP(CONCATENATE($A13,$B$6,$A$6),VacancyData!$A$3:$I$9009,9,FALSE),"—") -> 0.064561404 | D13: =IFERROR(VLOOKUP(CONCATENATE($A13,$B$6,$A$6),VacancyData!$A$3:$I$9009,8,FALSE),"—") -> 0.236
A14: =1+A13 -> 2017 | B14: =IFERROR(VLOOKUP(CONCATENATE($A14,$B$6,$A$6),VacancyData!$A$3:$I$9009,7,FALSE),"—") -> 8480 | C14: =IFERROR(VLOOKUP(CONCATENATE($A14,$B$6,$A$6),VacancyData!$A$3:$I$9009,9,FALSE),"—") -> 0.11799604 | D14: =IFERROR(VLOOKUP(CONCATENATE($A14,$B$6,$A$6),VacancyData!$A$3:$I$9009,8,FALSE),"—") -> 0.215
A15: =1+A14 -> 2018 | B15: =IFERROR(VLOOKUP(CONCATENATE($A15,$B$6,$A$6),VacancyData!$A$3:$I$9009,7,FALSE),"—") -> 10880 | C15: =IFERROR(VLOOKUP(CONCATENATE($A15,$B$6,$A$6),VacancyData!$A$3:$I$9009,9,FALSE),"—") -> 0.28301887 | D15: =IFERROR(VLOOKUP(CONCATENATE($A15,$B$6,$A$6),VacancyData!$A$3:$I$9009,8,FALSE),"—") -> 0.212
A16: =1+A15 -> 2019 | B16: =IFERROR(VLOOKUP(CONCATENATE($A16,$B$6,$A$6),VacancyData!$A$3:$I$9009,7,FALSE),"—") -> 12595 | C16: =IFERROR(VLOOKUP(CONCATENATE($A16,$B$6,$A$6),VacancyData!$A$3:$I$9009,9,FALSE),"—") -> 0.15762868 | D16: =IFERROR(VLOOKUP(CONCATENATE($A16,$B$6,$A$6),VacancyData!$A$3:$I$9009,8,FALSE),"—") -> 0.223
A17: =1+A16 -> 2020 | B17: =IFERROR(VLOOKUP(CONCATENATE($A17,$B$6,$A$6),VacancyData!$A$3:$I$9009,7,FALSE),"—") -> 21635 | C17: =IFERROR(VLOOKUP(CONCATENATE($A17,$B$6,$A$6),VacancyData!$A$3:$I$9009,9,FALSE),"—") -> 0.71774514 | D17: =IFERROR(VLOOKUP(CONCATENATE($A17,$B$6,$A$6),VacancyData!$A$3:$I$9009,8,FALSE),"—") -> 0.249
A18: =1+A17 -> 2021 | B18: =IFERROR(VLOOKUP(CONCATENATE($A18,$B$6,$A$6),VacancyData!$A$3:$I$9009,7,FALSE),"—") -> 23650 | C18: =IFERROR(VLOOKUP(CONCATENATE($A18,$B$6,$A$6),VacancyData!$A$3:$I$9009,9,FALSE),"—") -> 0.093136122 | D18: =IFERROR(VLOOKUP(CONCATENATE($A18,$B$6,$A$6),VacancyData!$A$3:$I$9009,8,FALSE),"—") -> 0.222
A19: =1+A18 -> 2022 | B19: =IFERROR(VLOOKUP(CONCATENATE($A19,$B$6,$A$6),VacancyData!$A$3:$I$9009,7,FALSE),"—") -> 27960 | C19: =IFERROR(VLOOKUP(CONCATENATE($A19,$B$6,$A$6),VacancyData!$A$3:$I$9009,9,FALSE),"—") -> 0.18224101 | D19: =IFERROR(VLOOKUP(CONCATENATE($A19,$B$6,$A$6),VacancyData!$A$3:$I$9009,8,FALSE),"—") -> 0.231
A20: =1+A19 -> 2023 | B20: =IFERROR(VLOOKUP(CONCATENATE($A20,$B$6,$A$6),VacancyData!$A$3:$I$9009,7,FALSE),"—") -> 30420 | C20: =IFERROR(VLOOKUP(CONCATENATE($A20,$B$6,$A$6),VacancyData!$A$3:$I$9009,9,FALSE),"—") -> 0.087982833 | D20: =IFERROR(VLOOKUP(CONCATENATE($A20,$B$6,$A$6),VacancyData!$A$3:$I$9009,8,FALSE),"—") -> 0.256
A21: Notes
A22: — Data unavailable.
A23: F: Unreliable data.
A24: X: Suppressed to meet confidentiality requirements.
A25: * RPNs are currently regulated in the 4 Western provinces (Manitoba, Saskatchewan, Alberta, British Columbia) and the Yukon.
A26: ^ Vacancies as a percentage of total vacancies for health care occupations is calculated as the average number of vacancies among a specific occupation in a selected jurisdiction divided by the average number of vacancies among "Health care, social work, personal support and mental health" occupations within a given jurisdiction.
A27: For full notes and methodology, please refer to the tab Notes on Vacancy metrics.
A28: Data is from Statistics Canada's Job Vacancy and Wage Survey (JVWS). For more information, see the Guide to the Job Vacancy and Wage Survey.
A29: Results of the JVWS are released quarterly. Data from the last 3 quarters of 1 calendar year and from the first quarter of the next calendar year have been combined to create fiscal year estimates. For example, vacancy numbers for fiscal year 2016–2017 are an average of vacancies for 2016Q2, 2016Q3, 2016Q4 and 2017Q1.
A30: Data collection for the JVWS was suspended for the second and third quarters of 2020 due to the COVID-19 pandemic. Estimates for fiscal year 2020–2021 are based on the fourth quarter of 2020 and the first quarter of 2021 only.
A31: Data for number of job vacancies is rounded to the nearest 5. Data for proportions is rounded to the nearest 0.1.
A32: Source
A33: Statistics Canada, Job Vacancy and Wage Survey, September 13, 2023.
A34: =CONCATENATE("Table 8b Supply and workforce counts, ",LOWER(A6),", ",TRIM(B6),", 2015 to 2023") -> Table 8b Supply and workforce counts, registered nurses, registered psychiatric nurses*, nursing coordinators and supervisors, Canada, 2015 to 2023
A35: Year | B35: =CONCATENATE(A6," supply count in ", TRIM(B6)) -> Registered nurses, registered psychiatric nurses*, nursing coordinators and supervisors supply count in Canada | C35: =CONCATENATE(A6," workforce count in ", TRIM(B6)) -> Registered nurses, registered psychiatric nurses*, nursing coordinators and supervisors workforce count in Canada
A36: 2015 | B36: =IFERROR(VLOOKUP(CONCATENATE($A36,$B$6,$A$6),VacancyData!$A$3:$I$1499,5,FALSE),"—") -> 298235 | C36: =IFERROR(VLOOKUP(CONCATENATE($A36,$B$6,$A$6),VacancyData!$A$3:$I$1499,6,FALSE),"—") -> 284935
A37: 2016 | B37: =IFERROR(VLOOKUP(CONCATENATE($A37,$B$6,$A$6),VacancyData!$A$3:$I$1499,5,FALSE),"—") -> 299885 | C37: =IFERROR(VLOOKUP(CONCATENATE($A37,$B$6,$A$6),VacancyData!$A$3:$I$1499,6,FALSE),"—") -> 286529
A38: 2017 | B38: =IFERROR(VLOOKUP(CONCATENATE($A38,$B$6,$A$6),VacancyData!$A$3:$I$1499,5,FALSE),"—") -> 301692 | C38: =IFERROR(VLOOKUP(CONCATENATE($A38,$B$6,$A$6),VacancyData!$A$3:$I$1499,6,FALSE),"—") -> 286956
A39: 2018 | B39: =IFERROR(VLOOKUP(CONCATENATE($A39,$B$6,$A$6),VacancyData!$A$3:$I$1499,5,FALSE),"—") -> 303484 | C39: =IFERROR(VLOOKUP(CONCATENATE($A39,$B$6,$A$6),VacancyData!$A$3:$I$1499,6,FALSE),"—") -> 288074
A40: 2019 | B40: =IFERROR(VLOOKUP(CONCATENATE($A40,$B$6,$A$6),VacancyData!$A$3:$I$1499,5,FALSE),"—") -> 306730 | C40: =IFERROR(VLOOKUP(CONCATENATE($A40,$B$6,$A$6),VacancyData!$A$3:$I$1499,6,FALSE),"—") -> 279285
A41: 2020 | B41: =IFERROR(VLOOKUP(CONCATENATE($A41,$B$6,$A$6),VacancyData!$A$3:$I$1499,5,FALSE),"—") -> 310922 | C41: =IFERROR(VLOOKUP(CONCATENATE($A41,$B$6,$A$6),VacancyData!$A$3:$I$1499,6,FALSE),"—") -> 281454
A42: 2021 | B42: =IFERROR(VLOOKUP(CONCATENATE($A42,$B$6,$A$6),VacancyData!$A$3:$I$1499,5,FALSE),"—") -> 318719 | C42: =IFERROR(VLOOKUP(CONCATENATE($A42,$B$6,$A$6),VacancyData!$A$3:$I$1499,6,FALSE),"—") -> 286135
A43: 2022 | B43: =IFERROR(VLOOKUP(CONCATENATE($A43,$B$6,$A$6),VacancyData!$A$3:$I$1499,5,FALSE),"—") -> 322226 | C43: =IFERROR(VLOOKUP(CONCATENATE($A43,$B$6,$A$6),VacancyData!$A$3:$I$1499,6,FALSE),"—") -> 289260
A44: 2023 | B44: =IFERROR(VLOOKUP(CONCATENATE($A44,$B$6,$A$6),VacancyData!$A$3:$I$1499,5,FALSE),"—") -> 328696 | C44: =IFERROR(VLOOKUP(CONCATENATE($A44,$B$6,$A$6),VacancyData!$A$3:$I$9009,6,FALSE),"—") -> 296009
A45: Notes
A46: — Data is not applicable, does not exist or is not reported due to data quality issues.
A47: * RPNs are currently regulated in the 4 Western provinces (Manitoba, Saskatchewan, Alberta, British Columbia) and the Yukon.
A48: For some data years, data is not available for all provinces and territories and is therefore not included in Canada totals.
A49: Supply refers to all professionals who are eligible to practise in the given year (including those employed and those not employed at the time of registration). Note that secondary registrants (also known as interprovincial duplicates) are excluded from the supply. For regulated nurses, secondary registrants in the territories are not removed.
A50: Workforce refers to only those professionals who were employed at the time of annual registration.
A51: For more data on the supply and workforce of health care professionals in Canada, refer to professional-specific data tables.
A52: For more information regarding collection and comparability of data as well as notes specific to individual provinces and territories, refer to professional-specific methodology notes.
A53: Professional-specific notes
A54: Nurse practitioners (NPs) and registered nurses (RNs)
A55: For both NPs and RNs, supply data is reported collectively for the Northwest Territories and Nunavut and is therefore not available when selecting either Northwest Territories or Nunavut.
A56: Workforce data for NPs and RNs in Manitoba for 2019 to 2023 has been suppressed due to significant under-coverage as a result of voluntary reporting. The corresponding information for 2015 to 2018 should be used with caution, as it was also reported voluntarily and may also be understated.
... A80: End of worksheet (back to Table of contents)

Sheet Notes to readers
A1: Notes to readers
A2: Summary
A3: This Quick Stats file is an interactive tool to visually compare the supply, workforce, inflow/outflow and provincial and territorial trends of Canada’s health workforce by profession, as well as vacancies and selected hospital staffing indicators.
A4: Health care professionals
A5: There are 4 groups of regulated nursing professionals in Canada. Occupational therapists, pharmacists and physiotherapists are also regulated professionals in Canada. Physicians and surgeons must obtain certification from either the College of Family Physicians of Canada (CFPC) or the Royal College of Physicians and Surgeons of Canada (RCPSC) and/or the Collège des médecins du Québec (CMQ), as well as become members of the provincial or territorial medical professional regulatory authority in order to practise in the provinces and territories. Each province and territory has its own legislation governing the practice for each profession, as well as its own body that regulates and licenses its members.
A6: Definitions of these health care professionals are as follows:
A7: Nurse practitioners (NPs) are advanced practice nurses who integrate clinical skills associated with nursing and medicine in order to assess, diagnose and manage patients in primary health care settings and acute care populations as well as ongoing care for populations with chronic illness.
A8: Registered nurses (RNs) are health care professionals who work both autonomously and in collaboration with others to enable individuals, families, groups, communities and populations to achieve their optimal levels of health. RNs deliver direct health care services to those at all stages of life and in situations of health, illness, injury and disability; they also coordinate care and support clients in managing their own health. RNs contribute to the health care system through their leadership across a wide range of settings.
A9: Registered psychiatric nurses (RPNs) are health care professionals who work both autonomously and in collaboration with clients and other health care team members to coordinate health care and provide client-centred services to individuals, families, groups and communities. RPNs focus on mental and developmental health, mental illness and addictions, while integrating physical health and utilizing bio-psycho-social and spiritual models for a holistic approach to care.
A10: RPNs are currently regulated in the 4 western provinces (Manitoba, Saskatchewan, Alberta and British Columbia) and the Yukon. Note: RPNs are educated and trained independently of the registered nursing class.
A11: Licensed practical nurses (LPNs) are health care professionals who work independently or in collaboration with other members of a health care team. LPNs assess clients and work in health promotion and illness prevention. LPNs are currently regulated in all 13 provinces and territories. Note: In Ontario, these nurses are called registered practical nurses. For the purposes of CIHI reporting, and to maintain continuity between provinces and territories, they are referred to as LPNs.
A12: Occupational therapists (OTs) are regulated health professionals who promote health, well-being and quality of life by enabling individuals, families, organizations and communities to participate in occupations that give meaning and purpose to their lives. Occupational therapy is a type of health care that helps to solve the problems that interfere with a person’s ability to do the things that are important to them — everyday things such as caring for themselves, being productive and enjoying leisure activities. OTs contribute to the productivity of Canadians through client-centred care.
... A17: End of worksheet (back to Table of contents)

Sheet Terminology
A1: Terminology
A2: Throughout this Quick Stats file,
A3: • Nursing refers collectively to Canada’s 4 regulated nursing professions, unless otherwise specified.
A4: • Supply refers to all professionals who are eligible to practise in the given year (including those employed and those not employed at the time of registration). Note that secondary registrants (also known as interprovincial duplicates) are excluded from the supply. For regulated nurses, secondary registrants in the territories are not removed.
A5: • Workforce refers to only those professionals who were employed at the time of annual registration. Note: The distinction between the terms supply and workforce is not applicable for physicians. In Scott's Medical Database, the count of physicians includes active physicians in clinical and non-clinical practice (e.g., research, academia) who have an MD degree and a valid mailing address. It excludes residents, physicians in the military, semi-retired and retired physicians as well as physicians who requested that their information not be published as of December 31 of the reference year. See Supply, Distribution and Migration of Physicians in Canada — Methodology Notes for details.
